Workbook
Name UPDATE: '[1]Data Sheet'!$E$1
Name UPDATE: '[2]Data Sheet'!$E$1

Sheet Intro
F6: Financial Modeling & Valuation Report
J13: Prepared By
J14: Shivalika Singh

Sheet Table of Contents
B5: Table of Contents
B10: 1. One Page Profile
B11: 2. Historical Financial Statement
B12: 3. Forecasting
B13: 4. Ratio Analysis
B14: 5. Common Size Statement
B15: 6. Reggretion Beta
B16: 7. WACC
B17: 8. Relative Valuation
B18: 9. DCF
B19: 10. VAR
B20: 11. Dupont Analysis
B21: 12. Altman's Z Score

Sheet one page profile
B2: ='[1]Data Sheet'!B1&" - One Page Profile" -> BAJAJ AUTO LTD - One Page Profile
C4: Bajaj Auto, the flagship company of Bajaj Group, is a two-wheeler and three-wheeler manufacturing company that exports to 79 countries across several countries in Latin America, Southeast Asia, and many more. Its headquarter is in Pune, India. It has acquired 48% of the KTM Brand which manufactures sports and super sports two-wheelers, which was 14% in 2007 when the company first acquired KTM.
B6: (INR)crs.
B9: Key Financial Metrics | C9: ='[1]Data Sheet'!C16 -> 42825 | D9: ='[1]Data Sheet'!D16 -> 43190 | E9: ='[1]Data Sheet'!E16 -> 43555 | F9: ='[1]Data Sheet'!F16 -> 43921 | G9: ='[1]Data Sheet'!G16 -> 44286 | H9: ='[1]Data Sheet'!H16 -> 44651 | I9: ='[1]Data Sheet'!I16 -> 45016 | J9: ='[1]Data Sheet'!J16 -> 45382 | K9: ='[1]Data Sheet'!K16 -> 45747 | M9: Capital Structure
B11: Total Sales | C11: ='[1]Data Sheet'!C17 -> 21754.72 | D11: ='[1]Data Sheet'!D17 -> 25209.93 | E11: ='[1]Data Sheet'!E17 -> 30357.63 | F11: ='[1]Data Sheet'!F17 -> 29918.65 | G11: ='[1]Data Sheet'!G17 -> 27741.08 | H11: ='[1]Data Sheet'!H17 -> 33144.71 | I11: ='[1]Data Sheet'!I17 -> 36455.38 | J11: ='[1]Data Sheet'!J17 -> 44870.43 | K11: ='[1]Data Sheet'!K17 -> 50994.55 | M11: Share Price as on XXX | Q11: ='[1]Data Sheet'!B8 -> 9164
B12: Sales Growth (y-o-y) | C12: ='[1]Data Sheet'!C34 -> -0.036279846 | D12: ='[1]Data Sheet'!D34 -> 0.15882576 | E12: ='[1]Data Sheet'!E34 -> 0.20419335 | F12: ='[1]Data Sheet'!F34 -> -0.014460286 | G12: ='[1]Data Sheet'!G34 -> -0.07278303 | H12: ='[1]Data Sheet'!H34 -> 0.19478802 | I12: ='[1]Data Sheet'!I34 -> 0.099885321 | J12: ='[1]Data Sheet'!J34 -> 0.2308315 | K12: ='[1]Data Sheet'!K34 -> 0.13648454 | M12: Numer of Shares O/S | Q12: ='[1]Data Sheet'!B6 -> 27.931626
B13: Gross Profit Margins (%) | C13: ='[1]Data Sheet'!C36 -> 0.2481935 | D13: ='[1]Data Sheet'!D36 -> 0.24181701 | E13: ='[1]Data Sheet'!E36 -> 0.21206497 | F13: ='[1]Data Sheet'!F36 -> 0.21972749 | G13: ='[1]Data Sheet'!G36 -> 0.20575803 | H13: ='[1]Data Sheet'!H36 -> 0.20759029 | I13: ='[1]Data Sheet'!I36 -> 0.21339018 | J13: ='[1]Data Sheet'!J36 -> 0.229797 | K13: ='[1]Data Sheet'!K36 -> 0.25236716
B14: EBITDA Margins (%) | C14: ='[1]Data Sheet'!C38 -> 0.19955531 | D14: ='[1]Data Sheet'!D38 -> 0.19298586 | E14: ='[1]Data Sheet'!E38 -> 0.16750583 | F14: ='[1]Data Sheet'!F38 -> 0.16656233 | G14: ='[1]Data Sheet'!G38 -> 0.16217177 | H14: ='[1]Data Sheet'!H38 -> 0.1700036 | I14: ='[1]Data Sheet'!I38 -> 0.17182594 | J14: ='[1]Data Sheet'!J38 -> 0.19193041 | K14: ='[1]Data Sheet'!K38 -> 0.18847936 | M14: Market Capitalization | Q14: =Q11*Q12 -> 255965.42
B15: EBIT Margins (%) | C15: ='[1]Data Sheet'!C40 -> 0.1854301 | D15: ='[1]Data Sheet'!D40 -> 0.18049872 | E15: ='[1]Data Sheet'!E40 -> 0.15875383 | F15: ='[1]Data Sheet'!F40 -> 0.15832566 | G15: ='[1]Data Sheet'!G40 -> 0.1528221 | H15: ='[1]Data Sheet'!H40 -> 0.16186474 | I15: ='[1]Data Sheet'!I40 -> 0.16398485 | J15: ='[1]Data Sheet'!J40 -> 0.183801 | K15: ='[1]Data Sheet'!K40 -> 0.18035633 | M15: Less: Cash & Equivalents | Q15: ='[1]Data Sheet'!K81*-1 -> -2847.6
B16: Net Profit Margins (%) | C16: ='[1]Data Sheet'!C44 -> 0.11604424 | D16: ='[1]Data Sheet'!D44 -> 0.11243903 | E16: ='[1]Data Sheet'!E44 -> 0.09180328 | F16: ='[1]Data Sheet'!F44 -> 0.10874521 | G16: ='[1]Data Sheet'!G44 -> 0.10267733 | H16: ='[1]Data Sheet'!H44 -> 0.1167755 | I16: ='[1]Data Sheet'!I44 -> 0.11402569 | J16: ='[1]Data Sheet'!J44 -> 0.13048839 | K16: ='[1]Data Sheet'!K44 -> 0.11588474 | M16: Add: Total Debt | Q16: ='[1]Data Sheet'!K71 -> 9364.16
B17: Earnings Per Share (in Rs) | C17: ='[1]Data Sheet'!C45 -> 87.23255 | D17: ='[1]Data Sheet'!D45 -> 97.946786 | E17: ='[1]Data Sheet'!E45 -> 96.300276 | F17: ='[1]Data Sheet'!F45 -> 112.4226 | G17: ='[1]Data Sheet'!G45 -> 98.423635 | H17: ='[1]Data Sheet'!H45 -> 133.74188 | I17: ='[1]Data Sheet'!I45 -> 146.88516 | J17: ='[1]Data Sheet'!J45 -> 209.70881 | K17: ='[1]Data Sheet'!K45 -> 211.58217
B18: EPS Growth (y-o-y) | C18: ='[1]Data Sheet'!C46 -> -0.15680747 | D18: ='[1]Data Sheet'!D46 -> 0.12282384 | E18: ='[1]Data Sheet'!E46 -> -0.016810251 | F18: ='[1]Data Sheet'!F46 -> 0.16741719 | G18: ='[1]Data Sheet'!G46 -> -0.1245209 | H18: ='[1]Data Sheet'!H46 -> 0.35883906 | I18: ='[1]Data Sheet'!I46 -> 0.098273475 | J18: ='[1]Data Sheet'!J46 -> 0.42770592 | K18: ='[1]Data Sheet'!K46 -> 0.0089331431
B19: Dividend Per Share (in Rs) | C19: ='[1]Data Sheet'!C47 -> 54.994471 | D19: ='[1]Data Sheet'!D47 -> 59.99378 | E19: ='[1]Data Sheet'!E47 -> 59.99378 | F19: ='[1]Data Sheet'!F47 -> 119.98756 | G19: ='[1]Data Sheet'!G47 -> 139.98549 | H19: ='[1]Data Sheet'!H47 -> 139.98549 | I19: ='[1]Data Sheet'!I47 -> 139.98021 | J19: ='[1]Data Sheet'!J47 -> 79.994269 | K19: ='[1]Data Sheet'!K47 -> 209.96992 | M19: Enterprise Value | Q19: =SUM(Q14:Q16) -> 262481.98
B20: DPS Growth (y-o-y) | C20: ='[1]Data Sheet'!C48 -> 0 | D20: ='[1]Data Sheet'!D48 -> 0.090905664 | E20: ='[1]Data Sheet'!E48 -> 0 | F20: ='[1]Data Sheet'!F48 -> 1 | G20: ='[1]Data Sheet'!G48 -> 0.16666667 | H20: ='[1]Data Sheet'!H48 -> 0 | I20: ='[1]Data Sheet'!I48 -> -3.7683912e-05 | J20: ='[1]Data Sheet'!J48 -> -0.42853159 | K20: ='[1]Data Sheet'!K48 -> 1.6248121
B22: Key Financial Ratios | C22: =C9 -> 42825 | D22: =D9 -> 43190 | E22: =E9 -> 43555 | F22: =F9 -> 43921 | G22: =G9 -> 44286 | H22: =H9 -> 44651 | I22: =I9 -> 45016 | J22: =J9 -> 45382 | K22: =K9 -> 45747 | M22: Recent Updates
B24: Price to Earnings | C24: ='[1]Data Sheet'!C95 -> 32.160587 | D24: ='[1]Data Sheet'!D95 -> 28.022359 | E24: ='[1]Data Sheet'!E95 -> 30.229404 | F24: ='[1]Data Sheet'!F95 -> 17.988821 | G24: ='[1]Data Sheet'!G95 -> 37.293888 | H24: ='[1]Data Sheet'!H95 -> 27.313808 | I24: ='[1]Data Sheet'!I95 -> 26.447532 | J24: ='[1]Data Sheet'!J95 -> 43.623107 | K24: ='[1]Data Sheet'!K95 -> 37.237779 | M24: • Bajaj Auto reported a 23.7% rise in Q2 (quarter ended Sept 30, 2025) profit, driven largely by strong exports of motorcycles even though domestic demand remained sluggish.
B25: EV/EBITDA | C25: ='[1]Data Sheet'!C90 -> 19.503374 | D25: ='[1]Data Sheet'!D90 -> 17.132986 | E25: ='[1]Data Sheet'!E90 -> 17.485421 | F25: ='[1]Data Sheet'!F90 -> 12.653895 | G25: ='[1]Data Sheet'!G90 -> 24.899108 | H25: ='[1]Data Sheet'!H90 -> 19.523831 | I25: ='[1]Data Sheet'!I90 -> 18.362583 | J25: ='[1]Data Sheet'!J90 -> 30.752706 | K25: ='[1]Data Sheet'!K90 -> 24.567635
B26: EV/Sales | C26: ='[1]Data Sheet'!C91 -> 3.892002 | D26: ='[1]Data Sheet'!D91 -> 3.306424 | E26: ='[1]Data Sheet'!E91 -> 2.9289099 | F26: ='[1]Data Sheet'!F91 -> 2.1076622 | G26: ='[1]Data Sheet'!G91 -> 4.0379323 | H26: ='[1]Data Sheet'!H91 -> 3.3191215 | I26: ='[1]Data Sheet'!I91 -> 3.1551682 | J26: ='[1]Data Sheet'!J91 -> 5.9023795 | K26: ='[1]Data Sheet'!K91 -> 4.6304921
B27: Price to Book Value | C27: ='[1]Data Sheet'!C93 -> 4.5467703 | D27: ='[1]Data Sheet'!D93 -> 3.8888952 | E27: ='[1]Data Sheet'!E93 -> 3.6260619 | F27: ='[1]Data Sheet'!F93 -> 2.7018093 | G27: ='[1]Data Sheet'!G93 -> 3.8948957 | H27: ='[1]Data Sheet'!H93 -> 3.5404909 | I27: ='[1]Data Sheet'!I93 -> 3.7443004 | J27: ='[1]Data Sheet'!J93 -> 8.8188914 | K27: ='[1]Data Sheet'!K93 -> 6.2535993
B28: Return on Equity(%) | C28: ='[1]Data Sheet'!C94 -> 0.1413771 | D28: ='[1]Data Sheet'!D94 -> 0.1387783 | E28: ='[1]Data Sheet'!E94 -> 0.11995148 | F28: ='[1]Data Sheet'!F94 -> 0.15019379 | G28: ='[1]Data Sheet'!G94 -> 0.10443791 | H28: ='[1]Data Sheet'!H94 -> 0.12962275 | I28: ='[1]Data Sheet'!I94 -> 0.14157466 | J28: ='[1]Data Sheet'!J94 -> 0.20216101 | K28: ='[1]Data Sheet'!K94 -> 0.16793696 | M28: • The company has completed acquisition of a majority stake in Austrian motorcycle maker KTM — through restructuring of its European holding — giving Bajaj full controlling interest in global KTM business.
B29: Return on Capital Employed (%) | C29: ='[3]Ratio Analysis'!$C$29 -> 0.22440335 | D29: ='[3]Ratio Analysis'!$C$29 -> 0.22440335 | E29: ='[3]Ratio Analysis'!$C$29 -> 0.22440335 | F29: ='[3]Ratio Analysis'!$C$29 -> 0.22440335 | G29: ='[3]Ratio Analysis'!$C$29 -> 0.22440335 | H29: ='[3]Ratio Analysis'!$C$29 -> 0.22440335 | I29: ='[3]Ratio Analysis'!$C$29 -> 0.22440335 | J29: ='[3]Ratio Analysis'!$C$29 -> 0.22440335 | K29: ='[3]Ratio Analysis'!$C$29 -> 0.22440335
B31: Top 10 Shareholders | F31: ='[1]Input Sheet'!C3 -> N. Shares (in Crs.) | H31: Shareholding (%) | J31: Market Value (in Crs.)
B33: ='[1]Input Sheet'!B15 -> Bajaj Holdings And Investment Limited | G33: ='[1]Input Sheet'!C4 -> 9.5547251 | I33: ='[1]Input Sheet'!D4 -> 0.3421 | K33: ='[1]Input Sheet'!E4 -> 86412.934 | M33: • Bajaj Auto has entered the electric-rickshaw (e-rickshaw) segment with launch of its new model Bajaj Riki featuring ~149 km range on single charge.
B34: ='[1]Input Sheet'!B16 -> Jamnalal Sons Pvt Limited | G34: ='[1]Input Sheet'!C5 -> 2.5960841 | I34: ='[1]Input Sheet'!D5 -> 0.093 | K34: ='[1]Input Sheet'!E5 -> 23478.985
B35: ='[1]Input Sheet'!B17 -> Lici Ulip-Growth Fund | G35: ='[1]Input Sheet'!C6 -> 1.0022378 | I35: ='[1]Input Sheet'!D6 -> 0.0359 | K35: ='[1]Input Sheet'!E6 -> 9064.2387
B36: ='[1]Input Sheet'!B18 -> Jaya Hind Industries Private Limited | G36: ='[1]Input Sheet'!C7 -> 0.993166 | I36: ='[1]Input Sheet'!D7 -> 0.0356 | K36: ='[1]Input Sheet'!E7 -> 8982.1933
B37: ='[1]Input Sheet'!B19 -> Maharashtra Scooters Limited | G37: ='[1]Input Sheet'!C8 -> 0.6879333 | I37: ='[1]Input Sheet'!D8 -> 0.0246 | K37: ='[1]Input Sheet'!E8 -> 6221.6688 | M37: • The company plans to expand “Riki” e-rickshaw rollout to 200 cities by Q1 2026, up from the current pilot in a handful of cities — signalling a push into last-mile urban mobility nationwide.
B38: ='[1]Input Sheet'!B20 -> Hdfc Mutual Fund - Hdfc Business Cycle Fund | G38: ='[1]Input Sheet'!C9 -> 0.6214942 | I38: ='[1]Input Sheet'!D9 -> 0.0223 | K38: ='[1]Input Sheet'!E9 -> 5620.7935
B39: ='[1]Input Sheet'!B21 -> Bajaj Sevashram Pvt Limited | G39: ='[1]Input Sheet'!C10 -> 0.4408288 | I39: ='[1]Input Sheet'!D10 -> 0.0158 | K39: ='[1]Input Sheet'!E10 -> 3986.8557
B40: ='[1]Input Sheet'!B22 -> Bachhraj And Company Pvt Limited | G40: ='[1]Input Sheet'!C11 -> 0.3646362 | I40: ='[1]Input Sheet'!D11 -> 0.0131 | K40: ='[1]Input Sheet'!E11 -> 3297.7698
B41: ='[1]Input Sheet'!B23 -> Yamuna Trust | G41: ='[1]Input Sheet'!C12 -> 0.3615269 | I41: ='[1]Input Sheet'!D12 -> 0.0129 | K41: ='[1]Input Sheet'!E12 -> 3269.6493 | M41: • On 27 Nov 2025, some brokerage analysts (e.g. from Anand Rathi) flagged Bajaj Auto shares as a “top buy” — citing bullish technical signals (like RSI divergences, engulfing patterns) for short-term gains.
B42: ='[1]Input Sheet'!B24 -> Sbi Consumption Opportunities Fund | G42: ='[1]Input Sheet'!C13 -> 0.2988761 | I42: ='[1]Input Sheet'!D13 -> 0.0107 | K42: ='[1]Input Sheet'!E13 -> 2703.0354
B44: Managerial Remuneration | F44: Designation | H44: Remunration | J44: X of Median sallary
B46: Mr. Rajiv Bajaj | F46: MD & CEO | H46: =585824725/10000000 -> 58.582473 | J46: 575.47 | M46: • In the same session, the broader auto index saw profit-booking after reaching record highs — and Bajaj Auto was among the leading losers of the day (alongside peers), showing current volatility in the stock.
B47: Mr. Pradeep Shrivastva | F47: ED | H47: =283317842/10000000 -> 28.331784 | J47: 278.31
B48: Mr. Rakesh Sharma | F48: ED | H48: =168130754/10000000 -> 16.813075 | J48: 165.16
B50: Notes:
B51: Pradeep Shrivastava and Rakesh Sharma, the executive directors of the Company are entitled to employee stock options as per Bajaj Auto Employee Stock Option Scheme 2019, as amended. The above remuneration is exclusive of fair value of options granted as per Black Scholes model in the year of vesting. | M51: Sources:
M52: Screener.in, Yahoo Finance, Bajaj Auto LTD Annual Report 2025, NSE India, Wikipedia.
B55: ='[1]Data Sheet'!B54&" - One Page Profile" -> 10311.91 - One Page Profile | C55: ='[1]Data Sheet'!C54&" - One Page Profile" -> 10838.24 - One Page Profile | D55: ='[1]Data Sheet'!D54&" - One Page Profile" -> 12165.33 - One Page Profile | E55: ='[1]Data Sheet'!E54&" - One Page Profile" -> 11554.95 - One Page Profile | F55: ='[1]Data Sheet'!F54&" - One Page Profile" -> 11932.07 - One Page Profile | G55: ='[1]Data Sheet'!G54&" - One Page Profile" -> 13247.28 - One Page Profile | H55: ='[1]Data Sheet'!H54&" - One Page Profile" -> 13168.88 - One Page Profile | I55: ='[1]Data Sheet'!I54&" - One Page Profile" -> 12646.32 - One Page Profile | ... Q55: ='[1]Data Sheet'!Q54&" - One Page Profile" -> - One Page Profile

Sheet Historical FS
B2: Return on Equity(ROE) | C2: Return on Equity(ROE) | D2: Return on Equity(ROE) | E2: Return on Equity(ROE) | F2: Return on Equity(ROE) | G2: Return on Equity(ROE) | H2: Return on Equity(ROE) | I2: Return on Equity(ROE) | L2: Return on Equity(ROE)
B4: ='[2]Data Sheet'!B1 -> BAJAJ AUTO LTD
B5: =CONCATENATE(" ",VLOOKUP(B4,'[2]LIST OF STOCKS'!B5:D5444,3,FALSE)," | ","Bse Code: ",VLOOKUP(B4,'[2]LIST OF STOCKS'!B5:E5444,2,FALSE),) -> BAJAJ-AUTO | Bse Code: 532977
B6: INR (Crs.)
B8: ="Historical Financial Statement - "&'[2]Balance Sheet'!A1 -> Historical Financial Statement - BAJAJ AUTO LTD
B9: Years | C9: =IFERROR('[2]Data Sheet'!C16,0) -> 42825 | D9: =IFERROR('[2]Data Sheet'!D16,0) -> 43190 | E9: =IFERROR('[2]Data Sheet'!E16,0) -> 43555 | F9: =IFERROR('[2]Data Sheet'!F16,0) -> 43921 | G9: =IFERROR('[2]Data Sheet'!G16,0) -> 44286 | H9: =IFERROR('[2]Data Sheet'!H16,0) -> 44651 | I9: =IFERROR('[2]Data Sheet'!I16,0) -> 45016 | J9: =IFERROR('[2]Data Sheet'!J16,0) -> 45382 | K9: =IFERROR('[2]Data Sheet'!K16,0) -> 45747 | L9: LTM
B11: Income Statement
B13: Sales | C13: ='[2]Data Sheet'!C17 -> 21754.72 | D13: ='[2]Data Sheet'!D17 -> 25209.93 | E13: ='[2]Data Sheet'!E17 -> 30357.63 | F13: ='[2]Data Sheet'!F17 -> 29918.65 | G13: ='[2]Data Sheet'!G17 -> 27741.08 | H13: ='[2]Data Sheet'!H17 -> 33144.71 | I13: ='[2]Data Sheet'!I17 -> 36455.38 | J13: ='[2]Data Sheet'!J17 -> 44870.43 | K13: ='[2]Data Sheet'!K17 -> 50994.55 | L13: =IFERROR(SUM('[2]Data Sheet'!H42:K42),0) -> 54683.29
A14: # | B14: Sales Growth | C14: - | D14: =IFERROR(D13/C13-1,0) -> 0.15882576 | E14: =IFERROR(E13/D13-1,0) -> 0.20419335 | F14: =IFERROR(F13/E13-1,0) -> -0.014460286 | G14: =IFERROR(G13/F13-1,0) -> -0.07278303 | H14: =IFERROR(H13/G13-1,0) -> 0.19478802 | I14: =IFERROR(I13/H13-1,0) -> 0.099885321 | J14: =IFERROR(J13/I13-1,0) -> 0.2308315 | K14: =IFERROR(K13/J13-1,0) -> 0.13648454 | L14: =IFERROR(L13/I13-1,0) -> 0.50000603
B16: COGS | C16: =SUM('[2]Data Sheet'!C18:C22) -> 16355.34 | D16: =SUM('[2]Data Sheet'!D18:D22) -> 19113.74 | E16: =SUM('[2]Data Sheet'!E18:E22) -> 23919.84 | F16: =SUM('[2]Data Sheet'!F18:F22) -> 23344.7 | G16: =SUM('[2]Data Sheet'!G18:G22) -> 22033.13 | H16: =SUM('[2]Data Sheet'!H18:H22) -> 26264.19 | I16: =SUM('[2]Data Sheet'!I18:I22) -> 28676.16 | J16: =SUM('[2]Data Sheet'!J18:J22) -> 34559.34 | K16: =SUM('[2]Data Sheet'!K18:K22) -> 38125.2 | L16: =IFERROR(SUM('[2]Data Sheet'!J18:J22)-'[2]Data Sheet'!J19,0) -> 34483
B17: COGS % Sales | C17: =C16/C13 -> 0.7518065 | D17: =D16/D13 -> 0.75818299 | E17: =E16/E13 -> 0.78793503 | F17: =F16/F13 -> 0.78027251 | G17: =G16/G13 -> 0.79424197 | H17: =H16/H13 -> 0.79240971 | I17: =I16/I13 -> 0.78660982 | L17: =L16/L13 -> 0.63059483
B19: Gross Profit | C19: =C13-C16 -> 5399.38 | D19: =D13-D16 -> 6096.19 | E19: =E13-E16 -> 6437.79 | F19: =F13-F16 -> 6573.95 | G19: =G13-G16 -> 5707.95 | H19: =H13-H16 -> 6880.52 | I19: =I13-I16 -> 7779.22 | J19: =J13-J16 -> 10311.09 | ... L19: =L13-L16 -> 20200.29
B20: Gross Margins | C20: =C19/C13 -> 0.2481935 | D20: =D19/D13 -> 0.24181701 | E20: =E19/E13 -> 0.21206497 | F20: =F19/F13 -> 0.21972749 | G20: =G19/G13 -> 0.20575803 | H20: =H19/H13 -> 0.20759029 | I20: =I19/I13 -> 0.21339018 | J20: =J19/J13 -> 0.229797 | ... L20: =L19/L13 -> 0.36940517
B22: Selling & General expenses | C22: =IFERROR(SUM('[2]Data Sheet'!C23:C24),0) -> 1058.11 | D22: =IFERROR(SUM('[2]Data Sheet'!D23:D24),0) -> 1231.03 | E22: =IFERROR(SUM('[2]Data Sheet'!E23:E24),0) -> 1352.71 | F22: =IFERROR(SUM('[2]Data Sheet'!F23:F24),0) -> 1590.63 | G22: =IFERROR(SUM('[2]Data Sheet'!G23:G24),0) -> 1209.13 | H22: =IFERROR(SUM('[2]Data Sheet'!H23:H24),0) -> 1245.8 | I22: =IFERROR(SUM('[2]Data Sheet'!I23:I24),0) -> 1515.24 | J22: =IFERROR(SUM('[2]Data Sheet'!J23:J24),0) -> 1699.09 | K22: =IFERROR(SUM('[2]Data Sheet'!K23:K24),0) -> 3257.93
B23: S&G Exp % Sales | C23: =C22/C13 -> 0.048638181 | D23: =D22/D13 -> 0.048831155 | E23: =E22/E13 -> 0.044559144 | F23: =F22/F13 -> 0.053165166 | G23: =G22/G13 -> 0.043586263 | H23: =H22/H13 -> 0.037586692 | I23: =I22/I13 -> 0.041564236 | J23: =J22/J13 -> 0.037866586 | K23: =K22/K13 -> 0.063887808
B25: EBITDA | C25: =C19-C22 -> 4341.27 | D25: =D19-D22 -> 4865.16 | E25: =E19-E22 -> 5085.08 | F25: =F19-F22 -> 4983.32 | G25: =G19-G22 -> 4498.82 | H25: =H19-H22 -> 5634.72 | I25: =I19-I22 -> 6263.98 | J25: =J19-J22 -> 8612 | K25: =K19-K22 -> 9611.42 | L25: =IFERROR(SUM('[2]Data Sheet'!H51:K51),0) -> 10730.21
B26: EBITDA Margins | C26: =C25/C13 -> 0.19955531 | D26: =D25/D13 -> 0.19298586 | E26: =E25/E13 -> 0.16750583 | F26: =F25/F13 -> 0.16656233 | G26: =G25/G13 -> 0.16217177 | H26: =H25/H13 -> 0.1700036 | I26: =I25/I13 -> 0.17182594 | J26: =J25/J13 -> 0.19193041 | ... L26: =L25/L13 -> 0.19622466
B28: Interest | C28: =IFERROR('[2]Data Sheet'!C27,0) -> 1.4 | D28: =IFERROR('[2]Data Sheet'!D27,0) -> 1.31 | E28: =IFERROR('[2]Data Sheet'!E27,0) -> 4.48 | F28: =IFERROR('[2]Data Sheet'!F27,0) -> 3.16 | G28: =IFERROR('[2]Data Sheet'!G27,0) -> 6.66 | H28: =IFERROR('[2]Data Sheet'!H27,0) -> 8.66 | I28: =IFERROR('[2]Data Sheet'!I27,0) -> 39.51 | J28: =IFERROR('[2]Data Sheet'!J27,0) -> 60.36 | K28: =IFERROR('[2]Data Sheet'!K27,0) -> 388.9 | L28: =IFERROR(SUM('[2]Data Sheet'!H46:K46),0) -> 777.33
B29: Interest % sales | C29: =C28/C13 -> 6.4353851e-05 | D29: =D28/D13 -> 5.1963651e-05 | E29: =E28/E13 -> 0.0001475741 | F29: =F28/F13 -> 0.00010561974 | G29: =G28/G13 -> 0.00024007717 | H29: =H28/H13 -> 0.0002612785 | I29: =I28/I13 -> 0.0010837907 | J29: =J28/J13 -> 0.0013452066 | ... L29: =L28/L13 -> 0.014215129
B31: Depreciation | C31: =IFERROR('[2]Data Sheet'!C26,0) -> 307.29 | D31: =IFERROR('[2]Data Sheet'!D26,0) -> 314.8 | E31: =IFERROR('[2]Data Sheet'!E26,0) -> 265.69 | F31: =IFERROR('[2]Data Sheet'!F26,0) -> 246.43 | G31: =IFERROR('[2]Data Sheet'!G26,0) -> 259.37 | H31: =IFERROR('[2]Data Sheet'!H26,0) -> 269.76 | I31: =IFERROR('[2]Data Sheet'!I26,0) -> 285.85 | J31: =IFERROR('[2]Data Sheet'!J26,0) -> 364.77 | K31: =IFERROR('[2]Data Sheet'!K26,0) -> 414.23 | L31: =IFERROR(SUM('[2]Data Sheet'!H45:K45),0) -> 457.45
B32: Depriciation % sales | C32: =C31/C13 -> 0.014125211 | D32: =D31/D13 -> 0.012487143 | E32: =E31/E13 -> 0.0087520007 | F32: =F31/F13 -> 0.0082366684 | G32: =G31/G13 -> 0.009349672 | H32: =H31/H13 -> 0.0081388553 | I32: =I31/I13 -> 0.0078410923 | J32: =J31/J13 -> 0.0081294073 | ... L32: =L31/L13 -> 0.008365444
B34: Earnings before Tax | C34: =IFERROR(C25-SUM(C28:C31),0) -> 4032.5799 | D34: =D25-SUM(D28:D31) -> 4549.0499 | E34: =E25-SUM(E28:E31) -> 4814.9099 | F34: =F25-SUM(F28:F31) -> 4733.7299 | G34: =G25-SUM(G28:G31) -> 4232.7898 | H34: =H25-SUM(H28:H31) -> 5356.2997 | I34: =I25-SUM(I28:I31) -> 5938.6189 | J34: =J25-SUM(J28:J31) -> 8186.8687 | K34: =K25-SUM(K28:K31) -> 8808.2824 | L34: =L25-SUM(L28:L31) -> 9495.4158
B35: EBT % Sales | C35: =C34/C13 -> 0.18536575 | D35: =D34/D13 -> 0.18044675 | E35: =E34/E13 -> 0.15860625 | F35: =F34/F13 -> 0.15822004 | G35: =G34/G13 -> 0.15258201 | H35: =H34/H13 -> 0.16160346 | I35: =I34/I13 -> 0.16290103 | J35: =J34/J13 -> 0.18245577 | ... L35: =L34/L13 -> 0.17364383
B37: Tax | C37: =IFERROR('[2]Data Sheet'!C29,0) -> 1508.07 | D37: =IFERROR('[2]Data Sheet'!D29,0) -> 1714.47 | E37: =IFERROR('[2]Data Sheet'!E29,0) -> 2027.98 | F37: =IFERROR('[2]Data Sheet'!F29,0) -> 1480.22 | G37: =IFERROR('[2]Data Sheet'!G29,0) -> 1384.41 | H37: =IFERROR('[2]Data Sheet'!H29,0) -> 1485.81 | I37: =IFERROR('[2]Data Sheet'!I29,0) -> 1781.77 | J37: =IFERROR('[2]Data Sheet'!J29,0) -> 2331.8 | K37: =IFERROR('[2]Data Sheet'!K29,0) -> 2898.8 | L37: =IFERROR(SUM('[2]Data Sheet'!H48:K48),0) -> 2990
B38: Effective Tax Rate | C38: =C37/C34 -> 0.37397151 | D38: =D37/D34 -> 0.37688529 | E38: =E37/E34 -> 0.42118753 | F38: =F37/F34 -> 0.31269634 | G38: =G37/G34 -> 0.32706798 | H38: =H37/H34 -> 0.27739486 | I38: =I37/I34 -> 0.30003104 | J38: =J37/J34 -> 0.28482196 | ... L38: =L37/L34 -> 0.31488879
B40: Net profit | C40: =IFERROR(C34-C37,0) -> 2524.5099 | D40: =IFERROR(D34-D37,0) -> 2834.5799 | E40: =IFERROR(E34-E37,0) -> 2786.9299 | F40: =IFERROR(F34-F37,0) -> 3253.5099 | G40: =IFERROR(G34-G37,0) -> 2848.3798 | H40: =IFERROR(H34-H37,0) -> 3870.4897 | I40: =IFERROR(I34-I37,0) -> 4156.8489 | J40: =IFERROR(J34-J37,0) -> 5855.0687 | ... L40: =IFERROR(L34-L37,0) -> 6505.4158
B41: Net margins | C41: =C40/C13 -> 0.11604424 | D41: =D40/D13 -> 0.11243902 | E41: =E40/E13 -> 0.091803275 | F41: =F40/F13 -> 0.10874521 | G41: =G40/G13 -> 0.10267732 | H41: =H40/H13 -> 0.11677549 | I41: =I40/I13 -> 0.11402566 | J41: =J40/J13 -> 0.13048836 | ... L41: =L40/L13 -> 0.11896533
B43: No. of Equity shares | C43: =IFERROR('[2]Data Sheet'!C93,0) -> 28.94 | D43: =IFERROR('[2]Data Sheet'!D93,0) -> 28.94 | E43: =IFERROR('[2]Data Sheet'!E93,0) -> 28.94 | F43: =IFERROR('[2]Data Sheet'!F93,0) -> 28.94 | G43: =IFERROR('[2]Data Sheet'!G93,0) -> 28.94 | H43: =IFERROR('[2]Data Sheet'!H93,0) -> 28.94 | I43: =IFERROR('[2]Data Sheet'!I93,0) -> 28.3 | J43: =IFERROR('[2]Data Sheet'!J93,0) -> 27.92 | K43: =IFERROR('[2]Data Sheet'!K93,0) -> 27.93 | L43: =IFERROR(SUM('[2]Data Sheet'!H93:K93),0) -> 113.09
B45: EPS | C45: =IFERROR(C40/C43,0) -> 87.232548 | D45: =IFERROR(D40/D43,0) -> 97.946785 | E45: =IFERROR(E40/E43,0) -> 96.300271 | F45: =IFERROR(F40/F43,0) -> 112.42259 | G45: =IFERROR(G40/G43,0) -> 98.423627 | H45: =IFERROR(H40/H43,0) -> 133.74187 | I45: =IFERROR(I40/I43,0) -> 146.88512 | J45: =IFERROR(J40/J43,0) -> 209.70876 | ... L45: =IFERROR(L40/L43,0) -> 57.524235
B46: EPS Growth % | D46: =D45/C45-1 -> 0.12282384 | E46: =E45/D45-1 -> -0.016810285 | F46: =F45/E45-1 -> 0.16741722 | G46: =G45/F45-1 -> -0.12452095 | H46: =H45/G45-1 -> 0.35883908 | I46: =I45/H45-1 -> 0.098273263 | J46: =J45/I45-1 -> 0.42770596 | K46: =K45/J45-1 -> 0.0089320729 | L46: =L45/I45 -> 0.39162738
B48: Dividend per share | C48: =IFERROR('[2]Data Sheet'!C31/'Historical FS'!C43,0) -> 54.994471 | D48: =IFERROR('[2]Data Sheet'!D31/'Historical FS'!D43,0) -> 59.99378 | E48: =IFERROR('[2]Data Sheet'!E31/'Historical FS'!E43,0) -> 59.99378 | F48: =IFERROR('[2]Data Sheet'!F31/'Historical FS'!F43,0) -> 119.98756 | G48: =IFERROR('[2]Data Sheet'!G31/'Historical FS'!G43,0) -> 139.98549 | H48: =IFERROR('[2]Data Sheet'!H31/'Historical FS'!H43,0) -> 139.98549 | I48: =IFERROR('[2]Data Sheet'!I31/'Historical FS'!I43,0) -> 139.98021 | J48: =IFERROR('[2]Data Sheet'!J31/'Historical FS'!J43,0) -> 79.994269 | K48: =IFERROR('[2]Data Sheet'!K31/'Historical FS'!K43,0) -> 209.96992 | L48: =IFERROR('[2]Data Sheet'!J31/'Historical FS'!L43,0) -> 19.749226
B49: Dividend Payout ratio | C49: =IFERROR(C48/C45,0) -> 0.63043523 | D49: =IFERROR(D48/D45,0) -> 0.61251403 | E49: =IFERROR(E48/E45,0) -> 0.62298662 | F49: =IFERROR(F48/F45,0) -> 1.0672904 | G49: =IFERROR(G48/G45,0) -> 1.4222752 | H49: =IFERROR(H48/H45,0) -> 1.0466841 | I49: =IFERROR(I48/I45,0) -> 0.95299109 | J49: =IFERROR(J48/J45,0) -> 0.38145411 | ... L49: =IFERROR(L48/L45,0) -> 0.3433201
B51: Retained Earnings | C51: =IFERROR(1-C49,0) -> 0.36956477 | D51: =IFERROR(1-D49,0) -> 0.38748597 | E51: =IFERROR(1-E49,0) -> 0.37701338 | F51: =IFERROR(1-F49,0) -> -0.067290438 | G51: =IFERROR(1-G49,0) -> -0.42227524 | H51: =IFERROR(1-H49,0) -> -0.046684082 | I51: =IFERROR(1-I49,0) -> 0.047008905 | J51: =IFERROR(1-J49,0) -> 0.61854589 | ... L51: =IFERROR(1-L49,0) -> 0.6566799
B53: Balance Sheet
B55: Equity Share Capital | C55: =IFERROR('[2]Data Sheet'!C57,0) -> 289.37 | D55: =IFERROR('[2]Data Sheet'!D57,0) -> 289.37 | E55: =IFERROR('[2]Data Sheet'!E57,0) -> 289.37 | F55: =IFERROR('[2]Data Sheet'!F57,0) -> 289.37 | G55: =IFERROR('[2]Data Sheet'!G57,0) -> 289.37 | H55: =IFERROR('[2]Data Sheet'!H57,0) -> 289.37 | I55: =IFERROR('[2]Data Sheet'!I57,0) -> 282.96 | J55: =IFERROR('[2]Data Sheet'!J57,0) -> 279.18 | K55: =IFERROR('[2]Data Sheet'!K57,0) -> 279.26
A56: # | B56: Reserves | C56: =IFERROR('[2]Data Sheet'!C58,0) -> 17567.2 | D56: =IFERROR('[2]Data Sheet'!D58,0) -> 20135.87 | E56: =IFERROR('[2]Data Sheet'!E58,0) -> 22944.44 | F56: =IFERROR('[2]Data Sheet'!F58,0) -> 21372.71 | G56: =IFERROR('[2]Data Sheet'!G58,0) -> 26984.06 | H56: =IFERROR('[2]Data Sheet'!H58,0) -> 29570.28 | I56: =IFERROR('[2]Data Sheet'!I58,0) -> 29078.58 | J56: =IFERROR('[2]Data Sheet'!J58,0) -> 28683.23 | K56: =IFERROR('[2]Data Sheet'!K58,0) -> 34909.48
B57: Borrowings | C57: =IFERROR('[2]Data Sheet'!C59,0) -> 119.9 | D57: =IFERROR('[2]Data Sheet'!D59,0) -> 120.77 | E57: =IFERROR('[2]Data Sheet'!E59,0) -> 124.52 | F57: =IFERROR('[2]Data Sheet'!F59,0) -> 125.59 | G57: =IFERROR('[2]Data Sheet'!G59,0) -> 121.46 | H57: =IFERROR('[2]Data Sheet'!H59,0) -> 122.77 | I57: =IFERROR('[2]Data Sheet'!I59,0) -> 124.23 | J57: =IFERROR('[2]Data Sheet'!J59,0) -> 1911.74 | K57: =IFERROR('[2]Data Sheet'!K59,0) -> 9364.16
B58: Other Liabilities | C58: =IFERROR('[2]Data Sheet'!C60,0) -> 3661.15 | D58: =IFERROR('[2]Data Sheet'!D60,0) -> 4594.99 | E58: =IFERROR('[2]Data Sheet'!E60,0) -> 5476.08 | F58: =IFERROR('[2]Data Sheet'!F60,0) -> 4722.35 | G58: =IFERROR('[2]Data Sheet'!G60,0) -> 6206.82 | H58: =IFERROR('[2]Data Sheet'!H60,0) -> 5128.79 | I58: =IFERROR('[2]Data Sheet'!I60,0) -> 5650.68 | J58: =IFERROR('[2]Data Sheet'!J60,0) -> 8469.54 | K58: =IFERROR('[2]Data Sheet'!K60,0) -> 9557.02
B59: Total Liabilities | C59: =IFERROR(SUM(C55:C58),0) -> 21637.62 | D59: =IFERROR(SUM(D55:D58),0) -> 25141 | E59: =IFERROR(SUM(E55:E58),0) -> 28834.41 | F59: =IFERROR(SUM(F55:F58),0) -> 26510.02 | G59: =IFERROR(SUM(G55:G58),0) -> 33601.71 | H59: =IFERROR(SUM(H55:H58),0) -> 35111.21 | I59: =IFERROR(SUM(I55:I58),0) -> 35136.45 | J59: =IFERROR(SUM(J55:J58),0) -> 39343.69 | K59: =IFERROR(SUM(K55:K58),0) -> 54109.92
B61: Fixed Assets Net Block | C61: =IFERROR('[2]Data Sheet'!C62,0) -> 2001.79 | D61: =IFERROR('[2]Data Sheet'!D62,0) -> 1878.33 | E61: =IFERROR('[2]Data Sheet'!E62,0) -> 1763.94 | F61: =IFERROR('[2]Data Sheet'!F62,0) -> 1699.02 | G61: =IFERROR('[2]Data Sheet'!G62,0) -> 1667.55 | H61: =IFERROR('[2]Data Sheet'!H62,0) -> 1836.05 | I61: =IFERROR('[2]Data Sheet'!I62,0) -> 2842.24 | J61: =IFERROR('[2]Data Sheet'!J62,0) -> 3217.37 | K61: =IFERROR('[2]Data Sheet'!K62,0) -> 3676.59
B62: Capital Work in Progress | C62: =IFERROR('[2]Data Sheet'!C63,0) -> 42.17 | D62: =IFERROR('[2]Data Sheet'!D63,0) -> 56.47 | E62: =IFERROR('[2]Data Sheet'!E63,0) -> 48.02 | F62: =IFERROR('[2]Data Sheet'!F63,0) -> 60.19 | G62: =IFERROR('[2]Data Sheet'!G63,0) -> 15.98 | H62: =IFERROR('[2]Data Sheet'!H63,0) -> 77.21 | I62: =IFERROR('[2]Data Sheet'!I63,0) -> 85.27 | J62: =IFERROR('[2]Data Sheet'!J63,0) -> 35.1 | K62: =IFERROR('[2]Data Sheet'!K63,0) -> 60.8
B63: Investments | C63: =IFERROR('[2]Data Sheet'!C64,0) -> 15477.04 | D63: =IFERROR('[2]Data Sheet'!D64,0) -> 18894.57 | E63: =IFERROR('[2]Data Sheet'!E64,0) -> 20602.85 | F63: =IFERROR('[2]Data Sheet'!F64,0) -> 19913.58 | G63: =IFERROR('[2]Data Sheet'!G64,0) -> 24686.65 | H63: =IFERROR('[2]Data Sheet'!H64,0) -> 26634.12 | I63: =IFERROR('[2]Data Sheet'!I64,0) -> 26182.91 | J63: =IFERROR('[2]Data Sheet'!J64,0) -> 28086.68 | K63: =IFERROR('[2]Data Sheet'!K64,0) -> 28913.87
B64: Other Assets | C64: =IFERROR('[2]Data Sheet'!C65-SUM(C67:C69),0) -> 2133.59 | D64: =IFERROR('[2]Data Sheet'!D65-SUM(D67:D69),0) -> 1284.52 | E64: =IFERROR('[2]Data Sheet'!E65-SUM(E67:E69),0) -> 1965.33 | F64: =IFERROR('[2]Data Sheet'!F65-SUM(F67:F69),0) -> 1732.29 | G64: =IFERROR('[2]Data Sheet'!G65-SUM(G67:G69),0) -> 2481.95 | H64: =IFERROR('[2]Data Sheet'!H65-SUM(H67:H69),0) -> 2858.88 | I64: =IFERROR('[2]Data Sheet'!I65-SUM(I67:I69),0) -> 2019.57 | J64: =IFERROR('[2]Data Sheet'!J65-SUM(J67:J69),0) -> 3284.94 | K64: =IFERROR('[2]Data Sheet'!K65-SUM(K67:K69),0) -> 14408.48
B65: Total Non current assets | C65: =IFERROR(SUM(C61:C64),0) -> 19654.59 | D65: =IFERROR(SUM(D61:D64),0) -> 22113.89 | E65: =IFERROR(SUM(E61:E64),0) -> 24380.14 | F65: =IFERROR(SUM(F61:F64),0) -> 23405.08 | G65: =IFERROR(SUM(G61:G64),0) -> 28852.13 | H65: =IFERROR(SUM(H61:H64),0) -> 31406.26 | I65: =IFERROR(SUM(I61:I64),0) -> 31129.99 | J65: =IFERROR(SUM(J61:J64),0) -> 34624.09 | K65: =IFERROR(SUM(K61:K64),0) -> 47059.74
B67: Receivables | C67: =IFERROR('[2]Data Sheet'!C67,0) -> 953.29 | D67: =IFERROR('[2]Data Sheet'!D67,0) -> 1491.87 | E67: =IFERROR('[2]Data Sheet'!E67,0) -> 2559.69 | F67: =IFERROR('[2]Data Sheet'!F67,0) -> 1725.1 | G67: =IFERROR('[2]Data Sheet'!G67,0) -> 2716.85 | H67: =IFERROR('[2]Data Sheet'!H67,0) -> 1516.38 | I67: =IFERROR('[2]Data Sheet'!I67,0) -> 1752.43 | J67: =IFERROR('[2]Data Sheet'!J67,0) -> 2075.53 | K67: =IFERROR('[2]Data Sheet'!K67,0) -> 2125.22
B68: Inventory | C68: =IFERROR('[2]Data Sheet'!C68,0) -> 728.38 | D68: =IFERROR('[2]Data Sheet'!D68,0) -> 742.58 | E68: =IFERROR('[2]Data Sheet'!E68,0) -> 961.51 | F68: =IFERROR('[2]Data Sheet'!F68,0) -> 1063.5 | G68: =IFERROR('[2]Data Sheet'!G68,0) -> 1493.89 | H68: =IFERROR('[2]Data Sheet'!H68,0) -> 1230.51 | I68: =IFERROR('[2]Data Sheet'!I68,0) -> 1563.55 | J68: =IFERROR('[2]Data Sheet'!J68,0) -> 1688.75 | K68: =IFERROR('[2]Data Sheet'!K68,0) -> 2077.36
B69: Cash & Bank | C69: =IFERROR('[2]Data Sheet'!C69,0) -> 301.36 | D69: =IFERROR('[2]Data Sheet'!D69,0) -> 792.66 | E69: =IFERROR('[2]Data Sheet'!E69,0) -> 933.07 | F69: =IFERROR('[2]Data Sheet'!F69,0) -> 316.34 | G69: =IFERROR('[2]Data Sheet'!G69,0) -> 538.84 | H69: =IFERROR('[2]Data Sheet'!H69,0) -> 958.06 | I69: =IFERROR('[2]Data Sheet'!I69,0) -> 690.48 | J69: =IFERROR('[2]Data Sheet'!J69,0) -> 955.32 | K69: =IFERROR('[2]Data Sheet'!K69,0) -> 2847.6
B70: Total Current Assets | C70: =IFERROR(SUM(C67:C69),0) -> 1983.03 | D70: =IFERROR(SUM(D67:D69),0) -> 3027.11 | E70: =IFERROR(SUM(E67:E69),0) -> 4454.27 | F70: =IFERROR(SUM(F67:F69),0) -> 3104.94 | G70: =IFERROR(SUM(G67:G69),0) -> 4749.58 | H70: =IFERROR(SUM(H67:H69),0) -> 3704.95 | I70: =IFERROR(SUM(I67:I69),0) -> 4006.46 | J70: =IFERROR(SUM(J67:J69),0) -> 4719.6 | K70: =IFERROR(SUM(K67:K69),0) -> 7050.18
B72: Total Assests | C72: =IFERROR(C70+C65,0) -> 21637.62 | D72: =IFERROR(D70+D65,0) -> 25141 | E72: =IFERROR(E70+E65,0) -> 28834.41 | F72: =IFERROR(F70+F65,0) -> 26510.02 | G72: =IFERROR(G70+G65,0) -> 33601.71 | H72: =IFERROR(H70+H65,0) -> 35111.21 | I72: =IFERROR(I70+I65,0) -> 35136.45 | J72: =IFERROR(J70+J65,0) -> 39343.69 | K72: =IFERROR(K70+K65,0) -> 54109.92
B74: Check | C74: =C72=C59 -> TRUE | D74: =D72=D59 -> TRUE | E74: =E72=E59 -> TRUE | F74: =F72=F59 -> TRUE | G74: =G72=G59 -> TRUE | H74: =H72=H59 -> TRUE | I74: =I72=I59 -> TRUE | J74: =J72=J59 -> TRUE | K74: =K72=K59 -> TRUE
B76: Cash Flow Statement
B78: Operating Activities
A79: # | B79: Profit from operations | C79: 4613 | D79: =IFERROR('[2]Cash Flow Data'!E10,0) -> 4922 | E79: =IFERROR('[2]Cash Flow Data'!F10,0) -> 5249 | F79: =IFERROR('[2]Cash Flow Data'!G10,0) -> 5163 | G79: =IFERROR('[2]Cash Flow Data'!H10,0) -> 4961 | H79: =IFERROR('[2]Cash Flow Data'!I10,0) -> 5300 | I79: =IFERROR('[2]Cash Flow Data'!J10,0) -> 6609 | J79: =IFERROR('[2]Cash Flow Data'!K10,0) -> 8784 | K79: =IFERROR('[2]Cash Flow Data'!L10,0) -> 10404
B80: Receivables | C80: -241 | D80: =IFERROR('[2]Cash Flow Data'!E11,0) -> -539 | E80: =IFERROR('[2]Cash Flow Data'!F11,0) -> -1070 | F80: =IFERROR('[2]Cash Flow Data'!G11,0) -> 829 | G80: =IFERROR('[2]Cash Flow Data'!H11,0) -> -1002 | H80: =IFERROR('[2]Cash Flow Data'!I11,0) -> 1203 | I80: =IFERROR('[2]Cash Flow Data'!J11,0) -> -243 | J80: =IFERROR('[2]Cash Flow Data'!K11,0) -> -293 | K80: =IFERROR('[2]Cash Flow Data'!L11,0) -> -52
B81: Inventory | C81: -9 | D81: =IFERROR('[2]Cash Flow Data'!E12,0) -> -14 | E81: =IFERROR('[2]Cash Flow Data'!F12,0) -> -219 | F81: =IFERROR('[2]Cash Flow Data'!G12,0) -> -102 | G81: =IFERROR('[2]Cash Flow Data'!H12,0) -> -430 | H81: =IFERROR('[2]Cash Flow Data'!I12,0) -> 263 | I81: =IFERROR('[2]Cash Flow Data'!J12,0) -> -333 | J81: =IFERROR('[2]Cash Flow Data'!K12,0) -> -125 | K81: =IFERROR('[2]Cash Flow Data'!L12,0) -> -389
B82: Loans Advances | C82: 0 | D82: =IFERROR('[2]Cash Flow Data'!E13,0) -> 0 | E82: =IFERROR('[2]Cash Flow Data'!F13,0) -> 0 | F82: =IFERROR('[2]Cash Flow Data'!G13,0) -> 0 | G82: =IFERROR('[2]Cash Flow Data'!H13,0) -> 0 | H82: =IFERROR('[2]Cash Flow Data'!I13,0) -> 0 | I82: =IFERROR('[2]Cash Flow Data'!J13,0) -> 0 | J82: =IFERROR('[2]Cash Flow Data'!K13,0) -> 0 | K82: =IFERROR('[2]Cash Flow Data'!L13,0) -> -9848
B83: Other WC items | C83: 407 | D83: =IFERROR('[2]Cash Flow Data'!E14,0) -> 1644 | E83: =IFERROR('[2]Cash Flow Data'!F14,0) -> 491 | F83: =IFERROR('[2]Cash Flow Data'!G14,0) -> -361 | G83: =IFERROR('[2]Cash Flow Data'!H14,0) -> 931 | H83: =IFERROR('[2]Cash Flow Data'!I14,0) -> -867 | I83: =IFERROR('[2]Cash Flow Data'!J14,0) -> 1164 | J83: =IFERROR('[2]Cash Flow Data'!K14,0) -> 579 | K83: =IFERROR('[2]Cash Flow Data'!L14,0) -> 1229
B84: Working capital changes | C84: 157 | D84: =IFERROR('[2]Cash Flow Data'!E15,0) -> 1091 | E84: =IFERROR('[2]Cash Flow Data'!F15,0) -> -798 | F84: =IFERROR('[2]Cash Flow Data'!G15,0) -> 366 | G84: =IFERROR('[2]Cash Flow Data'!H15,0) -> -501 | H84: =IFERROR('[2]Cash Flow Data'!I15,0) -> 599 | I84: =IFERROR('[2]Cash Flow Data'!J15,0) -> 587 | J84: =IFERROR('[2]Cash Flow Data'!K15,0) -> 161 | K84: =IFERROR('[2]Cash Flow Data'!L15,0) -> -9060
B85: Direct taxes | C85: -1503 | D85: =IFERROR('[2]Cash Flow Data'!E16,0) -> -1685 | E85: =IFERROR('[2]Cash Flow Data'!F16,0) -> -1964 | F85: =IFERROR('[2]Cash Flow Data'!G16,0) -> -1678 | G85: =IFERROR('[2]Cash Flow Data'!H16,0) -> -1340 | H85: =IFERROR('[2]Cash Flow Data'!I16,0) -> -1702 | I85: =IFERROR('[2]Cash Flow Data'!J16,0) -> -1919 | J85: =IFERROR('[2]Cash Flow Data'!K16,0) -> -2387 | K85: =IFERROR('[2]Cash Flow Data'!L16,0) -> -2750
B86: Cash from Operating Activity - | C86: =SUM(C79:C85) -> 3424 | D86: =IFERROR(SUM(D79:D85),0) -> 5419 | E86: =IFERROR(SUM(E79:E85),0) -> 1689 | F86: =IFERROR(SUM(F79:F85),0) -> 4217 | G86: =IFERROR(SUM(G79:G85),0) -> 2619 | H86: =IFERROR(SUM(H79:H85),0) -> 4796 | I86: =IFERROR(SUM(I79:I85),0) -> 5865 | J86: =IFERROR(SUM(J79:J85),0) -> 6719 | K86: =IFERROR(SUM(K79:K85),0) -> -10466
B88: Investing Activities
B89: Fixed assets purchased | C89: -206 | D89: =IFERROR('[2]Cash Flow Data'!E18,0) -> -196 | E89: =IFERROR('[2]Cash Flow Data'!F18,0) -> -184 | F89: =IFERROR('[2]Cash Flow Data'!G18,0) -> -297 | G89: =IFERROR('[2]Cash Flow Data'!H18,0) -> -260 | H89: =IFERROR('[2]Cash Flow Data'!I18,0) -> -551 | I89: =IFERROR('[2]Cash Flow Data'!J18,0) -> -1110 | J89: =IFERROR('[2]Cash Flow Data'!K18,0) -> -723 | K89: =IFERROR('[2]Cash Flow Data'!L18,0) -> -874
B90: Fixed assets sold | C90: 9 | D90: =IFERROR('[2]Cash Flow Data'!E19,0) -> 13 | E90: =IFERROR('[2]Cash Flow Data'!F19,0) -> 76 | F90: =IFERROR('[2]Cash Flow Data'!G19,0) -> 17 | G90: =IFERROR('[2]Cash Flow Data'!H19,0) -> 6 | H90: =IFERROR('[2]Cash Flow Data'!I19,0) -> 33 | I90: =IFERROR('[2]Cash Flow Data'!J19,0) -> 137 | J90: =IFERROR('[2]Cash Flow Data'!K19,0) -> 12 | K90: =IFERROR('[2]Cash Flow Data'!L19,0) -> 6
B91: Investments purchased | C91: -5783 | D91: =IFERROR('[2]Cash Flow Data'!E20,0) -> -7484 | E91: =IFERROR('[2]Cash Flow Data'!F20,0) -> -9601 | F91: =IFERROR('[2]Cash Flow Data'!G20,0) -> -3518 | G91: =IFERROR('[2]Cash Flow Data'!H20,0) -> -6240 | H91: =IFERROR('[2]Cash Flow Data'!I20,0) -> -11293 | I91: =IFERROR('[2]Cash Flow Data'!J20,0) -> -9384 | J91: =IFERROR('[2]Cash Flow Data'!K20,0) -> -17365 | K91: =IFERROR('[2]Cash Flow Data'!L20,0) -> -11897
B92: Investments sold | C92: 2200 | D92: =IFERROR('[2]Cash Flow Data'!E21,0) -> 5547 | E92: =IFERROR('[2]Cash Flow Data'!F21,0) -> 9355 | F92: =IFERROR('[2]Cash Flow Data'!G21,0) -> 5346 | G92: =IFERROR('[2]Cash Flow Data'!H21,0) -> 3556 | H92: =IFERROR('[2]Cash Flow Data'!I21,0) -> 11527 | I92: =IFERROR('[2]Cash Flow Data'!J21,0) -> 11553 | J92: =IFERROR('[2]Cash Flow Data'!K21,0) -> 17248 | K92: =IFERROR('[2]Cash Flow Data'!L21,0) -> 11229
B93: Investment income | C93: 0 | D93: =IFERROR('[2]Cash Flow Data'!E22,0) -> 0 | E93: =IFERROR('[2]Cash Flow Data'!F22,0) -> 0 | F93: =IFERROR('[2]Cash Flow Data'!G22,0) -> 0 | G93: =IFERROR('[2]Cash Flow Data'!H22,0) -> 0 | H93: =IFERROR('[2]Cash Flow Data'!I22,0) -> 0 | I93: =IFERROR('[2]Cash Flow Data'!J22,0) -> 0 | J93: =IFERROR('[2]Cash Flow Data'!K22,0) -> 0 | K93: =IFERROR('[2]Cash Flow Data'!L22,0) -> 0
B94: Interest received | C94: 63 | D94: =IFERROR('[2]Cash Flow Data'!E23,0) -> 70 | E94: =IFERROR('[2]Cash Flow Data'!F23,0) -> 16 | F94: =IFERROR('[2]Cash Flow Data'!G23,0) -> 23 | G94: =IFERROR('[2]Cash Flow Data'!H23,0) -> 66 | H94: =IFERROR('[2]Cash Flow Data'!I23,0) -> 197 | I94: =IFERROR('[2]Cash Flow Data'!J23,0) -> 376 | J94: =IFERROR('[2]Cash Flow Data'!K23,0) -> 413 | K94: =IFERROR('[2]Cash Flow Data'!L23,0) -> 277
B95: Dividends received | C95: 0 | D95: =IFERROR('[2]Cash Flow Data'!E24,0) -> 0 | E95: =IFERROR('[2]Cash Flow Data'!F24,0) -> 0 | F95: =IFERROR('[2]Cash Flow Data'!G24,0) -> 25 | G95: =IFERROR('[2]Cash Flow Data'!H24,0) -> 0 | H95: =IFERROR('[2]Cash Flow Data'!I24,0) -> 46 | I95: =IFERROR('[2]Cash Flow Data'!J24,0) -> 47 | J95: =IFERROR('[2]Cash Flow Data'!K24,0) -> 43 | K95: =IFERROR('[2]Cash Flow Data'!L24,0) -> 30
B96: Other investing items | C96: 107 | D96: =IFERROR('[2]Cash Flow Data'!E25,0) -> 95 | E96: =IFERROR('[2]Cash Flow Data'!F25,0) -> 65 | F96: =IFERROR('[2]Cash Flow Data'!G25,0) -> 170 | G96: =IFERROR('[2]Cash Flow Data'!H25,0) -> 2 | H96: =IFERROR('[2]Cash Flow Data'!I25,0) -> 318 | I96: =IFERROR('[2]Cash Flow Data'!J25,0) -> -407 | J96: =IFERROR('[2]Cash Flow Data'!K25,0) -> 300 | K96: =IFERROR('[2]Cash Flow Data'!L25,0) -> 174
B97: Cash From Investing Activities | C97: =SUM(C89:C96) -> -3610 | D97: =SUM(D89:D96) -> -1955 | E97: =SUM(E89:E96) -> -273 | F97: =SUM(F89:F96) -> 1766 | G97: =SUM(G89:G96) -> -2870 | H97: =SUM(H89:H96) -> 277 | I97: =SUM(I89:I96) -> 1212 | J97: =SUM(J89:J96) -> -72 | K97: =SUM(K89:K96) -> -1055
B99: Financing Activities
B100: Proceeds from shares | C100: 0 | D100: =IFERROR('[2]Cash Flow Data'!E27,0) -> 0 | E100: =IFERROR('[2]Cash Flow Data'!F27,0) -> 0 | F100: =IFERROR('[2]Cash Flow Data'!G27,0) -> 0 | G100: =IFERROR('[2]Cash Flow Data'!H27,0) -> 0 | H100: =IFERROR('[2]Cash Flow Data'!I27,0) -> 0 | I100: =IFERROR('[2]Cash Flow Data'!J27,0) -> 0 | J100: =IFERROR('[2]Cash Flow Data'!K27,0) -> 87 | K100: =IFERROR('[2]Cash Flow Data'!L27,0) -> 29
B101: Proceeds from borrowings | C101: 0 | D101: =IFERROR('[2]Cash Flow Data'!E28,0) -> 0 | E101: =IFERROR('[2]Cash Flow Data'!F28,0) -> 0 | F101: =IFERROR('[2]Cash Flow Data'!G28,0) -> 0 | G101: =IFERROR('[2]Cash Flow Data'!H28,0) -> 0 | H101: =IFERROR('[2]Cash Flow Data'!I28,0) -> 0 | I101: =IFERROR('[2]Cash Flow Data'!J28,0) -> 0 | J101: =IFERROR('[2]Cash Flow Data'!K28,0) -> 1785 | K101: =IFERROR('[2]Cash Flow Data'!L28,0) -> 8945
B102: Repayment of borrowings | C102: 0 | D102: =IFERROR('[2]Cash Flow Data'!E29,0) -> 0 | E102: =IFERROR('[2]Cash Flow Data'!F29,0) -> 0 | F102: =IFERROR('[2]Cash Flow Data'!G29,0) -> 0 | G102: =IFERROR('[2]Cash Flow Data'!H29,0) -> 0 | H102: =IFERROR('[2]Cash Flow Data'!I29,0) -> 0 | I102: =IFERROR('[2]Cash Flow Data'!J29,0) -> 0 | J102: =IFERROR('[2]Cash Flow Data'!K29,0) -> 0 | K102: =IFERROR('[2]Cash Flow Data'!L29,0) -> -1511
B103: Dividends paid Interest paid fin | C103: -1 | D103: =IFERROR('[2]Cash Flow Data'!E30,0) -> 0 | E103: =IFERROR('[2]Cash Flow Data'!F30,0) -> -4 | F103: =IFERROR('[2]Cash Flow Data'!G30,0) -> -2 | G103: =IFERROR('[2]Cash Flow Data'!H30,0) -> -5 | H103: =IFERROR('[2]Cash Flow Data'!I30,0) -> -7 | I103: =IFERROR('[2]Cash Flow Data'!J30,0) -> -38 | J103: =IFERROR('[2]Cash Flow Data'!K30,0) -> -59 | K103: =IFERROR('[2]Cash Flow Data'!L30,0) -> -66
B104: Other financing items | C104: -173 | D104: =IFERROR('[2]Cash Flow Data'!E31,0) -> -1588 | E104: =IFERROR('[2]Cash Flow Data'!F31,0) -> -1736 | F104: =IFERROR('[2]Cash Flow Data'!G31,0) -> -5195 | G104: =IFERROR('[2]Cash Flow Data'!H31,0) -> -14 | H104: =IFERROR('[2]Cash Flow Data'!I31,0) -> -4049 | I104: =IFERROR('[2]Cash Flow Data'!J31,0) -> -4047 | J104: =IFERROR('[2]Cash Flow Data'!K31,0) -> -3960 | K104: =IFERROR('[2]Cash Flow Data'!L31,0) -> -2235
B105: Dividends paid | C105: -17 | D105: =IFERROR('[2]Cash Flow Data'!E32,0) -> -296 | E105: =IFERROR('[2]Cash Flow Data'!F32,0) -> -335 | F105: =IFERROR('[2]Cash Flow Data'!G32,0) -> -1049 | G105: =IFERROR('[2]Cash Flow Data'!H32,0) -> 0 | H105: =IFERROR('[2]Cash Flow Data'!I32,0) -> 0 | I105: =IFERROR('[2]Cash Flow Data'!J32,0) -> -3096 | J105: =IFERROR('[2]Cash Flow Data'!K32,0) -> -4019 | K105: =IFERROR('[2]Cash Flow Data'!L32,0) -> -932
B106: Cash from Financing activities | C106: =SUM(C100:C105) -> -191 | D106: =IFERROR(SUM(D100:D105),0) -> -1884 | E106: =IFERROR(SUM(E100:E105),0) -> -2075 | F106: =IFERROR(SUM(F100:F105),0) -> -6246 | G106: =IFERROR(SUM(G100:G105),0) -> -19 | H106: =IFERROR(SUM(H100:H105),0) -> -4056 | I106: =IFERROR(SUM(I100:I105),0) -> -7181 | J106: =IFERROR(SUM(J100:J105),0) -> -6166 | K106: =IFERROR(SUM(K100:K105),0) -> 4230
B108: Net Cash Flow | C108: =SUM(C86,C97,C106) -> -377 | D108: =IFERROR(SUM(D86+D97+D106),0) -> 1580 | E108: =IFERROR(SUM(E86+E97+E106),0) -> -659 | F108: =IFERROR(SUM(F86+F97+F106),0) -> -263 | G108: =IFERROR(SUM(G86+G97+G106),0) -> -270 | H108: =IFERROR(SUM(H86+H97+H106),0) -> 1017 | I108: =IFERROR(SUM(I86+I97+I106),0) -> -104 | J108: =IFERROR(SUM(J86+J97+J106),0) -> 481 | K108: =IFERROR(SUM(K86+K97+K106),0) -> -7291
B110: Return on Equity(ROE) | C110: Return on Equity(ROE) | D110: Return on Equity(ROE) | E110: Return on Equity(ROE) | F110: Return on Equity(ROE) | G110: Return on Equity(ROE) | H110: Return on Equity(ROE) | I110: Return on Equity(ROE) | L110: Return on Equity(ROE)

Sheet Forcasting
B2: Return on Equity(ROE) | C2: Return on Equity(ROE) | D2: Return on Equity(ROE) | E2: Return on Equity(ROE) | F2: Return on Equity(ROE) | G2: Return on Equity(ROE) | H2: Return on Equity(ROE) | I2: Return on Equity(ROE) | J2: Return on Equity(ROE)
B4: ='[2]Data Sheet'!B1 -> BAJAJ AUTO LTD
B5: =CONCATENATE(" ",VLOOKUP(B4,'[2]LIST OF STOCKS'!B5:D5444,3,FALSE)," | ","Bse Code: ",VLOOKUP(B4,'[2]LIST OF STOCKS'!B5:E5444,2,FALSE),) -> BAJAJ-AUTO | Bse Code: 532977
B10: ="Sales Forcasting - "&'[2]Balance Sheet'!A1 -> Sales Forcasting - BAJAJ AUTO LTD
B11: Year Weight | C11: Year | D11: Sales | E11: Sales Growth
B12: 1 | C12: 2017A | D12: {=TRANSPOSE('[2]Data Sheet'!C17:I17)} -> 21754.72
B13: 2 | C13: 2018A | D13: 25209.93 | E13: =D13/D12-1 -> 0.15882576
B14: 3 | C14: 2019A | D14: 30357.63 | E14: =D14/D13-1 -> 0.20419335
B15: 4 | C15: 2020A | D15: 29918.65 | E15: =D15/D14-1 -> -0.014460286
B16: 5 | C16: 2021A | D16: 27741.08 | E16: =D16/D15-1 -> -0.07278303
B17: 6 | C17: 2022A | D17: 33144.71 | E17: =D17/D16-1 -> 0.19478802
B18: 7 | C18: 2023A | D18: 36455.38 | E18: =D18/D17-1 -> 0.099885321
B19: 8 | C19: 2024A | D19: ='[2]Data Sheet'!J17 -> 44870.43 | E19: =D19/D18-1 -> 0.2308315
B20: 9 | C20: 2025A | D20: ='[2]Data Sheet'!K17 -> 50994.55 | E20: =D20/D19-1 -> 0.13648454
B21: 10 | C21: 2026E | D21: =FORECAST(B21,$D$12:$D$20,$B$12:$B$20) -> 49329.874 | E21: =D21/D20-1 -> -0.032644197
B22: 11 | C22: 2027E | D22: =FORECAST(B22,$D$12:$D$20,$B$12:$B$20) -> 52519.247 | E22: =D22/D21-1 -> 0.064653986
B23: 12 | C23: 2028E | D23: =FORECAST(B23,$D$12:$D$20,$B$12:$B$20) -> 55708.62 | E23: =D23/D22-1 -> 0.060727699
B24: 13 | C24: 2029E | D24: =FORECAST(B24,$D$12:$D$20,$B$12:$B$20) -> 58897.993 | E24: =D24/D23-1 -> 0.057250979
B25: 14 | C25: 2030E | D25: =FORECAST(B25,$D$12:$D$20,$B$12:$B$20) -> 62087.366 | E25: =D25/D24-1 -> 0.054150793
B27: Return on Equity(ROE) | C27: Return on Equity(ROE) | D27: Return on Equity(ROE) | E27: Return on Equity(ROE) | F27: Return on Equity(ROE) | G27: Return on Equity(ROE) | H27: Return on Equity(ROE) | I27: Return on Equity(ROE) | J27: Return on Equity(ROE) | K27: Return on Equity(ROE)
H28: ="EBITDA Forcasting - "&'[2]Balance Sheet'!A1 -> EBITDA Forcasting - BAJAJ AUTO LTD
H29: Year Weight | I29: Year | J29: EBITDA | K29: EBITDA Growth
H30: 1 | I30: 2017A | J30: ='Historical FS'!C25 -> 4341.27
H31: 2 | I31: 2018A | J31: ='Historical FS'!D25 -> 4865.16 | K31: =J31/J30-1 -> 0.12067667
H32: 3 | I32: 2019A | J32: ='Historical FS'!E25 -> 5085.08 | K32: =J32/J31-1 -> 0.045203035
H33: 4 | I33: 2020A | J33: ='Historical FS'!F25 -> 4983.32 | K33: =J33/J32-1 -> -0.020011485
H34: 5 | I34: 2021A | J34: ='Historical FS'!G25 -> 4498.82 | K34: =J34/J33-1 -> -0.09722434
H35: 6 | I35: 2022A | J35: ='Historical FS'!H25 -> 5634.72 | K35: =J35/J34-1 -> 0.25248843
H36: 7 | I36: 2023A | J36: ='Historical FS'!I25 -> 6263.98 | K36: =J36/J35-1 -> 0.11167547
H37: 8 | I37: 2024A | J37: ='Historical FS'!J25 -> 8612 | K37: =J37/J36-1 -> 0.37484475
H38: 9 | I38: 2025A | J38: ='Historical FS'!K25 -> 9611.42 | K38: =J38/J37-1 -> 0.1160497
H39: 10 | I39: 2026E | J39: =FORECAST(H39,$J$30:$J$38,$H$30:$H$38) -> 8932.6122 | K39: =J39/J38-1 -> -0.070625129
H40: 11 | I40: 2027E | J40: =FORECAST(H40,$J$30:$J$38,$H$30:$H$38) -> 9521.4509 | K40: =J40/J39-1 -> 0.065920097
H41: 12 | I41: 2028E | J41: =FORECAST(H41,$J$30:$J$38,$H$30:$H$38) -> 10110.29 | K41: =J41/J40-1 -> 0.061843376
H42: 13 | I42: 2029E | J42: =FORECAST(H42,$J$30:$J$38,$H$30:$H$38) -> 10699.128 | K42: =J42/J41-1 -> 0.058241523
H43: 14 | I43: 2030E | J43: =FORECAST(H43,$J$30:$J$38,$H$30:$H$38) -> 11287.967 | K43: =J43/J42-1 -> 0.055036135
B46: ="Net Profit Forcasting - "&'[2]Balance Sheet'!A1 -> Net Profit Forcasting - BAJAJ AUTO LTD
B47: =B11 -> Year Weight | C47: =C11 -> Year | D47: Net Profit | E47: Net profit Growth
B48: 1 | C48: =C12 -> 2017A | D48: ='Historical FS'!C40 -> 2524.5099
B49: 2 | C49: =C13 -> 2018A | D49: ='Historical FS'!D40 -> 2834.5799 | E49: =D49/D48-1 -> 0.12282384
B50: 3 | C50: =C14 -> 2019A | D50: ='Historical FS'!E40 -> 2786.9299 | E50: =D50/D49-1 -> -0.016810285
B51: 4 | C51: =C15 -> 2020A | D51: ='Historical FS'!F40 -> 3253.5099 | E51: =D51/D50-1 -> 0.16741722
B52: 5 | C52: =C16 -> 2021A | D52: ='Historical FS'!G40 -> 2848.3798 | E52: =D52/D51-1 -> -0.12452095
B53: 6 | C53: =C17 -> 2022A | D53: ='Historical FS'!H40 -> 3870.4897 | E53: =D53/D52-1 -> 0.35883908
B54: 7 | C54: =C18 -> 2023A | D54: ='Historical FS'!I40 -> 4156.8489 | E54: =D54/D53-1 -> 0.073985257
B55: 8 | C55: =C19 -> 2024A | D55: ='Historical FS'!J40 -> 5855.0687 | E55: =D55/D54-1 -> 0.40853535
B56: 9 | C56: =C20 -> 2025A | D56: ='Historical FS'!K40 -> 5909.4824 | E56: =D56/D55-1 -> 0.0092934382
B57: 10 | C57: =C21 -> 2026E | D57: =FORECAST(B57,$D$48:$D$56,$B$48:$B$56) -> 5945.3811 | E57: =D57/D56-1 -> 0.0060747583
B58: 11 | C58: =C22 -> 2027E | D58: =FORECAST(B58,$D$48:$D$56,$B$48:$B$56) -> 6378.0173 | E58: =D58/D57-1 -> 0.072768461
B59: 12 | C59: =C23 -> 2028E | D59: =FORECAST(B59,$D$48:$D$56,$B$48:$B$56) -> 6810.6535 | E59: =D59/D58-1 -> 0.067832402
B60: 13 | C60: =C24 -> 2029E | D60: =FORECAST(B60,$D$48:$D$56,$B$48:$B$56) -> 7243.2897 | E60: =D60/D59-1 -> 0.063523453
B61: 14 | C61: =C25 -> 2030E | D61: =FORECAST(B61,$D$48:$D$56,$B$48:$B$56) -> 7675.926 | E61: =D61/D60-1 -> 0.059729245

Sheet Ratio Analysis
B2: Return on Equity(ROE) | C2: Return on Equity(ROE) | D2: Return on Equity(ROE) | E2: Return on Equity(ROE) | F2: Return on Equity(ROE) | G2: Return on Equity(ROE) | H2: Return on Equity(ROE) | I2: Return on Equity(ROE) | L2: Return on Equity(ROE) | M2: Return on Equity(ROE)
B4: ='[2]Data Sheet'!B1 -> BAJAJ AUTO LTD
B5: =CONCATENATE(" ",VLOOKUP(B4,'[2]LIST OF STOCKS'!B5:D5444,3,FALSE)," | ","Bse Code: ",VLOOKUP(B4,'[2]LIST OF STOCKS'!B5:E5444,2,FALSE),) -> BAJAJ-AUTO | Bse Code: 532977
B8: ="Ratio Analysis - "&'[2]Balance Sheet'!A1 -> Ratio Analysis - BAJAJ AUTO LTD
B9: Years | C9: =IFERROR('[2]Data Sheet'!C16,0) -> 42825 | D9: =IFERROR('[2]Data Sheet'!D16,0) -> 43190 | E9: =IFERROR('[2]Data Sheet'!E16,0) -> 43555 | F9: =IFERROR('[2]Data Sheet'!F16,0) -> 43921 | G9: =IFERROR('[2]Data Sheet'!G16,0) -> 44286 | H9: =IFERROR('[2]Data Sheet'!H16,0) -> 44651 | I9: =IFERROR('[2]Data Sheet'!I16,0) -> 45016 | J9: =IFERROR('[2]Data Sheet'!J16,0) -> 45382 | K9: =IFERROR('[2]Data Sheet'!K16,0) -> 45747 | L9: Mean | M9: Median
B11: Sales Growth | C11: - | D11: =IFERROR('Historical FS'!D14,0) -> 0.15882576 | E11: =IFERROR('Historical FS'!E14,0) -> 0.20419335 | F11: =IFERROR('Historical FS'!F14,0) -> -0.014460286 | G11: =IFERROR('Historical FS'!G14,0) -> -0.07278303 | H11: =IFERROR('Historical FS'!H14,0) -> 0.19478802 | I11: =IFERROR('Historical FS'!I14,0) -> 0.099885321 | J11: =IFERROR('Historical FS'!J14,0) -> 0.2308315 | K11: =IFERROR('Historical FS'!K14,0) -> 0.13648454 | L11: =IFERROR(AVERAGE(D11:I11),0) -> 0.095074856 | M11: =IFERROR(MEDIAN(D11:I11),0) -> 0.12935554
B12: EBIT Growth | D12: =IFERROR('Historical FS'!D34/'Historical FS'!C34-1,0) -> 0.12807434 | E12: =IFERROR('Historical FS'!E34/'Historical FS'!D34-1,0) -> 0.058442951 | F12: =IFERROR('Historical FS'!F34/'Historical FS'!E34-1,0) -> -0.01686012 | G12: =IFERROR('Historical FS'!G34/'Historical FS'!F34-1,0) -> -0.10582356 | H12: =IFERROR('Historical FS'!H34/'Historical FS'!G34-1,0) -> 0.26543014 | I12: =IFERROR('Historical FS'!I34/'Historical FS'!H34-1,0) -> 0.10871669 | J12: =IFERROR('Historical FS'!J34/'Historical FS'!I34-1,0) -> 0.37858124 | K12: =IFERROR('Historical FS'!K34/'Historical FS'!J34-1,0) -> 0.075903712 | L12: =IFERROR(AVERAGE(D12:I12),0) -> 0.072996741 | M12: =IFERROR(MEDIAN(D12:I12),0) -> 0.083579821
B13: Net Profit Growth | D13: =IFERROR('Historical FS'!D40/'Historical FS'!C40-1,0) -> 0.12282384 | E13: =IFERROR('Historical FS'!E40/'Historical FS'!D40-1,0) -> -0.016810285 | F13: =IFERROR('Historical FS'!F40/'Historical FS'!E40-1,0) -> 0.16741722 | G13: =IFERROR('Historical FS'!G40/'Historical FS'!F40-1,0) -> -0.12452095 | H13: =IFERROR('Historical FS'!H40/'Historical FS'!G40-1,0) -> 0.35883908 | I13: =IFERROR('Historical FS'!I40/'Historical FS'!H40-1,0) -> 0.073985257 | J13: =IFERROR('Historical FS'!J40/'Historical FS'!I40-1,0) -> 0.40853535 | K13: =IFERROR('Historical FS'!K40/'Historical FS'!J40-1,0) -> 0.0092934382 | L13: =IFERROR(AVERAGE(D13:I13),0) -> 0.096955695 | M13: =IFERROR(MEDIAN(D13:I13),0) -> 0.09840455
B14: Dividend Growth | D14: =IFERROR('Historical FS'!D48/'Historical FS'!C48-1,0) -> 0.090905664 | E14: =IFERROR('Historical FS'!E48/'Historical FS'!D48-1,0) -> 0 | F14: =IFERROR('Historical FS'!F48/'Historical FS'!E48-1,0) -> 1 | G14: =IFERROR('Historical FS'!G48/'Historical FS'!F48-1,0) -> 0.16666667 | H14: =IFERROR('Historical FS'!H48/'Historical FS'!G48-1,0) -> 0 | I14: =IFERROR('Historical FS'!I48/'Historical FS'!H48-1,0) -> -3.7683912e-05 | J14: =IFERROR('Historical FS'!J48/'Historical FS'!I48-1,0) -> -0.42853159 | K14: =IFERROR('Historical FS'!K48/'Historical FS'!J48-1,0) -> 1.6248121 | L14: =IFERROR(AVERAGE(D14:I14),0) -> 0.20958911 | M14: =IFERROR(MEDIAN(D14:I14),0) -> 0.045452832
B15: EBITDA Growth | D15: =IFERROR('Historical FS'!D25/'Historical FS'!C25-1,0) -> 0.12067667 | E15: =IFERROR('Historical FS'!E25/'Historical FS'!D25-1,0) -> 0.045203035 | F15: =IFERROR('Historical FS'!F25/'Historical FS'!E25-1,0) -> -0.020011485 | G15: =IFERROR('Historical FS'!G25/'Historical FS'!F25-1,0) -> -0.09722434 | H15: =IFERROR('Historical FS'!H25/'Historical FS'!G25-1,0) -> 0.25248843 | I15: =IFERROR('Historical FS'!I25/'Historical FS'!H25-1,0) -> 0.11167547 | J15: =IFERROR('Historical FS'!J25/'Historical FS'!I25-1,0) -> 0.37484475 | K15: =IFERROR('Historical FS'!K25/'Historical FS'!J25-1,0) -> 0.1160497 | L15: =IFERROR(AVERAGE(D15:I15),0) -> 0.068801296 | M15: =IFERROR(MEDIAN(D15:I15),0) -> 0.078439252
B17: Gross Margin | C17: =IFERROR('Historical FS'!C20,0) -> 0.2481935 | D17: =IFERROR('Historical FS'!D20,0) -> 0.24181701 | E17: =IFERROR('Historical FS'!E20,0) -> 0.21206497 | F17: =IFERROR('Historical FS'!F20,0) -> 0.21972749 | G17: =IFERROR('Historical FS'!G20,0) -> 0.20575803 | H17: =IFERROR('Historical FS'!H20,0) -> 0.20759029 | I17: =IFERROR('Historical FS'!I20,0) -> 0.21339018 | J17: =IFERROR('Historical FS'!J20,0) -> 0.229797 | K17: =IFERROR('Historical FS'!K20,0) -> 0.25236716 | L17: =IFERROR(AVERAGE(C17:I17),0) -> 0.22122021 | M17: =IFERROR(MEDIAN(C17:I17),0) -> 0.21339018
B18: EBITDA margin | C18: =IFERROR('Historical FS'!C26,0) -> 0.19955531 | D18: =IFERROR('Historical FS'!D26,0) -> 0.19298586 | E18: =IFERROR('Historical FS'!E26,0) -> 0.16750583 | F18: =IFERROR('Historical FS'!F26,0) -> 0.16656233 | G18: =IFERROR('Historical FS'!G26,0) -> 0.16217177 | H18: =IFERROR('Historical FS'!H26,0) -> 0.1700036 | I18: =IFERROR('Historical FS'!I26,0) -> 0.17182594 | J18: =IFERROR('Historical FS'!J26,0) -> 0.19193041 | K18: =IFERROR('Historical FS'!K26,0) -> 0.18847936 | L18: =IFERROR(AVERAGE(C18:I18),0) -> 0.17580152 | M18: =IFERROR(MEDIAN(C18:I18),0) -> 0.1700036
B19: EBIT margin | C19: =IFERROR(('Historical FS'!C25-'Historical FS'!C31)/'Historical FS'!C13,0) -> 0.1854301 | D19: =IFERROR(('Historical FS'!D25-'Historical FS'!D31)/'Historical FS'!D13,0) -> 0.18049872 | E19: =IFERROR(('Historical FS'!E25-'Historical FS'!E31)/'Historical FS'!E13,0) -> 0.15875383 | F19: =IFERROR(('Historical FS'!F25-'Historical FS'!F31)/'Historical FS'!F13,0) -> 0.15832566 | G19: =IFERROR(('Historical FS'!G25-'Historical FS'!G31)/'Historical FS'!G13,0) -> 0.1528221 | H19: =IFERROR(('Historical FS'!H25-'Historical FS'!H31)/'Historical FS'!H13,0) -> 0.16186474 | I19: =IFERROR(('Historical FS'!I25-'Historical FS'!I31)/'Historical FS'!I13,0) -> 0.16398485 | J19: =IFERROR(('Historical FS'!J25-'Historical FS'!J31)/'Historical FS'!J13,0) -> 0.183801 | K19: =IFERROR(('Historical FS'!K25-'Historical FS'!K31)/'Historical FS'!K13,0) -> 0.18035633 | L19: =IFERROR(AVERAGE(C19:I19),0) -> 0.16595429 | M19: =IFERROR(MEDIAN(C19:I19),0) -> 0.16186474
B20: EBT Margin | C20: =IFERROR('Historical FS'!C23,0) -> 0.048638181 | D20: =IFERROR('Historical FS'!D23,0) -> 0.048831155 | E20: =IFERROR('Historical FS'!E23,0) -> 0.044559144 | F20: =IFERROR('Historical FS'!F23,0) -> 0.053165166 | G20: =IFERROR('Historical FS'!G23,0) -> 0.043586263 | H20: =IFERROR('Historical FS'!H23,0) -> 0.037586692 | I20: =IFERROR('Historical FS'!I23,0) -> 0.041564236 | J20: =IFERROR('Historical FS'!J23,0) -> 0.037866586 | K20: =IFERROR('Historical FS'!K23,0) -> 0.063887808 | L20: =IFERROR(AVERAGE(C20:I20),0) -> 0.045418691 | M20: =IFERROR(MEDIAN(C20:I20),0) -> 0.044559144
B21: Net profit Margin | C21: =IFERROR('Historical FS'!C41,0) -> 0.11604424 | D21: =IFERROR('Historical FS'!D41,0) -> 0.11243902 | E21: =IFERROR('Historical FS'!E41,0) -> 0.091803275 | F21: =IFERROR('Historical FS'!F41,0) -> 0.10874521 | G21: =IFERROR('Historical FS'!G41,0) -> 0.10267732 | H21: =IFERROR('Historical FS'!H41,0) -> 0.11677549 | I21: =IFERROR('Historical FS'!I41,0) -> 0.11402566 | J21: =IFERROR('Historical FS'!J41,0) -> 0.13048836 | K21: =IFERROR('Historical FS'!K41,0) -> 0.11588459 | L21: =IFERROR(AVERAGE(C21:I21),0) -> 0.10893003 | M21: =IFERROR(MEDIAN(C21:I21),0) -> 0.11243902
B23: Sales expenses % sales | C23: =IFERROR('Historical FS'!C23,0) -> 0.048638181 | D23: =IFERROR('Historical FS'!D23,0) -> 0.048831155 | E23: =IFERROR('Historical FS'!E23,0) -> 0.044559144 | F23: =IFERROR('Historical FS'!F23,0) -> 0.053165166 | G23: =IFERROR('Historical FS'!G23,0) -> 0.043586263 | H23: =IFERROR('Historical FS'!H23,0) -> 0.037586692 | I23: =IFERROR('Historical FS'!I23,0) -> 0.041564236 | J23: =IFERROR('Historical FS'!J23,0) -> 0.037866586 | K23: =IFERROR('Historical FS'!K23,0) -> 0.063887808 | L23: =IFERROR(AVERAGE(C23:I23),0) -> 0.045418691 | M23: =IFERROR(MEDIAN(C23:I23),0) -> 0.044559144
B24: Depreciation % sales | C24: =IFERROR('Historical FS'!C32,0) -> 0.014125211 | D24: =IFERROR('Historical FS'!D32,0) -> 0.012487143 | E24: =IFERROR('Historical FS'!E32,0) -> 0.0087520007 | F24: =IFERROR('Historical FS'!F32,0) -> 0.0082366684 | G24: =IFERROR('Historical FS'!G32,0) -> 0.009349672 | H24: =IFERROR('Historical FS'!H32,0) -> 0.0081388553 | I24: =IFERROR('Historical FS'!I32,0) -> 0.0078410923 | J24: =IFERROR('Historical FS'!J32,0) -> 0.0081294073 | K24: =IFERROR('Historical FS'!K32,0) -> 0.0081230249 | L24: =IFERROR(AVERAGE(C24:I24),0) -> 0.0098472346 | M24: =IFERROR(MEDIAN(C24:I24),0) -> 0.0087520007
B25: Operating Income % Sales | C25: =C19 -> 0.1854301 | D25: =D19 -> 0.18049872 | E25: =E19 -> 0.15875383 | F25: =F19 -> 0.15832566 | G25: =G19 -> 0.1528221 | H25: =H19 -> 0.16186474 | I25: =I19 -> 0.16398485 | J25: =J19 -> 0.183801 | K25: =K19 -> 0.18035633 | L25: =IFERROR(AVERAGE(C25:I25),0) -> 0.16595429 | M25: =IFERROR(MEDIAN(C25:I25),0) -> 0.16186474
B27: Return on Capital Employed | C27: =IFERROR(('Historical FS'!C25-'Historical FS'!C31)/(SUM('Historical FS'!C55:C57)),0) -> 0.22440335 | D27: =IFERROR(('Historical FS'!D25-'Historical FS'!D31)/(SUM('Historical FS'!D55:D57)),0) -> 0.22147171 | E27: =IFERROR(('Historical FS'!E25-'Historical FS'!E31)/(SUM('Historical FS'!E55:E57)),0) -> 0.20632425 | F27: =IFERROR(('Historical FS'!F25-'Historical FS'!F31)/(SUM('Historical FS'!F55:F57)),0) -> 0.2174115 | G27: =IFERROR(('Historical FS'!G25-'Historical FS'!G31)/(SUM('Historical FS'!G55:G57)),0) -> 0.15475331 | H27: =IFERROR(('Historical FS'!H25-'Historical FS'!H31)/(SUM('Historical FS'!H55:H57)),0) -> 0.17893686 | I27: =IFERROR(('Historical FS'!I25-'Historical FS'!I31)/(SUM('Historical FS'!I55:I57)),0) -> 0.20274627 | J27: =IFERROR(('Historical FS'!J25-'Historical FS'!J31)/(SUM('Historical FS'!J55:J57)),0) -> 0.26712412 | K27: =IFERROR(('Historical FS'!K25-'Historical FS'!K31)/(SUM('Historical FS'!K55:K57)),0) -> 0.20643303 | L27: =IFERROR(AVERAGE(C27:I27),0) -> 0.20086389 | M27: =IFERROR(MEDIAN(C27:I27),0) -> 0.20632425
B28: Retained Earnings% | C28: =IFERROR('Historical FS'!C51,0) -> 0.36956477 | D28: =IFERROR('Historical FS'!D51,0) -> 0.38748597 | E28: =IFERROR('Historical FS'!E51,0) -> 0.37701338 | F28: =IFERROR('Historical FS'!F51,0) -> -0.067290438 | G28: =IFERROR('Historical FS'!G51,0) -> -0.42227524 | H28: =IFERROR('Historical FS'!H51,0) -> -0.046684082 | I28: =IFERROR('Historical FS'!I51,0) -> 0.047008905 | J28: =IFERROR('Historical FS'!J51,0) -> 0.61854589 | K28: =IFERROR('Historical FS'!K51,0) -> 0.0076186662 | L28: =IFERROR(AVERAGE(C28:I28),0) -> 0.09211761 | M28: =IFERROR(MEDIAN(C28:I28),0) -> 0.047008905
B29: Return of Equity% | C29: =IFERROR('Historical FS'!C40/SUM('Historical FS'!C55:C56),0) -> 0.14137709 | D29: =IFERROR('Historical FS'!D40/SUM('Historical FS'!D55:D56),0) -> 0.13877829 | E29: =IFERROR('Historical FS'!E40/SUM('Historical FS'!E55:E56),0) -> 0.11995148 | F29: =IFERROR('Historical FS'!F40/SUM('Historical FS'!F55:F56),0) -> 0.15019379 | G29: =IFERROR('Historical FS'!G40/SUM('Historical FS'!G55:G56),0) -> 0.1044379 | H29: =IFERROR('Historical FS'!H40/SUM('Historical FS'!H55:H56),0) -> 0.12962274 | I29: =IFERROR('Historical FS'!I40/SUM('Historical FS'!I55:I56),0) -> 0.14157462 | J29: =IFERROR('Historical FS'!J40/SUM('Historical FS'!J55:J56),0) -> 0.20216096 | K29: =IFERROR('Historical FS'!K40/SUM('Historical FS'!K55:K56),0) -> 0.16793674 | L29: =IFERROR(AVERAGE(C29:I29),0) -> 0.13227656 | M29: =IFERROR(MEDIAN(C29:I29),0) -> 0.13877829
B30: Self Sustained Growth Rate | C30: =IFERROR(C28*C29,0) -> 0.052247993 | D30: =IFERROR(D28*D29,0) -> 0.053774641 | E30: =IFERROR(E28*E29,0) -> 0.045223313 | F30: =IFERROR(F28*F29,0) -> -0.010106606 | G30: =IFERROR(G28*G29,0) -> -0.044101539 | H30: =IFERROR(H28*H29,0) -> -0.0060513188 | I30: =IFERROR(I28*I29,0) -> 0.006655268 | J30: =IFERROR(J28*J29,0) -> 0.12504583 | K30: =IFERROR(K28*K29,0) -> 0.001279454 | L30: =IFERROR(AVERAGE(C30:I30),0) -> 0.013948821 | M30: =IFERROR(MEDIAN(C30:I30),0) -> 0.006655268
B31: Interest Coverage Ratio | C31: =('Historical FS'!C25-'Historical FS'!C31)/'Historical FS'!C28 -> 2881.4143 | D31: =('Historical FS'!D25-'Historical FS'!D31)/'Historical FS'!D28 -> 3473.5573 | E31: =('Historical FS'!E25-'Historical FS'!E31)/'Historical FS'!E28 -> 1075.7567 | F31: =('Historical FS'!F25-'Historical FS'!F31)/'Historical FS'!F28 -> 1499.0158 | G31: =('Historical FS'!G25-'Historical FS'!G31)/'Historical FS'!G28 -> 636.55405 | H31: =('Historical FS'!H25-'Historical FS'!H31)/'Historical FS'!H28 -> 619.51039 | I31: =('Historical FS'!I25-'Historical FS'!I31)/'Historical FS'!I28 -> 151.30676 | J31: =('Historical FS'!J25-'Historical FS'!J31)/'Historical FS'!J28 -> 136.63403 | K31: =('Historical FS'!K25-'Historical FS'!K31)/'Historical FS'!K28 -> 23.649241 | L31: =IFERROR(AVERAGE(C31:I31),0) -> 1476.7308 | M31: =IFERROR(MEDIAN(C31:I31),0) -> 1075.7567
B33: Debtor Turnover Ratio | C33: =IFERROR('Historical FS'!C13/'Historical FS'!C67,0) -> 22.820674 | D33: =IFERROR('Historical FS'!D13/'Historical FS'!D67,0) -> 16.898208 | E33: =IFERROR('Historical FS'!E13/'Historical FS'!E67,0) -> 11.859885 | F33: =IFERROR('Historical FS'!F13/'Historical FS'!F67,0) -> 17.34314 | G33: =IFERROR('Historical FS'!G13/'Historical FS'!G67,0) -> 10.210751 | H33: =IFERROR('Historical FS'!H13/'Historical FS'!H67,0) -> 21.857786 | I33: =IFERROR('Historical FS'!I13/'Historical FS'!I67,0) -> 20.80276 | J33: =IFERROR('Historical FS'!J13/'Historical FS'!J67,0) -> 21.618782 | K33: =IFERROR('Historical FS'!K13/'Historical FS'!K67,0) -> 23.994951 | L33: =IFERROR(AVERAGE(C33:I33),0) -> 17.399029 | M33: =IFERROR(MEDIAN(C33:I33),0) -> 17.34314
B34: Creditor Turnover Ratio | C34: =IFERROR('Historical FS'!C13/'Historical FS'!C58,0) -> 5.9420455 | D34: =IFERROR('Historical FS'!D13/'Historical FS'!D58,0) -> 5.486395 | E34: =IFERROR('Historical FS'!E13/'Historical FS'!E58,0) -> 5.5436791 | F34: =IFERROR('Historical FS'!F13/'Historical FS'!F58,0) -> 6.3355427 | G34: =IFERROR('Historical FS'!G13/'Historical FS'!G58,0) -> 4.4694513 | H34: =IFERROR('Historical FS'!H13/'Historical FS'!H58,0) -> 6.4624814 | I34: =IFERROR('Historical FS'!I13/'Historical FS'!I58,0) -> 6.4515032 | J34: =IFERROR('Historical FS'!J13/'Historical FS'!J58,0) -> 5.2978592 | K34: =IFERROR('Historical FS'!K13/'Historical FS'!K58,0) -> 5.3358212 | L34: =IFERROR(AVERAGE(C34:I34),0) -> 5.813014 | M34: =IFERROR(MEDIAN(C34:I34),0) -> 5.9420455
B35: Inventory Turnover Ratio | C35: =IFERROR('Historical FS'!C13/'Historical FS'!C68,0) -> 29.867267 | D35: =IFERROR('Historical FS'!D13/'Historical FS'!D68,0) -> 33.94911 | E35: =IFERROR('Historical FS'!E13/'Historical FS'!E68,0) -> 31.57287 | F35: =IFERROR('Historical FS'!F13/'Historical FS'!F68,0) -> 28.132252 | G35: =IFERROR('Historical FS'!G13/'Historical FS'!G68,0) -> 18.569694 | H35: =IFERROR('Historical FS'!H13/'Historical FS'!H68,0) -> 26.93575 | I35: =IFERROR('Historical FS'!I13/'Historical FS'!I68,0) -> 23.315775 | J35: =IFERROR('Historical FS'!J13/'Historical FS'!J68,0) -> 26.570203 | K35: =IFERROR('Historical FS'!K13/'Historical FS'!K68,0) -> 24.547767 | L35: =IFERROR(AVERAGE(C35:I35),0) -> 27.477531 | M35: =IFERROR(MEDIAN(C35:I35),0) -> 28.132252
B36: Fixed Asset Turnover Ratio | C36: =IFERROR('Historical FS'!C13/'Historical FS'!C61,0) -> 10.867633 | D36: =IFERROR('Historical FS'!D13/'Historical FS'!D61,0) -> 13.421459 | E36: =IFERROR('Historical FS'!E13/'Historical FS'!E61,0) -> 17.210126 | F36: =IFERROR('Historical FS'!F13/'Historical FS'!F61,0) -> 17.609357 | G36: =IFERROR('Historical FS'!G13/'Historical FS'!G61,0) -> 16.635831 | H36: =IFERROR('Historical FS'!H13/'Historical FS'!H61,0) -> 18.052183 | I36: =IFERROR('Historical FS'!I13/'Historical FS'!I61,0) -> 12.826285 | J36: =IFERROR('Historical FS'!J13/'Historical FS'!J61,0) -> 13.946307 | K36: =IFERROR('Historical FS'!K13/'Historical FS'!K61,0) -> 13.870067 | L36: =IFERROR(AVERAGE(C36:I36),0) -> 15.231839 | M36: =IFERROR(MEDIAN(C36:I36),0) -> 16.635831
B37: Capital Turnover Ratio | C37: =IFERROR('Historical FS'!C13/SUM('Historical FS'!C55:C56),0) -> 1.2183034 | D37: =IFERROR('Historical FS'!D13/SUM('Historical FS'!D55:D56),0) -> 1.2342538 | E37: =IFERROR('Historical FS'!E13/SUM('Historical FS'!E55:E56),0) -> 1.3066144 | F37: =IFERROR('Historical FS'!F13/SUM('Historical FS'!F55:F56),0) -> 1.3811531 | G37: =IFERROR('Historical FS'!G13/SUM('Historical FS'!G55:G56),0) -> 1.0171467 | H37: =IFERROR('Historical FS'!H13/SUM('Historical FS'!H55:H56),0) -> 1.1100167 | I37: =IFERROR('Historical FS'!I13/SUM('Historical FS'!I55:I56),0) -> 1.2416031 | J37: =IFERROR('Historical FS'!J13/SUM('Historical FS'!J55:J56),0) -> 1.5492644 | K37: =IFERROR('Historical FS'!K13/SUM('Historical FS'!K55:K56),0) -> 1.4491724 | L37: =IFERROR(AVERAGE(C37:I37),0) -> 1.2155845 | M37: =IFERROR(MEDIAN(C37:I37),0) -> 1.2342538
B39: Debtor Days | C39: =IFERROR(365/C33,0) -> 15.994269 | D39: =IFERROR(365/D33,0) -> 21.599923 | E39: =IFERROR(365/E33,0) -> 30.776014 | F39: =IFERROR(365/F33,0) -> 21.045786 | G39: =IFERROR(365/G33,0) -> 35.746635 | H39: =IFERROR(365/H33,0) -> 16.698855 | I39: =IFERROR(365/I33,0) -> 17.545749 | J39: =IFERROR(365/J33,0) -> 16.883468 | K39: =IFERROR(365/K33,0) -> 15.211533 | L39: =IFERROR(AVERAGE(C39:I39),0) -> 22.772462 | M39: =IFERROR(MEDIAN(C39:I39),0) -> 21.045786
B40: Payble Days | C40: =IFERROR(365/C34,0) -> 61.426658 | D40: =IFERROR(365/D34,0) -> 66.528203 | E40: =IFERROR(365/E34,0) -> 65.840752 | F40: =IFERROR(365/F34,0) -> 57.611481 | G40: =IFERROR(365/G34,0) -> 81.665505 | H40: =IFERROR(365/H34,0) -> 56.479853 | I40: =IFERROR(365/I34,0) -> 56.575962 | J40: =IFERROR(365/J34,0) -> 68.895754 | K40: =IFERROR(365/K34,0) -> 68.40559 | L40: =IFERROR(AVERAGE(C40:I40),0) -> 63.732631 | M40: =IFERROR(MEDIAN(C40:I40),0) -> 61.426658
B41: Inventory Trunover | C41: =IFERROR(365/C35,0) -> 12.220736 | D41: =IFERROR(365/D35,0) -> 10.751386 | E41: =IFERROR(365/E35,0) -> 11.560558 | F41: =IFERROR(365/F35,0) -> 12.974432 | G41: =IFERROR(365/G35,0) -> 19.655682 | H41: =IFERROR(365/H35,0) -> 13.550764 | I41: =IFERROR(365/I35,0) -> 15.654637 | J41: =IFERROR(365/J35,0) -> 13.737193 | K41: =IFERROR(365/K35,0) -> 14.868969 | L41: =IFERROR(AVERAGE(C41:I41),0) -> 13.766885 | M41: =IFERROR(MEDIAN(C41:I41),0) -> 12.974432
B42: Cash Conversion Cycle | C42: =IFERROR(SUM(C39,C41)-C40,0) -> -33.211652 | D42: =IFERROR(SUM(D39,D41)-D40,0) -> -34.176894 | E42: =IFERROR(SUM(E39,E41)-E40,0) -> -23.50418 | F42: =IFERROR(SUM(F39,F41)-F40,0) -> -23.591263 | G42: =IFERROR(SUM(G39,G41)-G40,0) -> -26.263188 | H42: =IFERROR(SUM(H39,H41)-H40,0) -> -26.230234 | I42: =IFERROR(SUM(I39,I41)-I40,0) -> -23.375576 | J42: =IFERROR(SUM(J39,J41)-J40,0) -> -38.275093 | K42: =IFERROR(SUM(K39,K41)-K40,0) -> -38.325088 | L42: =IFERROR(AVERAGE(C42:I42),0) -> -27.193284 | M42: =IFERROR(MEDIAN(C42:I42),0) -> -26.230234
B44: CFO/Sales | C44: =IFERROR('Historical FS'!C86/'Historical FS'!C13,0) -> 0.15739113 | D44: =IFERROR('Historical FS'!#REF!/'Historical FS'!D13,0) -> 0 | E44: =IFERROR('Historical FS'!D86/'Historical FS'!E13,0) -> 0.17850537 | F44: =IFERROR('Historical FS'!E86/'Historical FS'!F13,0) -> 0.056453082 | G44: =IFERROR('Historical FS'!F86/'Historical FS'!G13,0) -> 0.15201283 | H44: =IFERROR('Historical FS'!G86/'Historical FS'!H13,0) -> 0.079017134 | I44: =IFERROR('Historical FS'!H86/'Historical FS'!I13,0) -> 0.13155809 | J44: =IFERROR('Historical FS'!I86/'Historical FS'!J13,0) -> 0.13070969 | K44: =IFERROR('Historical FS'!J86/'Historical FS'!K13,0) -> 0.13175918 | L44: =IFERROR(AVERAGE(C44:I44),0) -> 0.10784823 | M44: =IFERROR(MEDIAN(C44:I44),0) -> 0.13155809
B45: CFO/Total Asests | C45: =IFERROR('Historical FS'!C86/'Historical FS'!C72,0) -> 0.15824291 | D45: =IFERROR('Historical FS'!#REF!/'Historical FS'!D72,0) -> 0 | E45: =IFERROR('Historical FS'!D86/'Historical FS'!E72,0) -> 0.18793518 | F45: =IFERROR('Historical FS'!E86/'Historical FS'!F72,0) -> 0.063711759 | G45: =IFERROR('Historical FS'!F86/'Historical FS'!G72,0) -> 0.12549957 | H45: =IFERROR('Historical FS'!G86/'Historical FS'!H72,0) -> 0.074591562 | I45: =IFERROR('Historical FS'!H86/'Historical FS'!I72,0) -> 0.13649643 | J45: =IFERROR('Historical FS'!I86/'Historical FS'!J72,0) -> 0.14907092 | K45: =IFERROR('Historical FS'!J86/'Historical FS'!K72,0) -> 0.12417316 | L45: =IFERROR(AVERAGE(C45:I45),0) -> 0.10663963 | M45: =IFERROR(MEDIAN(C45:I45),0) -> 0.12549957
B46: CFO/Total Debt | C46: =IFERROR('Historical FS'!C86/'Historical FS'!C57,0) -> 28.557131 | D46: =IFERROR('Historical FS'!#REF!/'Historical FS'!D57,0) -> 0 | E46: =IFERROR('Historical FS'!D86/'Historical FS'!E57,0) -> 43.519113 | F46: =IFERROR('Historical FS'!E86/'Historical FS'!F57,0) -> 13.448523 | G46: =IFERROR('Historical FS'!F86/'Historical FS'!G57,0) -> 34.719249 | H46: =IFERROR('Historical FS'!G86/'Historical FS'!H57,0) -> 21.332573 | I46: =IFERROR('Historical FS'!H86/'Historical FS'!I57,0) -> 38.605812 | J46: =IFERROR('Historical FS'!I86/'Historical FS'!J57,0) -> 3.0678858 | K46: =IFERROR('Historical FS'!J86/'Historical FS'!K57,0) -> 0.71752298 | L46: =IFERROR(AVERAGE(C46:I46),0) -> 25.740343 | M46: =IFERROR(MEDIAN(C46:I46),0) -> 28.557131
B48: Return on Equity(ROE) | C48: Return on Equity(ROE) | D48: Return on Equity(ROE) | E48: Return on Equity(ROE) | F48: Return on Equity(ROE) | G48: Return on Equity(ROE) | H48: Return on Equity(ROE) | I48: Return on Equity(ROE) | L48: Return on Equity(ROE) | M48: Return on Equity(ROE)

Sheet Common Size Statement
B2: Return on Equity(ROE) | C2: Return on Equity(ROE) | D2: Return on Equity(ROE) | E2: Return on Equity(ROE) | F2: Return on Equity(ROE) | G2: Return on Equity(ROE) | H2: Return on Equity(ROE) | I2: Return on Equity(ROE) | J2: Return on Equity(ROE) | K2: Return on Equity(ROE)
B4: ='[2]Data Sheet'!B1 -> BAJAJ AUTO LTD
B5: =CONCATENATE(" ",VLOOKUP(B4,'[2]LIST OF STOCKS'!B5:D5444,3,FALSE)," | ","Bse Code: ",VLOOKUP(B4,'[2]LIST OF STOCKS'!B5:E5444,2,FALSE),) -> BAJAJ-AUTO | Bse Code: 532977
B8: ="Common Size Income Statement"&" "&" - "&'[2]Data Sheet'!$B$1 -> Common Size Income Statement - BAJAJ AUTO LTD | J8: Return on Equity(ROE) | K8: Return on Equity(ROE)
B11: Particulars | C11: ='[2]Data Sheet'!C16 -> 42825 | D11: ='[2]Data Sheet'!D16 -> 43190 | E11: ='[2]Data Sheet'!E16 -> 43555 | F11: ='[2]Data Sheet'!F16 -> 43921 | G11: ='[2]Data Sheet'!G16 -> 44286 | H11: ='[2]Data Sheet'!H16 -> 44651 | I11: ='[2]Data Sheet'!I16 -> 45016 | J11: ='[2]Data Sheet'!J16 -> 45382 | K11: ='[2]Data Sheet'!K16 -> 45747
B13: ='[2]Data Sheet'!A17 -> Sales | C13: ='[2]Data Sheet'!C17/'[2]Data Sheet'!C$17 -> 1 | D13: ='[2]Data Sheet'!D17/'[2]Data Sheet'!D$17 -> 1 | E13: ='[2]Data Sheet'!E17/'[2]Data Sheet'!E$17 -> 1 | F13: ='[2]Data Sheet'!F17/'[2]Data Sheet'!F$17 -> 1 | G13: ='[2]Data Sheet'!G17/'[2]Data Sheet'!G$17 -> 1 | H13: ='[2]Data Sheet'!H17/'[2]Data Sheet'!H$17 -> 1 | I13: ='[2]Data Sheet'!I17/'[2]Data Sheet'!I$17 -> 1 | J13: ='[2]Data Sheet'!J17/'[2]Data Sheet'!J$17 -> 1 | K13: ='[2]Data Sheet'!K17/'[2]Data Sheet'!K$17 -> 1
B14: ='[2]Data Sheet'!A18 -> Raw Material Cost | C14: ='[2]Data Sheet'!C18/'[2]Data Sheet'!C$17 -> 0.67423667 | D14: ='[2]Data Sheet'!D18/'[2]Data Sheet'!D$17 -> 0.69022048 | E14: ='[2]Data Sheet'!E18/'[2]Data Sheet'!E$17 -> 0.71988821 | F14: ='[2]Data Sheet'!F18/'[2]Data Sheet'!F$17 -> 0.70428612 | G14: ='[2]Data Sheet'!G18/'[2]Data Sheet'!G$17 -> 0.71479301 | H14: ='[2]Data Sheet'!H18/'[2]Data Sheet'!H$17 -> 0.72837747 | I14: ='[2]Data Sheet'!I18/'[2]Data Sheet'!I$17 -> 0.71927875 | J14: ='[2]Data Sheet'!J18/'[2]Data Sheet'!J$17 -> 0.71248637 | K14: ='[2]Data Sheet'!K18/'[2]Data Sheet'!K$17 -> 0.69087344
B15: ='[2]Data Sheet'!A19 -> Change in Inventory | C15: ='[2]Data Sheet'!C19/'[2]Data Sheet'!C$17 -> 0.0020078401 | D15: ='[2]Data Sheet'!D19/'[2]Data Sheet'!D$17 -> -0.00038397568 | E15: ='[2]Data Sheet'!E19/'[2]Data Sheet'!E$17 -> 0.0018585114 | F15: ='[2]Data Sheet'!F19/'[2]Data Sheet'!F$17 -> 0.0021060442 | G15: ='[2]Data Sheet'!G19/'[2]Data Sheet'!G$17 -> 0.0079117323 | H15: ='[2]Data Sheet'!H19/'[2]Data Sheet'!H$17 -> -0.0056708899 | I15: ='[2]Data Sheet'!I19/'[2]Data Sheet'!I$17 -> 0.0027521315 | J15: ='[2]Data Sheet'!J19/'[2]Data Sheet'!J$17 -> 0.0017013432 | K15: ='[2]Data Sheet'!K19/'[2]Data Sheet'!K$17 -> -0.00055711836
B16: ='[2]Data Sheet'!A20 -> Power and Fuel | C16: ='[2]Data Sheet'!C20/'[2]Data Sheet'!C$17 -> 0.0044339803 | D16: ='[2]Data Sheet'!D20/'[2]Data Sheet'!D$17 -> 0.0039770043 | E16: ='[2]Data Sheet'!E20/'[2]Data Sheet'!E$17 -> 0.0037885039 | F16: ='[2]Data Sheet'!F20/'[2]Data Sheet'!F$17 -> 0.0038962319 | G16: ='[2]Data Sheet'!G20/'[2]Data Sheet'!G$17 -> 0.0032925899 | H16: ='[2]Data Sheet'!H20/'[2]Data Sheet'!H$17 -> 0.0032587402 | I16: ='[2]Data Sheet'!I20/'[2]Data Sheet'!I$17 -> 0.0033630153 | J16: ='[2]Data Sheet'!J20/'[2]Data Sheet'!J$17 -> 0.0032970489 | K16: ='[2]Data Sheet'!K20/'[2]Data Sheet'!K$17 -> 0.0034697826
B17: ='[2]Data Sheet'!A21 -> Other Mfr. Exp | C17: ='[2]Data Sheet'!C21/'[2]Data Sheet'!C$17 -> 0.025168791 | D17: ='[2]Data Sheet'!D21/'[2]Data Sheet'!D$17 -> 0.021823147 | E17: ='[2]Data Sheet'!E21/'[2]Data Sheet'!E$17 -> 0.020884041 | F17: ='[2]Data Sheet'!F21/'[2]Data Sheet'!F$17 -> 0.023357672 | G17: ='[2]Data Sheet'!G21/'[2]Data Sheet'!G$17 -> 0.021524396 | H17: ='[2]Data Sheet'!H21/'[2]Data Sheet'!H$17 -> 0.025231176 | I17: ='[2]Data Sheet'!I21/'[2]Data Sheet'!I$17 -> 0.020396166 | J17: ='[2]Data Sheet'!J21/'[2]Data Sheet'!J$17 -> 0.016367795 | K17: ='[2]Data Sheet'!K21/'[2]Data Sheet'!K$17 -> 0.015992101
B18: ='[2]Data Sheet'!A22 -> Employee Cost | C18: ='[2]Data Sheet'!C22/'[2]Data Sheet'!C$17 -> 0.045959222 | D18: ='[2]Data Sheet'!D22/'[2]Data Sheet'!D$17 -> 0.04254633 | E18: ='[2]Data Sheet'!E22/'[2]Data Sheet'!E$17 -> 0.041515757 | F18: ='[2]Data Sheet'!F22/'[2]Data Sheet'!F$17 -> 0.046626435 | G18: ='[2]Data Sheet'!G22/'[2]Data Sheet'!G$17 -> 0.046720243 | H18: ='[2]Data Sheet'!H22/'[2]Data Sheet'!H$17 -> 0.041213213 | I18: ='[2]Data Sheet'!I22/'[2]Data Sheet'!I$17 -> 0.040819764 | J18: ='[2]Data Sheet'!J22/'[2]Data Sheet'!J$17 -> 0.036350443 | K18: ='[2]Data Sheet'!K22/'[2]Data Sheet'!K$17 -> 0.037854633
B19: ='[2]Data Sheet'!A23 -> Selling and admin | C19: ='[2]Data Sheet'!C23/'[2]Data Sheet'!C$17 -> 0.032164514 | D19: ='[2]Data Sheet'!D23/'[2]Data Sheet'!D$17 -> 0.033828733 | E19: ='[2]Data Sheet'!E23/'[2]Data Sheet'!E$17 -> 0.030994514 | F19: ='[2]Data Sheet'!F23/'[2]Data Sheet'!F$17 -> 0.034125203 | G19: ='[2]Data Sheet'!G23/'[2]Data Sheet'!G$17 -> 0.023606147 | H19: ='[2]Data Sheet'!H23/'[2]Data Sheet'!H$17 -> 0.019457102 | I19: ='[2]Data Sheet'!I23/'[2]Data Sheet'!I$17 -> 0.023387769 | J19: ='[2]Data Sheet'!J23/'[2]Data Sheet'!J$17 -> 0.022272352 | K19: ='[2]Data Sheet'!K23/'[2]Data Sheet'!K$17 -> 0.024304166
B20: ='[2]Data Sheet'!A24 -> Other Expenses | C20: ='[2]Data Sheet'!C24/'[2]Data Sheet'!C$17 -> 0.016473666 | D20: ='[2]Data Sheet'!D24/'[2]Data Sheet'!D$17 -> 0.015002422 | E20: ='[2]Data Sheet'!E24/'[2]Data Sheet'!E$17 -> 0.013564629 | F20: ='[2]Data Sheet'!F24/'[2]Data Sheet'!F$17 -> 0.019039963 | G20: ='[2]Data Sheet'!G24/'[2]Data Sheet'!G$17 -> 0.019980116 | H20: ='[2]Data Sheet'!H24/'[2]Data Sheet'!H$17 -> 0.01812959 | I20: ='[2]Data Sheet'!I24/'[2]Data Sheet'!I$17 -> 0.018176467 | J20: ='[2]Data Sheet'!J24/'[2]Data Sheet'!J$17 -> 0.015594234 | K20: ='[2]Data Sheet'!K24/'[2]Data Sheet'!K$17 -> 0.039583642
B21: ='[2]Data Sheet'!A25 -> Other Income | C21: ='[2]Data Sheet'!C25/'[2]Data Sheet'!C$17 -> 0.067461682 | D21: ='[2]Data Sheet'!D25/'[2]Data Sheet'!D$17 -> 0.055681234 | E21: ='[2]Data Sheet'!E25/'[2]Data Sheet'!E$17 -> 0.066798034 | F21: ='[2]Data Sheet'!F25/'[2]Data Sheet'!F$17 -> 0.06124541 | G21: ='[2]Data Sheet'!G25/'[2]Data Sheet'!G$17 -> 0.056583233 | H21: ='[2]Data Sheet'!H25/'[2]Data Sheet'!H$17 -> 0.080595063 | I21: ='[2]Data Sheet'!I25/'[2]Data Sheet'!I$17 -> 0.046706412 | J21: ='[2]Data Sheet'!J25/'[2]Data Sheet'!J$17 -> 0.037897787 | K21: ='[2]Data Sheet'!K25/'[2]Data Sheet'!K$17 -> 0.028867006
B22: ='[2]Data Sheet'!A26 -> Depreciation | C22: ='[2]Data Sheet'!C26/'[2]Data Sheet'!C$17 -> 0.014125211 | D22: ='[2]Data Sheet'!D26/'[2]Data Sheet'!D$17 -> 0.012487143 | E22: ='[2]Data Sheet'!E26/'[2]Data Sheet'!E$17 -> 0.0087520007 | F22: ='[2]Data Sheet'!F26/'[2]Data Sheet'!F$17 -> 0.0082366684 | G22: ='[2]Data Sheet'!G26/'[2]Data Sheet'!G$17 -> 0.009349672 | H22: ='[2]Data Sheet'!H26/'[2]Data Sheet'!H$17 -> 0.0081388553 | I22: ='[2]Data Sheet'!I26/'[2]Data Sheet'!I$17 -> 0.0078410923 | J22: ='[2]Data Sheet'!J26/'[2]Data Sheet'!J$17 -> 0.0081294073 | K22: ='[2]Data Sheet'!K26/'[2]Data Sheet'!K$17 -> 0.0081230249
B23: ='[2]Data Sheet'!A27 -> Interest | C23: ='[2]Data Sheet'!C27/'[2]Data Sheet'!C$17 -> 6.4353851e-05 | D23: ='[2]Data Sheet'!D27/'[2]Data Sheet'!D$17 -> 5.1963651e-05 | E23: ='[2]Data Sheet'!E27/'[2]Data Sheet'!E$17 -> 0.0001475741 | F23: ='[2]Data Sheet'!F27/'[2]Data Sheet'!F$17 -> 0.00010561974 | G23: ='[2]Data Sheet'!G27/'[2]Data Sheet'!G$17 -> 0.00024007717 | H23: ='[2]Data Sheet'!H27/'[2]Data Sheet'!H$17 -> 0.0002612785 | I23: ='[2]Data Sheet'!I27/'[2]Data Sheet'!I$17 -> 0.0010837907 | J23: ='[2]Data Sheet'!J27/'[2]Data Sheet'!J$17 -> 0.0013452066 | K23: ='[2]Data Sheet'!K27/'[2]Data Sheet'!K$17 -> 0.0076263052
B24: ='[2]Data Sheet'!A28 -> Profit before tax | C24: ='[2]Data Sheet'!C28/'[2]Data Sheet'!C$17 -> 0.25684311 | D24: ='[2]Data Sheet'!D28/'[2]Data Sheet'!D$17 -> 0.23536003 | E24: ='[2]Data Sheet'!E28/'[2]Data Sheet'!E$17 -> 0.22912131 | F24: ='[2]Data Sheet'!F28/'[2]Data Sheet'!F$17 -> 0.22367754 | G24: ='[2]Data Sheet'!G28/'[2]Data Sheet'!G$17 -> 0.22498872 | H24: ='[2]Data Sheet'!H28/'[2]Data Sheet'!H$17 -> 0.23085675 | I24: ='[2]Data Sheet'!I28/'[2]Data Sheet'!I$17 -> 0.21511173 | J24: ='[2]Data Sheet'!J28/'[2]Data Sheet'!J$17 -> 0.22375627 | K24: ='[2]Data Sheet'!K28/'[2]Data Sheet'!K$17 -> 0.2004828
... B27: ='[2]Data Sheet'!A31 -> Dividend Amount | C27: ='[2]Data Sheet'!C31/'[2]Data Sheet'!C$17 -> 0.073158377 | D27: ='[2]Data Sheet'!D31/'[2]Data Sheet'!D$17 -> 0.068870481 | E27: ='[2]Data Sheet'!E31/'[2]Data Sheet'!E$17 -> 0.057192212 | F27: ='[2]Data Sheet'!F31/'[2]Data Sheet'!F$17 -> 0.11606272 | G27: ='[2]Data Sheet'!G31/'[2]Data Sheet'!G$17 -> 0.14603541 | H27: ='[2]Data Sheet'!H31/'[2]Data Sheet'!H$17 -> 0.12222705 | I27: ='[2]Data Sheet'!I31/'[2]Data Sheet'!I$17 -> 0.10866544 | J27: ='[2]Data Sheet'!J31/'[2]Data Sheet'!J$17 -> 0.04977532 | K27: ='[2]Data Sheet'!K31/'[2]Data Sheet'!K$17 -> 0.1150017
B30: ="Common Size Balance sheet"&" "&" - "&'[2]Data Sheet'!$B$1 -> Common Size Balance sheet - BAJAJ AUTO LTD | J30: Return on Equity(ROE) | K30: Return on Equity(ROE)
B33: Particulars | C33: 42825 | D33: 43190 | E33: 43555 | F33: 43921 | G33: 44286 | H33: 44651 | I33: 45016 | J33: =J11 -> 45382 | K33: =K11 -> 45747
B35: Total Liabilities | C35: ='[2]Data Sheet'!C61/'[2]Data Sheet'!C$61 -> 1 | D35: ='[2]Data Sheet'!D61/'[2]Data Sheet'!D$61 -> 1 | E35: ='[2]Data Sheet'!E61/'[2]Data Sheet'!E$61 -> 1 | F35: ='[2]Data Sheet'!F61/'[2]Data Sheet'!F$61 -> 1 | G35: ='[2]Data Sheet'!G61/'[2]Data Sheet'!G$61 -> 1 | H35: ='[2]Data Sheet'!H61/'[2]Data Sheet'!H$61 -> 1 | I35: ='[2]Data Sheet'!I61/'[2]Data Sheet'!I$61 -> 1 | J35: ='[2]Data Sheet'!J61/'[2]Data Sheet'!J$61 -> 1 | K35: ='[2]Data Sheet'!K61/'[2]Data Sheet'!K$61 -> 1
B36: ='[2]Data Sheet'!A57 -> Equity Share Capital | C36: ='[2]Data Sheet'!C57/'[2]Data Sheet'!C$61 -> 0.013373467 | D36: ='[2]Data Sheet'!D57/'[2]Data Sheet'!D$61 -> 0.011509884 | E36: ='[2]Data Sheet'!E57/'[2]Data Sheet'!E$61 -> 0.010035579 | F36: ='[2]Data Sheet'!F57/'[2]Data Sheet'!F$61 -> 0.010915495 | G36: ='[2]Data Sheet'!G57/'[2]Data Sheet'!G$61 -> 0.0086117641 | H36: ='[2]Data Sheet'!H57/'[2]Data Sheet'!H$61 -> 0.0082415274 | I36: ='[2]Data Sheet'!I57/'[2]Data Sheet'!I$61 -> 0.0080531755 | J36: ='[2]Data Sheet'!J57/'[2]Data Sheet'!J$61 -> 0.0070959282 | K36: ='[2]Data Sheet'!K57/'[2]Data Sheet'!K$61 -> 0.005160976
B37: ='[2]Data Sheet'!A58 -> Reserves | C37: ='[2]Data Sheet'!C58/'[2]Data Sheet'!C$61 -> 0.81188227 | D37: ='[2]Data Sheet'!D58/'[2]Data Sheet'!D$61 -> 0.80091762 | E37: ='[2]Data Sheet'!E58/'[2]Data Sheet'!E$61 -> 0.79573121 | F37: ='[2]Data Sheet'!F58/'[2]Data Sheet'!F$61 -> 0.80621252 | G37: ='[2]Data Sheet'!G58/'[2]Data Sheet'!G$61 -> 0.80305615 | H37: ='[2]Data Sheet'!H58/'[2]Data Sheet'!H$61 -> 0.84218915 | I37: ='[2]Data Sheet'!I58/'[2]Data Sheet'!I$61 -> 0.82759015 | J37: ='[2]Data Sheet'!J58/'[2]Data Sheet'!J$61 -> 0.7290427 | K37: ='[2]Data Sheet'!K58/'[2]Data Sheet'!K$61 -> 0.6451586
B38: ='[2]Data Sheet'!A59 -> Borrowings | C38: ='[2]Data Sheet'!C59/'[2]Data Sheet'!C$61 -> 0.0055412749 | D38: ='[2]Data Sheet'!D59/'[2]Data Sheet'!D$61 -> 0.0048037071 | E38: ='[2]Data Sheet'!E59/'[2]Data Sheet'!E$61 -> 0.0043184515 | F38: ='[2]Data Sheet'!F59/'[2]Data Sheet'!F$61 -> 0.004737454 | G38: ='[2]Data Sheet'!G59/'[2]Data Sheet'!G$61 -> 0.003614697 | H38: ='[2]Data Sheet'!H59/'[2]Data Sheet'!H$61 -> 0.0034966041 | I38: ='[2]Data Sheet'!I59/'[2]Data Sheet'!I$61 -> 0.0035356446 | J38: ='[2]Data Sheet'!J59/'[2]Data Sheet'!J$61 -> 0.048590765 | K38: ='[2]Data Sheet'!K59/'[2]Data Sheet'!K$61 -> 0.1730581
B39: ='[2]Data Sheet'!A60 -> Other Liabilities | C39: ='[2]Data Sheet'!C60/'[2]Data Sheet'!C$61 -> 0.16920299 | D39: ='[2]Data Sheet'!D60/'[2]Data Sheet'!D$61 -> 0.18276878 | E39: ='[2]Data Sheet'!E60/'[2]Data Sheet'!E$61 -> 0.18991476 | F39: ='[2]Data Sheet'!F60/'[2]Data Sheet'!F$61 -> 0.17813453 | G39: ='[2]Data Sheet'!G60/'[2]Data Sheet'!G$61 -> 0.18471738 | H39: ='[2]Data Sheet'!H60/'[2]Data Sheet'!H$61 -> 0.14607272 | I39: ='[2]Data Sheet'!I60/'[2]Data Sheet'!I$61 -> 0.16082103 | J39: ='[2]Data Sheet'!J60/'[2]Data Sheet'!J$61 -> 0.21527061 | K39: ='[2]Data Sheet'!K60/'[2]Data Sheet'!K$61 -> 0.17662233
B41: Total Assets | C41: ='Historical FS'!C72/'Historical FS'!C$72 -> 1 | D41: ='Historical FS'!D72/'Historical FS'!D$72 -> 1 | E41: ='Historical FS'!E72/'Historical FS'!E$72 -> 1 | F41: ='Historical FS'!F72/'Historical FS'!F$72 -> 1 | G41: ='Historical FS'!G72/'Historical FS'!G$72 -> 1 | H41: ='Historical FS'!H72/'Historical FS'!H$72 -> 1 | I41: ='Historical FS'!I72/'Historical FS'!I$72 -> 1 | J41: ='Historical FS'!J72/'Historical FS'!J$72 -> 1 | K41: ='Historical FS'!K72/'Historical FS'!K$72 -> 1
B42: ='[2]Data Sheet'!A62 -> Net Block | C42: ='Historical FS'!C61/'Historical FS'!C$72 -> 0.092514334 | D42: ='Historical FS'!D61/'Historical FS'!D$72 -> 0.074711825 | E42: ='Historical FS'!E61/'Historical FS'!E$72 -> 0.061174825 | F42: ='Historical FS'!F61/'Historical FS'!F$72 -> 0.064089729 | G42: ='Historical FS'!G61/'Historical FS'!G$72 -> 0.049626939 | H42: ='Historical FS'!H61/'Historical FS'!H$72 -> 0.052292416 | I42: ='Historical FS'!I61/'Historical FS'!I$72 -> 0.080891496 | J42: ='Historical FS'!J61/'Historical FS'!J$72 -> 0.08177601 | K42: ='Historical FS'!K61/'Historical FS'!K$72 -> 0.067946691
B43: ='[2]Data Sheet'!A63 -> Capital Work in Progress | C43: ='Historical FS'!C62/'Historical FS'!C$72 -> 0.0019489204 | D43: ='Historical FS'!D62/'Historical FS'!D$72 -> 0.0022461318 | E43: ='Historical FS'!E62/'Historical FS'!E$72 -> 0.0016653713 | F43: ='Historical FS'!F62/'Historical FS'!F$72 -> 0.0022704623 | G43: ='Historical FS'!G62/'Historical FS'!G$72 -> 0.00047557103 | H43: ='Historical FS'!H62/'Historical FS'!H$72 -> 0.0021990128 | I43: ='Historical FS'!I62/'Historical FS'!I$72 -> 0.0024268246 | J43: ='Historical FS'!J62/'Historical FS'!J$72 -> 0.00089213798 | K43: ='Historical FS'!K62/'Historical FS'!K$72 -> 0.0011236387
B44: ='[2]Data Sheet'!A64 -> Investments | C44: ='Historical FS'!C63/'Historical FS'!C$72 -> 0.71528384 | D44: ='Historical FS'!D63/'Historical FS'!D$72 -> 0.75154409 | E44: ='Historical FS'!E63/'Historical FS'!E$72 -> 0.71452303 | F44: ='Historical FS'!F63/'Historical FS'!F$72 -> 0.75117182 | G44: ='Historical FS'!G63/'Historical FS'!G$72 -> 0.73468434 | H44: ='Historical FS'!H63/'Historical FS'!H$72 -> 0.75856457 | I44: ='Historical FS'!I63/'Historical FS'!I$72 -> 0.74517801 | J44: ='Historical FS'!J63/'Historical FS'!J$72 -> 0.71388017 | K44: ='Historical FS'!K63/'Historical FS'!K$72 -> 0.53435433
B45: ='[2]Data Sheet'!A65 -> Other Assets | C45: ='Historical FS'!C64/'Historical FS'!C$72 -> 0.098605577 | D45: ='Historical FS'!D64/'Historical FS'!D$72 -> 0.051092638 | E45: ='Historical FS'!E64/'Historical FS'!E$72 -> 0.068159189 | F45: ='Historical FS'!F64/'Historical FS'!F$72 -> 0.065344726 | G45: ='Historical FS'!G64/'Historical FS'!G$72 -> 0.0738638 | H45: ='Historical FS'!H64/'Historical FS'!H$72 -> 0.081423568 | I45: ='Historical FS'!I64/'Historical FS'!I$72 -> 0.057477918 | J45: ='Historical FS'!J64/'Historical FS'!J$72 -> 0.083493439 | K45: ='Historical FS'!K64/'Historical FS'!K$72 -> 0.26628167
B46: ='[2]Data Sheet'!A67 -> Receivables | C46: ='Historical FS'!C67/'Historical FS'!C$72 -> 0.044057064 | D46: ='Historical FS'!D67/'Historical FS'!D$72 -> 0.059340122 | E46: ='Historical FS'!E67/'Historical FS'!E$72 -> 0.088772061 | F46: ='Historical FS'!F67/'Historical FS'!F$72 -> 0.065073508 | G46: ='Historical FS'!G67/'Historical FS'!G$72 -> 0.080854516 | H46: ='Historical FS'!H67/'Historical FS'!H$72 -> 0.043187916 | I46: ='Historical FS'!I67/'Historical FS'!I$72 -> 0.049874987 | J46: ='Historical FS'!J67/'Historical FS'!J$72 -> 0.052753822 | K46: ='Historical FS'!K67/'Historical FS'!K$72 -> 0.039275977
B47: ='[2]Data Sheet'!A68 -> Inventory | C47: ='Historical FS'!C68/'Historical FS'!C$72 -> 0.033662667 | D47: ='Historical FS'!D68/'Historical FS'!D$72 -> 0.029536613 | E47: ='Historical FS'!E68/'Historical FS'!E$72 -> 0.033345922 | F47: ='Historical FS'!F68/'Historical FS'!F$72 -> 0.040116907 | G47: ='Historical FS'!G68/'Historical FS'!G$72 -> 0.044458749 | H47: ='Historical FS'!H68/'Historical FS'!H$72 -> 0.035046072 | I47: ='Historical FS'!I68/'Historical FS'!I$72 -> 0.044499373 | J47: ='Historical FS'!J68/'Historical FS'!J$72 -> 0.04292302 | K47: ='Historical FS'!K68/'Historical FS'!K$72 -> 0.038391482
B48: ='[2]Data Sheet'!A69 -> Cash & Bank | C48: ='Historical FS'!C69/'Historical FS'!C$72 -> 0.013927595 | D48: ='Historical FS'!D69/'Historical FS'!D$72 -> 0.031528579 | E48: ='Historical FS'!E69/'Historical FS'!E$72 -> 0.032359601 | F48: ='Historical FS'!F69/'Historical FS'!F$72 -> 0.011932847 | G48: ='Historical FS'!G69/'Historical FS'!G$72 -> 0.016036089 | H48: ='Historical FS'!H69/'Historical FS'!H$72 -> 0.027286442 | I48: ='Historical FS'!I69/'Historical FS'!I$72 -> 0.019651388 | J48: ='Historical FS'!J69/'Historical FS'!J$72 -> 0.024281403 | K48: ='Historical FS'!K69/'Historical FS'!K$72 -> 0.05262621
B50: Return on Equity(ROE) | C50: Return on Equity(ROE) | D50: Return on Equity(ROE) | E50: Return on Equity(ROE) | F50: Return on Equity(ROE) | G50: Return on Equity(ROE) | H50: Return on Equity(ROE) | I50: Return on Equity(ROE) | J50: Return on Equity(ROE) | K50: Return on Equity(ROE)

Sheet Beta Calculation
B2: Return on Equity(ROE) | C2: Return on Equity(ROE) | D2: Return on Equity(ROE) | E2: Return on Equity(ROE) | F2: Return on Equity(ROE) | G2: Return on Equity(ROE) | I2: Return on Equity(ROE) | L2: Return on Equity(ROE)
B4: ='[2]Data Sheet'!B1 -> BAJAJ AUTO LTD
B5: =CONCATENATE(" ",VLOOKUP(B4,'[2]LIST OF STOCKS'!B5:D5444,3,FALSE)," | ","Bse Code: ",VLOOKUP(B4,'[2]LIST OF STOCKS'!B5:E5444,2,FALSE),) -> BAJAJ-AUTO | Bse Code: 532977
B6: INR (Crs.)
B10: Regression Beta
B12: Bajaj Auto Weekly Returns | F12: NIFTY Weekly Returns | J12: Beta 1 | K12: =SLOPE(D15:D117,G15:G117) -> 0.70195173
B13: Date | C13: Closing Price | D13: Weekly Returns | F13: Closing Price | G13: Weekly Returns | J13: Beta 2 | K13: =K32 -> 0.70195173
B14: 45011 | C14: 3884.75 | F14: 17359.75
B15: 45004 | C15: 3827.9 | D15: =C15/C14-1 -> -0.014634146 | F15: 16945.05 | G15: =F15/F14-1 -> -0.023888593 | J15: SUMMARY OUTPUT
B16: 44997 | C16: 3814.4 | D16: =C16/C15-1 -> -0.0035267379 | F16: 17100.05 | G16: =F16/F15-1 -> 0.0091472141
B17: 44990 | C17: 3821.9 | D17: =C17/C16-1 -> 0.0019662332 | F17: 17412.9 | G17: =F17/F16-1 -> 0.018295268 | J17: Regression Statistics
B18: 44983 | C18: 3732 | D18: =C18/C17-1 -> -0.023522332 | F18: 17594.35 | G18: =F18/F17-1 -> 0.010420435 | J18: Multiple R | K18: 0.46195618
B19: 44976 | C19: 3849.95 | D19: =C19/C18-1 -> 0.031605038 | F19: 17465.8 | G19: =F19/F18-1 -> -0.0073063228 | J19: R Square | K19: 0.21340351
B20: 44969 | C20: 3894.3 | D20: =C20/C19-1 -> 0.01151963 | F20: 17944.2 | G20: =F20/F19-1 -> 0.027390672 | J20: Adjusted R Square | K20: 0.20561542
B21: 44962 | C21: 3831.65 | D21: =C21/C20-1 -> -0.016087615 | F21: 17856.5 | G21: =F21/F20-1 -> -0.0048873731 | J21: Standard Error | K21: 0.02753976
B22: 44955 | C22: 3852.55 | D22: =C22/C21-1 -> 0.0054545692 | F22: 17854.05 | G22: =F22/F21-1 -> -0.00013720494 | J22: Observations | K22: 103
B23: 44948 | C23: 3936.75 | D23: =C23/C22-1 -> 0.021855654 | F23: 17604.35 | G23: =F23/F22-1 -> -0.013985622
B24: 44941 | C24: 3572.75 | D24: =C24/C23-1 -> -0.092462056 | F24: 18027.65 | G24: =F24/F23-1 -> 0.024045193 | J24: ANOVA
B25: 44934 | C25: 3605.3 | D25: =C25/C24-1 -> 0.0091106291 | F25: 17956.6 | G25: =F25/F24-1 -> -0.0039411682 | K25: df | L25: SS | M25: MS | N25: F | O25: Significance F
B26: 44927 | C26: 3642.25 | D26: =C26/C25-1 -> 0.0102488 | F26: 17859.45 | G26: =F26/F25-1 -> -0.005410267 | J26: Regression | K26: 1 | L26: 0.020782186 | M26: 0.020782186 | N26: 27.401285 | O26: 9.020068e-07
B27: 44920 | C27: 3616.05 | D27: =C27/C26-1 -> -0.0071933558 | F27: 18105.3 | G27: =F27/F26-1 -> 0.013765821 | J27: Residual | K27: 101 | L27: 0.076602277 | M27: 0.00075843839
B28: 44913 | C28: 3541.8 | D28: =C28/C27-1 -> -0.020533455 | F28: 17806.8 | G28: =F28/F27-1 -> -0.016486885 | J28: Total | K28: 102 | L28: 0.097384463
B29: 44906 | C29: 3549.6 | D29: =C29/C28-1 -> 0.00220227 | F29: 18269 | G29: =F29/F28-1 -> 0.025956376
B30: 44899 | C30: 3616.95 | D30: =C30/C29-1 -> 0.018973969 | F30: 18496.6 | G30: =F30/F29-1 -> 0.012458263 | K30: Coefficients | L30: Standard Error | M30: t Stat | N30: P-value | O30: Lower 95% | P30: Upper 95% | Q30: Lower 95.0% | R30: Upper 95.0%
B31: 44892 | C31: 3659.35 | D31: =C31/C30-1 -> 0.011722584 | F31: 18696.1 | G31: =F31/F30-1 -> 0.010785766 | J31: Intercept | K31: 0.0007987863 | L31: 0.0027193486 | M31: 0.29374178 | N31: 0.76955799 | O31: -0.0045956697 | P31: 0.0061932423 | Q31: -0.0045956697 | R31: 0.0061932423
B32: 44885 | C32: 3640.25 | D32: =C32/C31-1 -> -0.0052195062 | F32: 18512.75 | G32: =F32/F31-1 -> -0.0098068581 | J32: X Variable 1 | K32: 0.70195173 | L32: 0.13409784 | M32: 5.2346236 | N32: 9.020068e-07 | O32: 0.43593769 | P32: 0.96796577 | Q32: 0.43593769 | R32: 0.96796577
B33: 44878 | C33: 3632.95 | D33: =C33/C32-1 -> -0.0020053568 | F33: 18307.65 | G33: =F33/F32-1 -> -0.011078851
B34: 44871 | C34: 3727.65 | D34: =C34/C33-1 -> 0.02606697 | F34: 18349.7 | G34: =F34/F33-1 -> 0.002296854
B35: 44864 | C35: 3771.1 | D35: =C35/C34-1 -> 0.011656137 | F35: 18117.15 | G35: =F35/F34-1 -> -0.012673232
B36: 44857 | C36: 3670.7 | D36: =C36/C35-1 -> -0.026623532 | F36: 17786.8 | G36: =F36/F35-1 -> -0.018234104
B37: 44850 | C37: 3668.6 | D37: =C37/C36-1 -> -0.00057209796 | F37: 17576.3 | G37: =F37/F36-1 -> -0.011834619
B38: 44843 | C38: 3570.5 | D38: =C38/C37-1 -> -0.026740446 | F38: 17185.7 | G38: =F38/F37-1 -> -0.022223107
B39: 44836 | C39: 3603.55 | D39: =C39/C38-1 -> 0.0092564067 | F39: 17314.65 | G39: =F39/F38-1 -> 0.0075033313
B40: 44829 | C40: 3527.75 | D40: =C40/C39-1 -> -0.021034813 | F40: 17094.35 | G40: =F40/F39-1 -> -0.01272333
B41: 44822 | C41: 3698.9 | D41: =C41/C40-1 -> 0.048515343 | F41: 17327.35 | G41: =F41/F40-1 -> 0.013630235
B42: 44815 | C42: 3689.55 | D42: =C42/C41-1 -> -0.0025277785 | F42: 17530.85 | G42: =F42/F41-1 -> 0.011744439
B43: 44808 | C43: 3848.6 | D43: =C43/C42-1 -> 0.043108238 | F43: 17833.35 | G43: =F43/F42-1 -> 0.017255296
B44: 44801 | C44: 4030.9 | D44: =C44/C43-1 -> 0.047367874 | F44: 17539.45 | G44: =F44/F43-1 -> -0.016480358
... B117: 44290 | C117: 3651.3 | D117: =C117/C116-1 -> 0.0045809088 | F117: 14834.85 | G117: =F117/F116-1 -> 0.014844864

Sheet WACC
B2: Return on Equity(ROE) | C2: Return on Equity(ROE) | D2: Return on Equity(ROE) | E2: Return on Equity(ROE) | F2: Return on Equity(ROE) | G2: Return on Equity(ROE) | H2: Return on Equity(ROE) | I2: Return on Equity(ROE) | L2: Return on Equity(ROE) | M2: Return on Equity(ROE)
B4: ='[2]Data Sheet'!B1 -> BAJAJ AUTO LTD
B5: =CONCATENATE(" ",VLOOKUP(B4,'[2]LIST OF STOCKS'!B5:D5444,3,FALSE)," | ","Bse Code: ",VLOOKUP(B4,'[2]LIST OF STOCKS'!B5:E5444,2,FALSE),) -> BAJAJ-AUTO | Bse Code: 532977
B8: Weighted Average cost of capital
B11: All figures in INR unless stated otherwise
B12: Peer Comps
H13: Debt / | I13: Debt / | J13: Levered | K13: Unlevered
B14: Name of the comp | D14: Country | E14: Total Equity | F14: Total Debt | G14: Tax Rate 1 | H14: Equity | I14: Capital | J14: Beta 2 | K14: Beta 3
B16: Bajaj Auto | D16: India | E16: 248803 | F16: 19693 | G16: 0.3 | H16: =IFERROR(F16/E16,0) -> 0.079150975 | I16: =IFERROR(F16/(F16+E16),0) -> 0.073345599 | J16: 0.73 | K16: =J16/(1+(1-G16)*H16) -> 0.69167716
B17: Eicher Motors | D17: India | E17: 186896 | F17: 446 | G17: 0.3 | H17: =IFERROR(F17/E17,0) -> 0.0023863539 | I17: =IFERROR(F17/(F17+E17),0) -> 0.0023806728 | J17: 0.07 | K17: =J17/(1+(1-G17)*H17) -> 0.069883264
B18: TVS Motor Co. | D18: India | E18: 165242 | F18: 16862 | G18: 0.3 | H18: =IFERROR(F18/E18,0) -> 0.10204427 | I18: =IFERROR(F18/(F18+E18),0) -> 0.09259544 | J18: -0.06 | K18: =J18/(1+(1-G18)*H18) -> -0.055999873
B19: Hero Motocorp | D19: India | E19: 161025 | F19: 718 | G19: 0.3 | H19: =IFERROR(F19/E19,0) -> 0.0044589349 | I19: =IFERROR(F19/(F19+E19),0) -> 0.0044391411 | J19: 0.71 | K19: =J19/(1+(1-G19)*H19) -> 0.7077908
F21: Average | G21: =AVERAGE(G16:G19) -> 0.3 | H21: =AVERAGE(H16:H19) -> 0.047010135 | I21: =AVERAGE(I16:I19) -> 0.043190213 | J21: =AVERAGE(J16:J19) -> 0.3625 | K21: =AVERAGE(K16:K19) -> 0.35333784
F22: Median | G22: =MEDIAN(G16:G19) -> 0.3 | H22: =MEDIAN(H16:H19) -> 0.041804955 | I22: =MEDIAN(I16:I19) -> 0.03889237 | J22: =MEDIAN(J16:J19) -> 0.39 | K22: =MEDIAN(K16:K19) -> 0.38078021
B24: Cost of Debt | G24: Cost of Equity
B26: Pre-Tax Cost of Debt | E26: 0.084 | G26: Risk free Rate | K26: 0.0739
B27: Tax Rate | E27: =G21 -> 0.3 | G27: Equity risk Premium | K27: 0.0802
B28: Post Tax Cost of Debt | E28: =E26*(1-E27) -> 0.0588 | G28: Levered Beta 4 | K28: =K37 -> 0.39331058
G29: Cost of Equity | K29: =K26+K27*K28 -> 0.10544351
B32: Capital Structure | G32: Levered Beta
D34: Current | E34: Target | G34: Comps Median Unlevered Beta | K34: =K22 -> 0.38078021
B35: Total Debt | C35: =F16 -> 19693 | D35: =C35/$C$37 -> 0.073345599 | E35: =I21 -> 0.043190213 | G35: Target Debt / Equity | K35: =H21 -> 0.047010135
B36: Market capitalization | C36: =E16 -> 248803 | D36: =C36/$C$37 -> 0.9266544 | E36: =E37-E35 -> 0.95680979 | G36: Tax Rate | K36: 0.3
B37: Total capital | C37: =SUM(C35:C36) -> 268496 | D37: =SUM(D35:D36) -> 1 | E37: =D37 -> 1 | G37: Levered Beta | K37: =K34*(1+(1-K36)*K35) -> 0.39331058
B40: Debt/Equity | D40: =D35/D36 -> 0.079150975 | E40: =E35/E36 -> 0.045139811 | G40: Weighted average Cost of Capital
J42: Total Cost | K42: Total weight
B43: Notes: | G43: Debt | J43: =E28 -> 0.0588 | K43: =E35 -> 0.043190213
B44: 1. Tax Rate considered as Marginal Tax Rate for the country | G44: Equity | J44: =K29 -> 0.10544351 | K44: =E36 -> 0.95680979
B45: 2. Levered Beta is based on 5 year monthly data. | G45: Weighted Average cost of capital | K45: =SUMPRODUCT(J43:J44,K43:K44) -> 0.10342897
B46: 3. Unlevered Beta = Levered Beta/(1+(1-tax rate)*Debt/Equity)
B47: 4. Levered Beta = Unlevered Beta*(1+(1-tax rate)*Debt/Equity)

Sheet Relative Valuation
B2: Return on Equity(ROE) | C2: Return on Equity(ROE) | D2: Return on Equity(ROE) | E2: Return on Equity(ROE) | F2: Return on Equity(ROE) | G2: Return on Equity(ROE) | H2: Return on Equity(ROE) | I2: Return on Equity(ROE) | L2: Return on Equity(ROE) | M2: Return on Equity(ROE) | N2: Return on Equity(ROE) | O2: Return on Equity(ROE) | P2: Return on Equity(ROE)
B4: ='[2]Data Sheet'!B1 -> BAJAJ AUTO LTD
B5: =CONCATENATE(" ",VLOOKUP(B4,'[2]LIST OF STOCKS'!B5:D5444,3,FALSE)," | ","Bse Code: ",VLOOKUP(B4,'[2]LIST OF STOCKS'!B5:E5444,2,FALSE),) -> BAJAJ-AUTO | Bse Code: 532977
B6: INR(Crs.)
D7: Market Data | K7: Financials | O7: Valuation
B8: Company | C8: Ticker | D8: Share Price | E8: Share Outstanding | F8: Equity Value | G8: Net Debt | H8: Enterprise Value | J8: Revenue | K8: EBITDA | L8: Net Income | N8: EV/Revenue | O8: EV/EBITDA | P8: P/E
B10: Maruti Suzuki | C10: MARUTI | D10: =[4]Data!D7 -> 15977 | E10: =[4]Data!N7 -> 368.23 | F10: =E10*D10 -> 5883210.7 | G10: =[4]Data!P7 -> -453 | H10: =[4]Data!Q7 -> 501918.87 | J10: =[4]Data!G7 -> 160633.8 | K10: =[4]Data!M7 -> 42178 | L10: =[4]Data!H7 -> 14779.4 | N10: =$H10/J10 -> 3.1246156 | O10: =$H10/K10 -> 11.900016 | P10: =F10/L10 -> 398.06831
B11: M & M | C11: M&M | D11: =[4]Data!D8 -> 3749.6 | E11: =[4]Data!N8 -> 124.35 | F11: =E11*D11 -> 466262.76 | G11: =[4]Data!P8 -> 106094.49 | H11: =[4]Data!Q8 -> 572455.89 | J11: =[4]Data!G8 -> 175704.22 | K11: =[4]Data!M8 -> 37698.07 | L11: =[4]Data!H8 -> 15506.66 | N11: =$H11/J11 -> 3.2580657 | O11: =$H11/K11 -> 15.185284 | P11: =F11/L11 -> 30.068549
B12: Bajaj Auto | C12: BAJAJ-AUTO | D12: =[4]Data!D9 -> 8892 | E12: =[4]Data!N9 -> 31.44 | F12: =E12*D12 -> 279564.48 | G12: =[4]Data!P9 -> 16845.64 | H12: =[4]Data!Q9 -> 265044.03 | J12: =[4]Data!G9 -> 54683.29 | K12: =[4]Data!M9 -> 25274.2 | L12: =[4]Data!H9 -> 8329.97 | N12: =$H12/J12 -> 4.8468925 | O12: =$H12/K12 -> 10.486743 | P12: =F12/L12 -> 33.561283
B13: Eicher Motors | C13: EICHERMOT | D13: =[4]Data!D10 -> 7134.5 | E13: =[4]Data!N10 -> 81.25 | F13: =E13*D13 -> 579678.12 | G13: =[4]Data!P10 -> 182.77 | H13: =[4]Data!Q10 -> 195915.9 | J13: =[4]Data!G10 -> 21427.66 | K13: =[4]Data!M10 -> 9733.66 | L13: =[4]Data!H10 -> 5107.32 | N13: =$H13/J13 -> 9.1431309 | O13: =$H13/K13 -> 20.12767 | P13: =F13/L13 -> 113.49947
B14: Hyundai Motor I | C14: HYUNDAI | D14: =[4]Data!D11 -> 2335.9 | E14: =[4]Data!N11 -> 47.51 | F14: =E14*D14 -> 110978.61 | G14: =[4]Data!P11 -> -7278.79 | H14: =[4]Data!Q11 -> 182559.23 | J14: =[4]Data!G11 -> 66889.41 | K14: =[4]Data!M11 -> 7472.24 | L14: =[4]Data!H11 -> 5612.65 | N14: =$H14/J14 -> 2.7292696 | O14: =$H14/K14 -> 24.43166 | P14: =F14/L14 -> 19.772943
B15: TVS Motor Co. | C15: TVSMOTOR | D15: =[4]Data!D12 -> 3441.9 | E15: =[4]Data!N12 -> 20.01 | F15: =E15*D15 -> 68872.419 | G15: =[4]Data!P12 -> 12475.62 | H15: =[4]Data!Q12 -> 176024 | J15: =[4]Data!G12 -> 48838.15 | K15: =[4]Data!M12 -> 7867.06 | L15: =[4]Data!H12 -> 2782.48 | N15: =$H15/J15 -> 3.6042315 | O15: =$H15/K15 -> 22.374813 | P15: =F15/L15 -> 24.75217
B16: Tata Motors PVeh | C16: TATAMOTOR | D16: =[4]Data!D13 -> 362.25 | E16: =[4]Data!N13 -> 27.43 | F16: =E16*D16 -> 9936.5175 | G16: =[4]Data!P13 -> 26424 | H16: =[4]Data!Q13 -> 159834.99 | J16: =[4]Data!G13 -> 392137 | K16: =[4]Data!M13 -> 7343.23 | L16: =[4]Data!H13 -> 94292 | N16: =$H16/J16 -> 0.40759987 | O16: =$H16/K16 -> 21.766306 | P16: =F16/L16 -> 0.10538028
B17: Hero Motocorp | C17: HEROMOTOCO | D17: =[4]Data!D14 -> 6002.5 | E17: =[4]Data!N14 -> 441.08 | F17: =E17*D17 -> 2647582.7 | G17: =[4]Data!P14 -> 143.99 | H17: =[4]Data!Q14 -> 120225.96 | J17: =[4]Data!G14 -> 42175.84 | K17: =[4]Data!M14 -> -1217 | L17: =[4]Data!H14 -> 5303.76 | N17: =$H17/J17 -> 2.8505884 | O17: =$H17/K17 -> -98.788792 | P17: =F17/L17 -> 499.18976
B18: Ather Energy | C18: ATHR(NSE) | D18: =[4]Data!D15 -> 695.9 | E18: =[4]Data!N15 -> 27.93 | F18: =E18*D18 -> 19436.487 | G18: =[4]Data!P15 -> 59.9 | H18: =[4]Data!Q15 -> 26467.03 | J18: =[4]Data!G15 -> 2854.5 | K18: =[4]Data!M15 -> 12554.75 | L18: =[4]Data!H15 -> -764.5 | N18: =$H18/J18 -> 9.2720371 | O18: =$H18/K18 -> 2.1081288 | P18: =F18/L18 -> -25.423789
B19: Force Motors | C19: FORCEMOT | D19: =[4]Data!D16 -> 16901 | E19: =[4]Data!N16 -> 1.32 | F19: =E19*D19 -> 22309.32 | G19: =[4]Data!P16 -> -507.41 | H19: =[4]Data!Q16 -> 21763.06 | J19: =[4]Data!G16 -> 8624.15 | K19: =[4]Data!M16 -> 1340.65 | L19: =[4]Data!H16 -> 1077.14 | N19: =$H19/J19 -> 2.523502 | O19: =$H19/K19 -> 16.233215 | P19: =F19/L19 -> 20.711625
B21: High | N21: =MAX(N10:N19) -> 9.2720371 | O21: =MAX(O10:O19) -> 24.43166 | P21: =MAX(P10:P19) -> 499.18976
B22: 75th percentile | N22: =QUARTILE(N10:N19,3) -> 4.5362273 | O22: =QUARTILE(O10:O19,3) -> 21.356647 | P22: =QUARTILE(P10:P19,3) -> 93.514925
B23: Average | N23: =AVERAGE(N10:N19) -> 4.1759933 | O23: =AVERAGE(O10:O19) -> 4.5825044 | P23: =AVERAGE(P10:P19) -> 111.43057
B24: Median | N24: =MEDIAN(N10:N19) -> 3.1913406 | O24: =MEDIAN(O10:O19) -> 15.709249 | P24: =MEDIAN(P10:P19) -> 27.410359
B25: 25th percentile | N25: =QUARTILE(N10:N19,1) -> 2.7595993 | O25: =QUARTILE(O10:O19,1) -> 10.840061 | P25: =QUARTILE(P10:P19,1) -> 20.007614
B26: Low | N26: =MIN(N10:N19) -> 0.40759987 | O26: =MIN(O10:O19) -> -98.788792 | P26: =MIN(P10:P19) -> -25.423789
B28: Bajaj Auto Comparable valuation | N28: EV/Revenue | O28: EV/EBITDA | P28: P/E
B29: Implied Enterprise Value | N29: =N$24*J12 -> 174513 | O29: =O$24*K12 -> 397038.71 | P29: =P30+P31 -> 245173.11
B30: Net Debt | N30: =$G$12 -> 16845.64 | O30: =$G$12 -> 16845.64 | P30: =$G$12 -> 16845.64
B31: Implied Market Value | N31: =N29-N30 -> 157667.36 | O31: =O29-O30 -> 380193.07 | P31: =P24*L12 -> 228327.47
B32: Share Outstanding | N32: =$E$12 -> 31.44 | O32: =$E$12 -> 31.44 | P32: =$E$12 -> 31.44
B33: Implied Value per Share | N33: =N31/N32 -> 5014.8653 | O33: =O31/O32 -> 12092.655 | P33: =P31/P32 -> 7262.3242
B35: Soruce: The Valuation School, Screener.in | N35: =IF(N33>$D$12, "Undervalued","Overvalued") -> Overvalued | O35: =IF(O33>$D$12, "Undervalued","Overvalued") -> Undervalued | P35: =IF(P33>$D$12, "Undervalued","Overvalued") -> Overvalued

Sheet DCF
B2: Return on Equity(ROE) | C2: Return on Equity(ROE) | D2: Return on Equity(ROE) | E2: Return on Equity(ROE) | F2: Return on Equity(ROE) | G2: Return on Equity(ROE) | H2: Return on Equity(ROE) | I2: Return on Equity(ROE) | L2: Return on Equity(ROE) | M2: Return on Equity(ROE)
B4: ='[2]Data Sheet'!B1 -> BAJAJ AUTO LTD
B5: =CONCATENATE(" ",VLOOKUP(B4,'[2]LIST OF STOCKS'!B5:D5444,3,FALSE)," | ","Bse Code: ",VLOOKUP(B4,'[2]LIST OF STOCKS'!B5:E5444,2,FALSE),) -> BAJAJ-AUTO | Bse Code: 532977
B8: ="Intrinsic Valuation – Discounted Cash Flow (DCF) - "&'[3]Data Sheet'!$B$1 -> Intrinsic Valuation – Discounted Cash Flow (DCF) - BAJAJ AUTO LTD
B9: Calculation of PV of FCFF | F9: ='[4]Intrinsic Growth'!J8 -> 44986 | G9: =F9+366 -> 45352 | H9: =G9+366 -> 45718 | I9: =H9+366 -> 46084 | J9: =I9+366 -> 46450 | K9: =J9+366 -> 46816 | L9: =K9+366 -> 47182 | M9: =L9+366 -> 47548
B12: EBIT | F12: ='[2]Historical FS'!C34+'[2]Historical FS'!C28 -> 4033.9799 | G12: ='[2]Historical FS'!D34+'[2]Historical FS'!D28 -> 4550.3599 | H12: ='[2]Historical FS'!E34+'[2]Historical FS'!E28 -> 4819.3899 | I12: ='[2]Historical FS'!F34+'[2]Historical FS'!F28 -> 4736.8899 | J12: ='[2]Historical FS'!G34+'[2]Historical FS'!G28 -> 4239.4498 | K12: ='[2]Historical FS'!H34+'[2]Historical FS'!H28 -> 5364.9597 | L12: ='[2]Historical FS'!I34+'[2]Historical FS'!I28 -> 5978.1289 | M12: ='[2]Historical FS'!J34+'[2]Historical FS'!J28 -> 8247.2287
B13: Tax Rate | F13: 0.25 | G13: =F13 -> 0.25 | H13: =G13 -> 0.25 | I13: =H13 -> 0.25 | J13: =I13 -> 0.25 | K13: =J13 -> 0.25 | L13: =K13 -> 0.25 | M13: =L13 -> 0.25
B14: EBIT(1-T) | F14: =F12*(1-F13) -> 3025.485 | G14: =G12*(1-G13) -> 3412.77 | H14: =H12*(1-H13) -> 3614.5424 | I14: =I12*(1-I13) -> 3552.6674 | J14: =J12*(1-J13) -> 3179.5873 | K14: =K12*(1-K13) -> 4023.7198 | L14: =L12*(1-L13) -> 4483.5967 | M14: =M12*(1-M13) -> 6185.4215
B15: Less: Reinvestment Rate | F15: 0.384 | G15: =F15 -> 0.384 | H15: =G15 -> 0.384 | I15: =H15 -> 0.384 | J15: =I15 -> 0.384 | K15: =J15 -> 0.384 | L15: =K15 -> 0.384 | M15: =L15 -> 0.384
B16: Free Cash Flow to Firm(FCFF) | F16: =F14*(1-F15) -> 1863.6987 | G16: =G14*(1-G15) -> 2102.2663 | H16: =H14*(1-H15) -> 2226.5581 | I16: =I14*(1-I15) -> 2188.4431 | J16: =J14*(1-J15) -> 1958.6258 | K16: =K14*(1-K15) -> 2478.6114 | L16: =L14*(1-L15) -> 2761.8956 | M16: =M14*(1-M15) -> 3810.2196
B17: Mid year Convention | G17: 0.5 | H17: =G17+1 -> 1.5 | I17: =H17+1 -> 2.5 | J17: =I17+1 -> 3.5 | K17: =J17+1 -> 4.5 | L17: =K17+1 -> 5.5 | M17: =L17+1 -> 6.5
B18: Discounting Factor | G18: =1/(1+$E$24)^G17 -> 0.95197997 | H18: =1/(1+$E$24)^H17 -> 0.86274694 | I18: =1/(1+$E$24)^I17 -> 0.7818781 | J18: =1/(1+$E$24)^J17 -> 0.70858943 | K18: =1/(1+$E$24)^K17 -> 0.64217041 | L18: =1/(1+$E$24)^L17 -> 0.58197712 | M18: =1/(1+$E$24)^M17 -> 0.52742599
B20: PV of FCFF | G20: =G16*G18 -> 2001.3154 | H20: =H16*H18 -> 1920.9562 | I20: =I16*I18 -> 1711.0958 | J20: =J16*J18 -> 1387.8615 | K20: =K16*K18 -> 1591.6909 | L20: =L16*L18 -> 1607.36 | M20: =M16*M18 -> 2009.6089
B22: Expected Growth | E22: 0.281
B23: Terminal Growth | E23: 0.03
B24: WACC | E24: =WACC!K45 -> 0.10342897
B26: Calculation of Terminal Value | G26: Sensitivity Analysis
B28: FCFF(n+1) | E28: =M16*(1+E22) -> 4880.8914 | G28: =E32 -> 66470.926 | H28: 0.055 | I28: 0.1034 | J28: 0.15 | K28: 0.2 | L28: 0.25
B29: WACC | E29: =E24 -> 0.10342897 | G29: 0.01 | H29: 108464.25 | I29: 52257.937 | J29: 34863.51 | K29: 25688.902 | L29: 20337.047
B30: Terminal Growth Rate | E30: =E23 -> 0.03 | G30: 0.02 | H30: 139454.04 | I30: 58523.877 | J30: 37545.318 | K30: 27116.063 | L30: 21221.267
G31: 0.03 | H31: 195235.65 | I31: 66497.157 | J31: 40674.095 | K31: 28711.126 | L31: 22185.87
B32: Terminal Value | E32: =E28/(E29-E30) -> 66470.926 | G32: 0.04 | H32: 325392.76 | I32: 76985.668 | J32: 44371.74 | K32: 30505.571 | L32: 23242.34
G33: 0.05 | H33: 976178.27 | I33: 91402.46 | J33: 48808.914 | K33: 32539.276 | L33: 24404.457
B35: Calculation of Equity Value
B37: PV of FCFF | E37: =SUM(G20:M20) -> 12229.889
B38: Pv of Terminal value | E38: =E32*M18 -> 35058.494
B39: Terminal Growth Rate | E39: =E32 -> 66470.926
B40: Value of Operating Asset | E40: =SUM(E37:E39) -> 113759.31
B42: Add: Cash | E42: ='[3]Data Sheet'!$I$69 -> 690.48
B43: Less: Debt | E43: =('[4]Raw Data Bajaj Auto '!L15) -> 124
B44: Value of Equity | E44: =E37+E42-E43 -> 12796.369
B45: No. of shares | E45: ='[3]Data Sheet'!$B$6 -> 27.925761
B47: Equity Value per share | E47: =E44/E45 -> 458.22811
B49: Share price | E49: 8984
B50: Discount/Premium | E50: =E49/E47-1 -> 18.605955
B51: Times | E51: =E49/E47-1 -> 18.605955

Sheet Var
C1: Return on Equity(ROE) | D1: Return on Equity(ROE) | E1: Return on Equity(ROE) | F1: Return on Equity(ROE) | G1: Return on Equity(ROE) | H1: Return on Equity(ROE) | I1: Return on Equity(ROE) | J1: Return on Equity(ROE) | K1: Return on Equity(ROE) | L1: Return on Equity(ROE) | M1: Return on Equity(ROE) | N1: Return on Equity(ROE)
C3: Bajaj Auto LTD
C4: BAJAJ AUTO | BSE CODE: 532977
L7: Return on Equity(ROE) | M7: Return on Equity(ROE) | N7: Return on Equity(ROE)
C10: Date | D10: Adjust Close | E10: Returns | F10: Sorted returns | G10: Replication | H10: Simulated Returns | J10: Calculation of value at Risk - Bajaj Auto (Historical Data)
C13: 45219 | D13: 5482.6 | E13: =(D13-D14)/D14 -> 0.068628789 | F13: 0.067193522 | G13: 1 | H13: =NORMINV(RAND(),N$15,N$16) -> -0.025377868 | J13: Historical Approach
C14: 45187 | D14: 5130.5 | E14: =(D14-D15)/D15 -> 0.049160549 | F14: 0.05903602 | G14: 2 | H14: =NORMINV(RAND(),N$15,N$16) -> -0.0021098547
C15: 45113 | D15: 4890.1 | E15: =(D15-D16)/D16 -> -0.35635406 | F15: 0.057227483 | G15: 3 | H15: =NORMINV(RAND(),N$15,N$16) -> 0.01422193 | J15: Mean | N15: =AVERAGE(F13:F256) -> 0.003510795
C16: 45320 | D16: 7597.5 | E16: =(D16-D17)/D17 -> 0.087454376 | F16: 0.053321133 | G16: 4 | H16: =NORMINV(RAND(),N$15,N$16) -> 0.0086182276 | J16: Std Deviation | N16: =STDEV(F13:F256) -> 0.014393422
C17: 45295 | D17: 6986.5 | E17: =(D17-D18)/D18 -> 0.041253707 | F17: 0.048221332 | G17: 5 | H17: =NORMINV(RAND(),N$15,N$16) -> -0.00049527598 | J17: Min | N17: =MIN(F13:F256) -> -0.034107978
C18: 45288 | D18: 6709.7 | E18: =(D18-D19)/D19 -> -0.080724493 | F18: 0.037914179 | G18: 6 | H18: =NORMINV(RAND(),N$15,N$16) -> -0.003645265 | J18: Max | N18: =MAX(F13:F256) -> 0.067193522
C19: 45303 | D19: 7298.9 | E19: =(D19-D20)/D20 -> -0.14115432 | F19: 0.034747228 | G19: 7 | H19: =NORMINV(RAND(),N$15,N$16) -> -0.015928789 | J19: current market price | N19: 8890
C20: 45345 | D20: 8498.5 | E20: =(D20-D21)/D21 -> -0.042864705 | F20: 0.032336042 | G20: 8 | H20: =NORMINV(RAND(),N$15,N$16) -> 0.0027763258
C21: 45362 | D21: 8879.1 | E21: =(D21-D22)/D22 -> 0.031757652 | F21: 0.031757652 | G21: 9 | H21: =NORMINV(RAND(),N$15,N$16) -> 0.015003798 | J21: Monte Carlo Simulation
C22: 45358 | D22: 8605.8 | E22: =(D22-D23)/D23 -> 0.33099278 | F22: 0.030412606 | G22: 10 | H22: =NORMINV(RAND(),N$15,N$16) -> 0.0074066497
C23: 45279 | D23: 6465.7 | E23: =(D23-D24)/D24 -> 0.091202133 | F23: 0.030357598 | G23: 11 | H23: =NORMINV(RAND(),N$15,N$16) -> 0.00096230563 | J23: Mean | N23: =AVERAGE(H13:H256) -> 0.0023533232
C24: 45254 | D24: 5925.3 | E24: =(D24-D25)/D25 -> 0.41841815 | F24: 0.030200292 | G24: 12 | H24: =NORMINV(RAND(),N$15,N$16) -> 0.0095137021 | J24: Std Deviation | N24: =STDEV(H13:H256) -> 0.014310432
C25: 45028 | D25: 4177.4 | E25: =(D25-D26)/D26 -> -0.10047373 | F25: 0.028510932 | G25: 13 | H25: =NORMINV(RAND(),N$15,N$16) -> 0.012984465 | J25: Min | N25: =MIN(H13:H256) -> -0.034546371
C26: 45072 | D26: 4644 | E26: =(D26-D27)/D27 -> 0.083527765 | F26: 0.027979458 | G26: 14 | H26: =NORMINV(RAND(),N$15,N$16) -> 0.046537302 | J26: Max | N26: =MAX(H13:H256) -> 0.046537302
C27: 45029 | D27: 4286 | E27: =(D27-D28)/D28 -> -0.30889917 | F27: 0.025997032 | G27: 15 | H27: =NORMINV(RAND(),N$15,N$16) -> -0.010616537 | J27: current market price | N27: 8890
C28: 45265 | D28: 6201.7 | E28: =(D28-D29)/D29 -> 0.40685541 | F28: 0.025735598 | G28: 16 | H28: =NORMINV(RAND(),N$15,N$16) -> 0.0068914488
C29: 45044 | D29: 4408.2 | E29: =(D29-D30)/D30 -> -0.47049285 | F29: 0.025401256 | G29: 17 | H29: =NORMINV(RAND(),N$15,N$16) -> -0.00028575425 | J29: Confidence | K29: Percentile | L29: Var | M29: Stock Price | N29: VAR INR
C30: 45341 | D30: 8325.1 | E30: =(D30-D31)/D31 -> -0.09139427 | F30: 0.024867354 | G30: 18 | H30: =NORMINV(RAND(),N$15,N$16) -> 0.0050452919
C31: 45379 | D31: 9162.5 | E31: =(D31-D32)/D32 -> 0.024280907 | F31: 0.022531973 | G31: 19 | H31: =NORMINV(RAND(),N$15,N$16) -> 0.0069048846 | J31: =100%-K31 -> 0.95 | K31: 0.05 | L31: =PERCENTILE(F$13:$F$256,K31) -> -0.016841703 | M31: =N$19*(1-L31) -> 9039.7227 | N31: =$N$19-M31 -> -149.72274
C32: 45377 | D32: 8945.3 | E32: =(D32-D33)/D33 -> 0.051188644 | F32: 0.022249903 | G32: 20 | H32: =NORMINV(RAND(),N$15,N$16) -> 0.016142869 | J32: =100%-K32 -> 0.99 | K32: 0.01 | L32: =PERCENTILE(F$13:$F$256,K32) -> -0.025007426 | M32: =N$19*(1-L32) -> 9112.316 | N32: =$N$19-M32 -> -222.31602
C33: 45342 | D33: 8509.7 | E33: =(D33-D34)/D34 -> 0.58361248 | F33: 0.022173908 | G33: 21 | H33: =NORMINV(RAND(),N$15,N$16) -> 0.0049924215 | J33: =100%-K33 -> 0.995 | K33: 0.005 | L33: =PERCENTILE(F$13:$F$256,K33) -> -0.030907441 | M33: =N$19*(1-L33) -> 9164.7671 | N33: =$N$19-M33 -> -274.76715
C34: 45229 | D34: 5373.6 | E34: =(D34-D35)/D35 -> 0.13936772 | F34: 0.021713503 | G34: 22 | H34: =NORMINV(RAND(),N$15,N$16) -> 0.0076957288 | J34: =100%-K34 -> 0.9 | K34: 0.1 | L34: =PERCENTILE(F$13:$F$256,K34) -> -0.011021352 | M34: =N$19*(1-L34) -> 8987.9798 | N34: =$N$19-M34 -> -97.979818
C35: 45107 | D35: 4716.3 | E35: =(D35-D36)/D36 -> -0.4165378 | F35: 0.021264156 | G35: 23 | H35: =NORMINV(RAND(),N$15,N$16) -> 0.00026506802
C36: 45337 | D36: 8083.3 | E36: =(D36-D37)/D37 -> -0.015108501 | F36: 0.020953848 | G36: 24 | H36: =NORMINV(RAND(),N$15,N$16) -> 0.0067793782
C37: 45356 | D37: 8207.3 | E37: =(D37-D38)/D38 -> 0.48234508 | F37: 0.020643428 | G37: 25 | H37: =NORMINV(RAND(),N$15,N$16) -> 0.024418151
C38: 45246 | D38: 5536.7 | E38: =(D38-D39)/D39 -> -0.35028984 | F38: 0.020552238 | G38: 26 | H38: =NORMINV(RAND(),N$15,N$16) -> 0.019296061
C39: 45370 | D39: 8521.8 | E39: =(D39-D40)/D40 -> 0.33736131 | F39: 0.0204893 | G39: 27 | H39: =NORMINV(RAND(),N$15,N$16) -> -0.0042278394
C40: 45286 | D40: 6372.1 | E40: =(D40-D41)/D41 -> 0.40067703 | F40: 0.020123591 | G40: 28 | H40: =NORMINV(RAND(),N$15,N$16) -> -0.0011149432
C41: 45055 | D41: 4549.3 | E41: =(D41-D42)/D42 -> -0.27260081 | F41: 0.01931393 | G41: 29 | H41: =NORMINV(RAND(),N$15,N$16) -> 0.012467404
C42: 45273 | D42: 6254.2 | E42: =(D42-D43)/D43 -> 0.24806929 | F42: 0.018864851 | G42: 30 | H42: =NORMINV(RAND(),N$15,N$16) -> 0.0021351768
C43: 45205 | D43: 5011.1 | E43: =(D43-D44)/D44 -> -0.39999761 | F43: 0.018806164 | G43: 31 | H43: =NORMINV(RAND(),N$15,N$16) -> 0.020384952
C44: 45357 | D44: 8351.8 | E44: =(D44-D45)/D45 -> 0.79856146 | F44: 0.017606277 | G44: 32 | H44: =NORMINV(RAND(),N$15,N$16) -> -0.0014306486
C45: 45079 | D45: 4643.6 | E45: =(D45-D46)/D46 -> -0.42244499 | F45: 0.016727973 | G45: 33 | H45: =NORMINV(RAND(),N$15,N$16) -> -0.012246334
C46: 45353 | D46: 8040.1 | E46: =(D46-D47)/D47 -> 0.11468341 | F46: 0.016524642 | G46: 34 | H46: =NORMINV(RAND(),N$15,N$16) -> 0.0023957134
... C256: 45352 | D256: 7909.4 | E256: =(D256-D257)/D257 -> #DIV/0! | F256: -0.034107978 | G256: 244 | H256: =NORMINV(RAND(),N$15,N$16) -> 0.0034494799

Sheet Dupont Analysis
B2: Return on Equity(ROE) | C2: Return on Equity(ROE) | D2: Return on Equity(ROE) | E2: Return on Equity(ROE) | F2: Return on Equity(ROE) | G2: Return on Equity(ROE) | H2: Return on Equity(ROE) | I2: Return on Equity(ROE) | J2: Return on Equity(ROE) | K2: Return on Equity(ROE) | L2: Return on Equity(ROE)
B4: ='[2]Data Sheet'!B1 -> BAJAJ AUTO LTD
B5: =CONCATENATE(" ",VLOOKUP(B4,'[2]LIST OF STOCKS'!B5:D5444,3,FALSE)," | ","Bse Code: ",VLOOKUP(B4,'[2]LIST OF STOCKS'!B5:E5444,2,FALSE),) -> BAJAJ-AUTO | Bse Code: 532977
B6: =CONCATENATE(" ","INR"," "&'[2]Data Sheet'!B8) -> INR 8860
B7: 52 Week (High - 9,636 INR & Low - 7,089)
B12: About the company
B14: Bajaj Auto Limited is an Indian multinational automotive manufacturing company based in Pune. It manufactures motorcycles, scooters and auto rickshaws. Auto Bajaj is a part of Bajaj Group. It was founded by Jamnalal Bajaj (1889–1942) in Rajasthan in the 1940s. Bajaj Auto is the world's third-largest manufacturer of motorcycles and the second-largest in India. It is the world's largest three-wheeler manufacturer. In December 2020, Bajaj Auto crossed a market capitalisation of ₹1 trillion (US$12 billion), making it the world's most valuable two-wheeler company.
B20: Financial Summary
B23: Revenue (INR Crs.) | E23: Net Profit (INR Crs.) | I23: Average Total Assets (INR Crs.)
B33: Return on Equity (%) | E33: Return on Assets (%) | I33: Financial Leverage
B43: Return on Equity(ROE) | C43: Return on Equity(ROE) | D43: Return on Equity(ROE) | E43: Return on Equity(ROE) | F43: Return on Equity(ROE) | G43: Return on Equity(ROE) | H43: Return on Equity(ROE) | I43: Return on Equity(ROE) | J43: Return on Equity(ROE) | K43: Return on Equity(ROE) | L43: Return on Equity(ROE)
B45: Dupont Analysis - Return on Equity & Return on Assets
B48: Return on Equity(ROE)
D49: ='Historical FS'!C9 -> 42825 | E49: ='Historical FS'!D9 -> 43190 | F49: ='Historical FS'!E9 -> 43555 | G49: ='Historical FS'!F9 -> 43921 | H49: ='Historical FS'!G9 -> 44286 | I49: ='Historical FS'!H9 -> 44651 | J49: ='Historical FS'!I9 -> 45016 | K49: ='Historical FS'!J9 -> 45382 | L49: ='Historical FS'!K9 -> 45747
B50: Net Profit | D50: ='[2]Data Sheet'!C30 -> 4079.49 | E50: ='[2]Data Sheet'!D30 -> 4218.95 | F50: ='[2]Data Sheet'!E30 -> 4927.61 | G50: ='[2]Data Sheet'!F30 -> 5211.91 | H50: ='[2]Data Sheet'!G30 -> 4857.02 | I50: ='[2]Data Sheet'!H30 -> 6165.87 | J50: ='[2]Data Sheet'!I30 -> 6060.21 | K50: ='[2]Data Sheet'!J30 -> 7708.24 | L50: ='[2]Data Sheet'!K30 -> 7324.73
B51: Average Shareholder Equity | D51: =(('[2]Data Sheet'!C57+'[2]Data Sheet'!C58)+('[2]Data Sheet'!B57+'[2]Data Sheet'!B58))/2 -> 15938.44 | E51: =(('[2]Data Sheet'!D57+'[2]Data Sheet'!D58)+('[2]Data Sheet'!C57+'[2]Data Sheet'!C58))/2 -> 19140.905 | F51: =(('[2]Data Sheet'!E57+'[2]Data Sheet'!E58)+('[2]Data Sheet'!D57+'[2]Data Sheet'!D58))/2 -> 21829.525 | G51: =(('[2]Data Sheet'!F57+'[2]Data Sheet'!F58)+('[2]Data Sheet'!E57+'[2]Data Sheet'!E58))/2 -> 22447.945 | H51: =(('[2]Data Sheet'!G57+'[2]Data Sheet'!G58)+('[2]Data Sheet'!F57+'[2]Data Sheet'!F58))/2 -> 24467.755 | I51: =(('[2]Data Sheet'!H57+'[2]Data Sheet'!H58)+('[2]Data Sheet'!G57+'[2]Data Sheet'!G58))/2 -> 28566.54 | J51: =(('[2]Data Sheet'!I57+'[2]Data Sheet'!I58)+('[2]Data Sheet'!H57+'[2]Data Sheet'!H58))/2 -> 29610.595 | K51: =(('[2]Data Sheet'!J57+'[2]Data Sheet'!J58)+('[2]Data Sheet'!I57+'[2]Data Sheet'!I58))/2 -> 29161.975 | L51: =(('[2]Data Sheet'!K57+'[2]Data Sheet'!K58)+('[2]Data Sheet'!J57+'[2]Data Sheet'!J58))/2 -> 32075.575
B52: Return or Equity | D52: =D50/D51 -> 0.2559529 | E52: =E50/E51 -> 0.22041539 | F52: =F50/F51 -> 0.22573143 | G52: =G50/G51 -> 0.2321776 | H52: =H50/H51 -> 0.19850697 | I52: =I50/I51 -> 0.21584238 | J52: =J50/J51 -> 0.20466357 | K52: =K50/K51 -> 0.26432503 | L52: =L50/L51 -> 0.22835849
B54: ROE- Dupont Equation
D55: =D49 -> 42825 | E55: =E49 -> 43190 | F55: =F49 -> 43555 | G55: =G49 -> 43921 | H55: =H49 -> 44286 | I55: =I49 -> 44651 | J55: =J49 -> 45016 | K55: =K49 -> 45382 | L55: =L49 -> 45747
B56: Net Profit | D56: =D50 -> 4079.49 | E56: =E50 -> 4218.95 | F56: =F50 -> 4927.61 | G56: =G50 -> 5211.91 | H56: =H50 -> 4857.02 | I56: =I50 -> 6165.87 | J56: =J50 -> 6060.21 | K56: =K50 -> 7708.24 | L56: =L50 -> 7324.73
B57: Revenue | D57: ='[2]Data Sheet'!C17 -> 21754.72 | E57: ='[2]Data Sheet'!D17 -> 25209.93 | F57: ='[2]Data Sheet'!E17 -> 30357.63 | G57: ='[2]Data Sheet'!F17 -> 29918.65 | H57: ='[2]Data Sheet'!G17 -> 27741.08 | I57: ='[2]Data Sheet'!H17 -> 33144.71 | J57: ='[2]Data Sheet'!I17 -> 36455.38 | K57: ='[2]Data Sheet'!J17 -> 44870.43 | L57: ='[2]Data Sheet'!K17 -> 50994.55
B58: Net Profit Margin(A) | D58: =D56/D57 -> 0.18752206 | E58: =E56/E57 -> 0.16735271 | F58: =F56/F57 -> 0.16231867 | G58: =G56/G57 -> 0.17420271 | H58: =H56/H57 -> 0.17508403 | I58: =I56/I57 -> 0.18602878 | J58: =J56/J57 -> 0.16623637 | K58: =K56/K57 -> 0.17178886 | L58: =L56/L57 -> 0.14363751
B60: Revenue | D60: =D57 -> 21754.72 | E60: =E57 -> 25209.93 | F60: =F57 -> 30357.63 | G60: =G57 -> 29918.65 | H60: =H57 -> 27741.08 | I60: =I57 -> 33144.71 | J60: =J57 -> 36455.38 | K60: =K57 -> 44870.43 | L60: =L57 -> 50994.55
B61: Average Total Asset | D61: =('[2]Data Sheet'!C66+'[2]Data Sheet'!B66)/2 -> 19438.995 | E61: =('[2]Data Sheet'!D66+'[2]Data Sheet'!C66)/2 -> 23389.31 | F61: =('[2]Data Sheet'!E66+'[2]Data Sheet'!D66)/2 -> 26987.705 | G61: =('[2]Data Sheet'!F66+'[2]Data Sheet'!E66)/2 -> 27672.215 | H61: =('[2]Data Sheet'!G66+'[2]Data Sheet'!F66)/2 -> 30055.865 | I61: =('[2]Data Sheet'!H66+'[2]Data Sheet'!G66)/2 -> 34356.46 | J61: =('[2]Data Sheet'!I66+'[2]Data Sheet'!H66)/2 -> 35123.83 | K61: =('[2]Data Sheet'!J66+'[2]Data Sheet'!I66)/2 -> 37240.07 | L61: =('[2]Data Sheet'!K66+'[2]Data Sheet'!J66)/2 -> 46726.805
B62: Assest Turnover Ratio(B) | D62: =D60/D61 -> 1.1191278 | E62: =E60/E61 -> 1.0778398 | F62: =F60/F61 -> 1.1248689 | G62: =G60/G61 -> 1.0811802 | H62: =H60/H61 -> 0.92298392 | I62: =I60/I61 -> 0.96473007 | J62: =J60/J61 -> 1.0379102 | K62: =K60/K61 -> 1.2048965 | L62: =L60/L61 -> 1.091334
B64: =B61 -> Average Total Asset | D64: =D61 -> 19438.995 | E64: =E61 -> 23389.31 | F64: =F61 -> 26987.705 | G64: =G61 -> 27672.215 | H64: =H61 -> 30055.865 | I64: =I61 -> 34356.46 | J64: =J61 -> 35123.83 | K64: =K61 -> 37240.07 | L64: =L61 -> 46726.805
B65: =B51 -> Average Shareholder Equity | D65: =D51 -> 15938.44 | E65: =E51 -> 19140.905 | F65: =F51 -> 21829.525 | G65: =G51 -> 22447.945 | H65: =H51 -> 24467.755 | I65: =I51 -> 28566.54 | J65: =J51 -> 29610.595 | K65: =K51 -> 29161.975 | L65: =L51 -> 32075.575
B66: Equity Multiplier (C ) | D66: =D64/D65 -> 1.2196297 | E66: =E64/E65 -> 1.2219542 | F66: =F64/F65 -> 1.2362937 | G66: =G64/G65 -> 1.2327282 | H66: =H64/H65 -> 1.2283867 | I66: =I64/I65 -> 1.2026819 | J66: =J64/J65 -> 1.1861913 | K66: =K64/K65 -> 1.2770078 | L66: =L64/L65 -> 1.4567722
B68: Return on Equity (A*B*C) | D68: =D66*D62*D58 -> 0.2559529 | E68: =E66*E62*E58 -> 0.22041539 | F68: =F66*F62*F58 -> 0.22573143 | G68: =G66*G62*G58 -> 0.2321776 | H68: =H66*H62*H58 -> 0.19850697 | I68: =I66*I62*I58 -> 0.21584238 | J68: =J66*J62*J58 -> 0.20466357 | K68: =K66*K62*K58 -> 0.26432503 | L68: =L66*L62*L58 -> 0.22835849
B71: Return on Asset(ROA)
D72: =D49 -> 42825 | E72: =E49 -> 43190 | F72: =F49 -> 43555 | G72: =G49 -> 43921 | H72: =H49 -> 44286 | I72: =I49 -> 44651 | J72: =J49 -> 45016 | K72: =K49 -> 45382 | L72: =L49 -> 45747
B73: Net Profit | D73: =D56 -> 4079.49 | E73: =E56 -> 4218.95 | F73: =F56 -> 4927.61 | G73: =G56 -> 5211.91 | H73: =H56 -> 4857.02 | I73: =I56 -> 6165.87 | J73: =J56 -> 6060.21 | K73: =K56 -> 7708.24 | L73: =L56 -> 7324.73
B74: Average Total Assest | D74: ='Dupont Analysis'!D61 -> 19438.995 | E74: ='Dupont Analysis'!E61 -> 23389.31 | F74: ='Dupont Analysis'!F61 -> 26987.705 | G74: ='Dupont Analysis'!G61 -> 27672.215 | H74: ='Dupont Analysis'!H61 -> 30055.865 | I74: ='Dupont Analysis'!I61 -> 34356.46 | J74: ='Dupont Analysis'!J61 -> 35123.83 | K74: ='Dupont Analysis'!K61 -> 37240.07 | L74: ='Dupont Analysis'!L61 -> 46726.805
B75: Return or Asset | D75: =D73/D74 -> 0.20986116 | E75: =E73/E74 -> 0.18037941 | F75: =F73/F74 -> 0.18258722 | G75: =G73/G74 -> 0.18834452 | H75: =H73/H74 -> 0.16159974 | I75: =I73/I74 -> 0.17946756 | J75: =J73/J74 -> 0.17253842 | K75: =K73/K74 -> 0.2069878 | L75: =L73/L74 -> 0.15675649
B77: ROA- Dupont Equation
D78: =D72 -> 42825 | E78: =E72 -> 43190 | F78: =F72 -> 43555 | G78: =G72 -> 43921 | H78: =H72 -> 44286 | I78: =I72 -> 44651 | J78: =J72 -> 45016 | K78: =K72 -> 45382 | L78: =L72 -> 45747
B79: Net Profit | D79: =D73 -> 4079.49 | E79: =E73 -> 4218.95 | F79: =F73 -> 4927.61 | G79: =G73 -> 5211.91 | H79: =H73 -> 4857.02 | I79: =I73 -> 6165.87 | J79: =J73 -> 6060.21 | K79: =K73 -> 7708.24 | L79: =L73 -> 7324.73
B80: Revenue | D80: =D60 -> 21754.72 | E80: =E60 -> 25209.93 | F80: =F60 -> 30357.63 | G80: =G60 -> 29918.65 | H80: =H60 -> 27741.08 | I80: =I60 -> 33144.71 | J80: =J60 -> 36455.38 | K80: =K60 -> 44870.43 | L80: =L60 -> 50994.55
B81: Net Profit Margin(A) | D81: =D79/D80 -> 0.18752206 | E81: =E79/E80 -> 0.16735271 | F81: =F79/F80 -> 0.16231867 | G81: =G79/G80 -> 0.17420271 | H81: =H79/H80 -> 0.17508403 | I81: =I79/I80 -> 0.18602878 | J81: =J79/J80 -> 0.16623637 | K81: =K79/K80 -> 0.17178886 | L81: =L79/L80 -> 0.14363751
B83: Revenue | D83: =D80 -> 21754.72 | E83: =E80 -> 25209.93 | F83: =F80 -> 30357.63 | G83: =G80 -> 29918.65 | H83: =H80 -> 27741.08 | I83: =I80 -> 33144.71 | J83: =J80 -> 36455.38 | K83: =K80 -> 44870.43 | L83: =L80 -> 50994.55
B84: Average Total Asset | D84: =D61 -> 19438.995 | E84: =E61 -> 23389.31 | F84: =F61 -> 26987.705 | G84: =G61 -> 27672.215 | H84: =H61 -> 30055.865 | I84: =I61 -> 34356.46 | J84: =J61 -> 35123.83 | K84: =K61 -> 37240.07 | L84: =L61 -> 46726.805
B85: Assest Turnover Ratio(B) | D85: =D83/D84 -> 1.1191278 | E85: =E83/E84 -> 1.0778398 | F85: =F83/F84 -> 1.1248689 | G85: =G83/G84 -> 1.0811802 | H85: =H83/H84 -> 0.92298392 | I85: =I83/I84 -> 0.96473007 | J85: =J83/J84 -> 1.0379102 | K85: =K83/K84 -> 1.2048965 | L85: =L83/L84 -> 1.091334
B87: Return on Asset (A*B) | D87: =D81*D85 -> 0.20986116 | E87: =E81*E85 -> 0.18037941 | F87: =F81*F85 -> 0.18258722 | G87: =G81*G85 -> 0.18834452 | H87: =H81*H85 -> 0.16159974 | I87: =I81*I85 -> 0.17946756 | J87: =J81*J85 -> 0.17253842 | K87: =K81*K85 -> 0.2069878 | L87: =L81*L85 -> 0.15675649
B89: Dupont Summary
B90: 1. ROE has gradually declined over the years, moving from 25.60% (Mar-17) to 20.47% (Mar-23), indicating a slow erosion in overall shareholder returns despite occasional recoveries. 2. Net Profit Margin has shown a consistent downward trend, falling from 18.75% to 16.62%, suggesting rising costs, pricing pressure, or margin compression over time. 3. Asset Turnover has remained relatively stable, fluctuating between 1.12× and 1.04×, showing that the company’s efficiency in using assets to generate revenue has not significantly changed but has slightly weakened. 4. Equity Multiplier has remained almost constant (around 1.22× to 1.19×), indicating very low leverage usage; changes in ROE are mainly driven by profitability and efficiency, not by debt levels.The decline in ROE is primarily driven by lower profit margins, with only minor impact from asset turnover and almost no contribution from leverage, highlighting that the company’s weakening profitability is the key factor behind reduced shareholder returns.
B102: Disclaimer:
B103: This report is prepared solely for educational and academic purposes. It should not be considered as investment advice or a recommendation to buy, sell, or act on any financial instrument. Readers are advised to consult a SEBI-registered Research Analyst or a qualified financial professional before making any investment decisions.
B107: Return on Asset(ROA) | C107: Return on Asset(ROA) | D107: Return on Asset(ROA) | E107: Return on Asset(ROA) | F107: Return on Asset(ROA) | G107: Return on Asset(ROA) | H107: Return on Asset(ROA) | I107: Return on Asset(ROA) | J107: Return on Asset(ROA) | K107: Return on Asset(ROA) | L107: Return on Asset(ROA)

Sheet Altman's Z score
B2: Return on Equity(ROE) | C2: Return on Equity(ROE) | D2: Return on Equity(ROE) | E2: Return on Equity(ROE) | F2: Return on Equity(ROE) | G2: Return on Equity(ROE) | H2: Return on Equity(ROE) | I2: Return on Equity(ROE) | J2: Return on Equity(ROE) | K2: Return on Equity(ROE) | L2: Return on Equity(ROE)
B4: ='[2]Data Sheet'!B1 -> BAJAJ AUTO LTD
B5: =CONCATENATE(" ",VLOOKUP(B4,'[2]LIST OF STOCKS'!B5:D5444,3,FALSE)," | ","Bse Code: ",VLOOKUP(B4,'[2]LIST OF STOCKS'!B5:E5444,2,FALSE),) -> BAJAJ-AUTO | Bse Code: 532977
B6: =CONCATENATE(" ","INR"," "&'[2]Data Sheet'!B8) -> INR 8860
B7: 52 Week (High - 9,636 INR & Low - 7,089)
B12: Altman's Z Score Analysis
B14: The company consistently shows a strong Altman Z-Score, indicating very low bankruptcy risk across all years. Profitability ratios like EBIT/Total Assets remain healthy, though they show mild fluctuations. Working capital and retained earnings ratios dip in some years, signalling occasional liquidity pressure. However, the huge Market Cap to Long-Term Liabilities ratio highlights strong market confidence and a solid balance sheet. Overall, the business appears financially robust with stable long-term solvency.
B20: Financial Summary
B23: Working Capital/Total Assets (%) | E23: Retained Earnings/Total Assets% | J23: EBIT/ Total Assets(%)
B36: Market Cap/Long term Total Liabilities (%) | E36: Sales/Total Assets (%) | J36: Altman's Z Score(%)
B46: Return on Equity(ROE) | C46: Return on Equity(ROE) | D46: Return on Equity(ROE) | E46: Return on Equity(ROE) | F46: Return on Equity(ROE) | G46: Return on Equity(ROE) | H46: Return on Equity(ROE) | I46: Return on Equity(ROE) | J46: Return on Equity(ROE) | K46: Return on Equity(ROE) | L46: Return on Equity(ROE)
B48: Altman's Z Score Analysis Calculation
B51: Working Capital / Total Assets
D52: ='Historical FS'!C9 -> 42825 | E52: ='Historical FS'!D9 -> 43190 | F52: ='Historical FS'!E9 -> 43555 | G52: ='Historical FS'!F9 -> 43921 | H52: ='Historical FS'!G9 -> 44286 | I52: ='Historical FS'!H9 -> 44651 | J52: ='Historical FS'!I9 -> 45016 | K52: ='Historical FS'!J9 -> 45382 | L52: ='Historical FS'!K9 -> 45747
B53: Working Capital | D53: ='[2]Data Sheet'!C65-'[2]Data Sheet'!C60 -> 455.47 | E53: ='[2]Data Sheet'!D65-'[2]Data Sheet'!D60 -> -283.36 | F53: ='[2]Data Sheet'!E65-'[2]Data Sheet'!E60 -> 943.52 | G53: ='[2]Data Sheet'!F65-'[2]Data Sheet'!F60 -> 114.88 | H53: ='[2]Data Sheet'!G65-'[2]Data Sheet'!G60 -> 1024.71 | I53: ='[2]Data Sheet'!H65-'[2]Data Sheet'!H60 -> 1435.04 | J53: ='[2]Data Sheet'!I65-'[2]Data Sheet'!I60 -> 375.35 | K53: ='[2]Data Sheet'!J65-'[2]Data Sheet'!J60 -> -465 | L53: ='[2]Data Sheet'!K65-'[2]Data Sheet'!K60 -> 11901.64
B54: Total Assets | D54: ='[2]Data Sheet'!C66 -> 21637.62 | E54: ='[2]Data Sheet'!D66 -> 25141 | F54: ='[2]Data Sheet'!E66 -> 28834.41 | G54: ='[2]Data Sheet'!F66 -> 26510.02 | H54: ='[2]Data Sheet'!G66 -> 33601.71 | I54: ='[2]Data Sheet'!H66 -> 35111.21 | J54: ='[2]Data Sheet'!I66 -> 35136.45 | K54: ='[2]Data Sheet'!J66 -> 39343.69 | L54: ='[2]Data Sheet'!K66 -> 54109.92
B55: Working Capital/Total Assets(A) | D55: =D53/D54 -> 0.021049912 | E55: =E53/E54 -> -0.011270833 | F55: =F53/F54 -> 0.032722015 | G55: =G53/G54 -> 0.0043334558 | H55: =H53/H54 -> 0.030495769 | I55: =I53/I54 -> 0.040871277 | J55: =J53/J54 -> 0.010682639 | K55: =K53/K54 -> -0.011818922 | L55: =L53/L54 -> 0.21995301
B57: Retained Earnings / Total Assets
D58: =D52 -> 42825 | E58: =E52 -> 43190 | F58: =F52 -> 43555 | G58: =G52 -> 43921 | H58: =H52 -> 44286 | I58: =I52 -> 44651 | J58: =J52 -> 45016 | K58: =K52 -> 45382 | L58: =L52 -> 45747
B59: Retained Earnings | D59: ='Historical FS'!C43*'Historical FS'!C45*'Historical FS'!C51 -> 932.96994 | E59: ='Historical FS'!D43*'Historical FS'!D45*'Historical FS'!D51 -> 1098.3599 | F59: ='Historical FS'!E43*'Historical FS'!E45*'Historical FS'!E51 -> 1050.7099 | G59: ='Historical FS'!F43*'Historical FS'!F45*'Historical FS'!F51 -> -218.93011 | H59: ='Historical FS'!G43*'Historical FS'!G45*'Historical FS'!G51 -> -1202.8002 | I59: ='Historical FS'!H43*'Historical FS'!H45*'Historical FS'!H51 -> -180.69026 | J59: ='Historical FS'!I43*'Historical FS'!I45*'Historical FS'!I51 -> 195.40892 | K59: ='Historical FS'!J43*'Historical FS'!J45*'Historical FS'!J51 -> 3621.6287 | L59: ='Historical FS'!K43*'Historical FS'!K45*'Historical FS'!K51 -> 45.022374
B60: Total Assets | D60: =D54 -> 21637.62 | E60: =E54 -> 25141 | F60: =F54 -> 28834.41 | G60: =G54 -> 26510.02 | H60: =H54 -> 33601.71 | I60: =I54 -> 35111.21 | J60: =J54 -> 35136.45 | K60: =K54 -> 39343.69 | L60: =L54 -> 54109.92
B61: Retained Earnings / Total Assets(B) | D61: =D59/D60 -> 0.043117955 | E61: =E59/E60 -> 0.043687998 | F61: =F59/F60 -> 0.036439443 | G61: =G59/G60 -> -0.0082583908 | H61: =H59/H60 -> -0.035795804 | I61: =I59/I60 -> -0.0051462271 | J61: =J59/J60 -> 0.0055614303 | K61: =K59/K60 -> 0.092051067 | L61: =L59/L60 -> 0.00083205397
B63: EBIT / Total Assets
D64: =D52 -> 42825 | E64: =E52 -> 43190 | F64: =F52 -> 43555 | G64: =G52 -> 43921 | H64: =H52 -> 44286 | I64: =I52 -> 44651 | J64: =J52 -> 45016 | K64: =K52 -> 45382 | L64: =L52 -> 45747
B65: EBIT | D65: ='Historical FS'!C34+'Historical FS'!C28 -> 4033.9799 | E65: ='Historical FS'!D34+'Historical FS'!D28 -> 4550.3599 | F65: ='Historical FS'!E34+'Historical FS'!E28 -> 4819.3899 | G65: ='Historical FS'!F34+'Historical FS'!F28 -> 4736.8899 | H65: ='Historical FS'!G34+'Historical FS'!G28 -> 4239.4498 | I65: ='Historical FS'!H34+'Historical FS'!H28 -> 5364.9597 | J65: ='Historical FS'!I34+'Historical FS'!I28 -> 5978.1289 | K65: ='Historical FS'!J34+'Historical FS'!J28 -> 8247.2287 | L65: ='Historical FS'!K34+'Historical FS'!K28 -> 9197.1824
B66: Total Assets | D66: =D54 -> 21637.62 | E66: =E54 -> 25141 | F66: =F54 -> 28834.41 | G66: =G54 -> 26510.02 | H66: =H54 -> 33601.71 | I66: =I54 -> 35111.21 | J66: =J54 -> 35136.45 | K66: =K54 -> 39343.69 | L66: =L54 -> 54109.92
B67: EBIT / Total Assests(C ) | D67: =D65/D66 -> 0.18643363 | E67: =E65/E66 -> 0.18099359 | F67: =F65/F66 -> 0.16714023 | G67: =G65/G66 -> 0.178683 | H67: =H65/H66 -> 0.12616768 | I67: =I65/I66 -> 0.15279906 | J67: =J65/J66 -> 0.17014038 | K67: =K65/K66 -> 0.20962011 | L67: =L65/L66 -> 0.1699722
B69: Market Cap / Long Term Liabilities
D70: =D58 -> 42825 | E70: =E58 -> 43190 | F70: =F58 -> 43555 | G70: =G58 -> 43921 | H70: =H58 -> 44286 | I70: =I58 -> 44651 | J70: =J58 -> 45016 | K70: =K58 -> 45382 | L70: =L58 -> 45747
B71: Market Cap | D71: =('[2]Data Sheet'!C70*'[2]Data Sheet'!C90)/10000000 -> 81180.471 | E71: =E66 -> 25141 | F71: =F66 -> 28834.41 | G71: =G66 -> 26510.02 | H71: =H66 -> 33601.71 | I71: =I66 -> 35111.21 | J71: =J66 -> 35136.45 | K71: =K66 -> 39343.69 | L71: =L66 -> 54109.92
B72: Long Term Liabilities | D72: ='[2]Data Sheet'!C59 -> 119.9 | E72: ='[2]Data Sheet'!D59 -> 120.77 | F72: ='[2]Data Sheet'!E59 -> 124.52 | G72: ='[2]Data Sheet'!F59 -> 125.59 | H72: ='[2]Data Sheet'!G59 -> 121.46 | I72: ='[2]Data Sheet'!H59 -> 122.77 | J72: ='[2]Data Sheet'!I59 -> 124.23 | K72: ='[2]Data Sheet'!J59 -> 1911.74 | L72: ='[2]Data Sheet'!K59 -> 9364.16
B73: Market Cap/Long term Liabilities(D) | D73: =D71/D72 -> 677.06815 | E73: =E71/E72 -> 208.17256 | F73: =F71/F72 -> 231.56449 | G73: =G71/G72 -> 211.08384 | H73: =H71/H72 -> 276.64836 | I73: =I71/I72 -> 285.99177 | J73: =J71/J72 -> 282.83386 | K73: =K71/K72 -> 20.580042 | L73: =L71/L72 -> 5.7784062
B75: Sales / Total Assets
D76: =D52 -> 42825 | E76: =E52 -> 43190 | F76: =F52 -> 43555 | G76: =G52 -> 43921 | H76: =H52 -> 44286 | I76: =I52 -> 44651 | J76: =J52 -> 45016 | K76: =K52 -> 45382 | L76: =L52 -> 45747
B77: Sales | D77: ='[2]Data Sheet'!C17 -> 21754.72 | E77: ='[2]Data Sheet'!D17 -> 25209.93 | F77: ='[2]Data Sheet'!E17 -> 30357.63 | G77: ='[2]Data Sheet'!F17 -> 29918.65 | H77: ='[2]Data Sheet'!G17 -> 27741.08 | I77: ='[2]Data Sheet'!H17 -> 33144.71 | J77: ='[2]Data Sheet'!I17 -> 36455.38 | K77: ='[2]Data Sheet'!J17 -> 44870.43 | L77: ='[2]Data Sheet'!K17 -> 50994.55
B78: Total Assets | D78: =D60 -> 21637.62 | E78: =E60 -> 25141 | F78: =F60 -> 28834.41 | G78: =G60 -> 26510.02 | H78: =H60 -> 33601.71 | I78: =I60 -> 35111.21 | J78: =J60 -> 35136.45 | K78: =K60 -> 39343.69 | L78: =L60 -> 54109.92
B79: Sales/Total Assets (E ) | D79: =D77/D78 -> 1.0054119 | E79: =E77/E78 -> 1.0027417 | F79: =F77/F78 -> 1.0528265 | G79: =G77/G78 -> 1.1285789 | H79: =H77/H78 -> 0.82558536 | I79: =I77/I78 -> 0.94399225 | J79: =J77/J78 -> 1.0375374 | K79: =K77/K78 -> 1.1404734 | L79: =L77/L78 -> 0.94242516
B81: Altman's Z Score
D82: =D76 -> 42825 | E82: =E76 -> 43190 | F82: =F76 -> 43555 | G82: =G76 -> 43921 | H82: =H76 -> 44286 | I82: =I76 -> 44651 | J82: =J76 -> 45016 | K82: =K76 -> 45382 | L82: =L76 -> 45747
B83: Final Score | D83: =(D55*1.2)+(D61*1.4)+(D67*3.3)+(D73*0.6)+(D79*1) -> 407.94716 | E83: =(E55*1.2)+(E61*1.4)+(E67*3.3)+(E73*0.6)+(E79*1) -> 126.55119 | F83: =(F55*1.2)+(F61*1.4)+(F67*3.3)+(F73*0.6)+(F79*1) -> 140.63336 | G83: =(G55*1.2)+(G61*1.4)+(G67*3.3)+(G73*0.6)+(G79*1) -> 128.36218 | H83: =(H55*1.2)+(H61*1.4)+(H67*3.3)+(H73*0.6)+(H79*1) -> 167.21744 | I83: =(I55*1.2)+(I61*1.4)+(I67*3.3)+(I73*0.6)+(I79*1) -> 173.08513 | J83: =(J55*1.2)+(J61*1.4)+(J67*3.3)+(J73*0.6)+(J79*1) -> 171.31992 | K83: =(K55*1.2)+(K61*1.4)+(K67*3.3)+(K73*0.6)+(K79*1) -> 14.294934 | L83: =(L55*1.2)+(L61*1.4)+(L67*3.3)+(L73*0.6)+(L79*1) -> 5.2354856
B85: Financial Health | D85: =IF(D83<1.81,"Distressed",IF(D83>3,"Strong","Grey Zone")) -> Strong | E85: =IF(E83<1.81,"Distressed",IF(E83>3,"Strong","Grey Zone")) -> Strong | F85: =IF(F83<1.81,"Distressed",IF(F83>3,"Strong","Grey Zone")) -> Strong | G85: =IF(G83<1.81,"Distressed",IF(G83>3,"Strong","Grey Zone")) -> Strong | H85: =IF(H83<1.81,"Distressed",IF(H83>3,"Strong","Grey Zone")) -> Strong | I85: =IF(I83<1.81,"Distressed",IF(I83>3,"Strong","Grey Zone")) -> Strong | J85: =IF(J83<1.81,"Distressed",IF(J83>3,"Strong","Grey Zone")) -> Strong | K85: =IF(K83<1.81,"Distressed",IF(K83>3,"Strong","Grey Zone")) -> Strong | L85: =IF(L83<1.81,"Distressed",IF(L83>3,"Strong","Grey Zone")) -> Strong
B87: Disclaimer:
B88: This report is prepared solely for educational and academic purposes. It should not be considered as investment advice or a recommendation to buy, sell, or act on any financial instrument. Readers are advised to consult a SEBI-registered Research Analyst or a qualified financial professional before making any investment decisions.
B92: Return on Asset(ROA) | C92: Return on Asset(ROA) | D92: Return on Asset(ROA) | E92: Return on Asset(ROA) | F92: Return on Asset(ROA) | G92: Return on Asset(ROA) | H92: Return on Asset(ROA) | I92: Return on Asset(ROA) | J92: Return on Asset(ROA) | K92: Return on Asset(ROA) | L92: Return on Asset(ROA)

Sheet LBO
B2: (One Page Leveraged Buyout - LBO)
B4: Return on Equity(ROE) | C4: Return on Equity(ROE) | D4: Return on Equity(ROE) | E4: Return on Equity(ROE) | F4: Return on Equity(ROE) | G4: Return on Equity(ROE) | H4: Return on Equity(ROE) | I4: Return on Equity(ROE) | L4: Return on Equity(ROE) | M4: Return on Equity(ROE) | N4: Return on Equity(ROE) | O4: Return on Equity(ROE)
B6: ='[2]Data Sheet'!B1 -> BAJAJ AUTO LTD
B7: =CONCATENATE(" ",VLOOKUP(B6,'[2]LIST OF STOCKS'!B5:D5444,3,FALSE)," | ","Bse Code: ",VLOOKUP(B6,'[2]LIST OF STOCKS'!B5:E5444,2,FALSE),) -> BAJAJ-AUTO | Bse Code: 532977
B8: INR (Crs.)
B11: Assumptions
B13: Entry | G13: Financials | L13: Capital Structure | N13: Amount | O13: Cost
B14: LTM EBITDA | E14: =J19 -> 9611.42 | G14: LTM Financials | L14: Bank Debt | N14: 4 | O14: 0.06
B15: EBITDA Multiple | E15: 10 | G15: Revenue | J15: ='Historical FS'!K13 -> 50994.55 | L15: Senior Notes | N15: 2 | O15: 0.12
B16: Enterprise Value | E16: =E14*E15 -> 96114.2 | G16: D&A | J16: ='Historical FS'!K31 -> 414.23
B17: Existing Net Debt | E17: 30000 | G17: Capex | J17: ='Historical FS'!K89 -> -874
B18: Equity Value | E18: =E16-E17 -> 66114.2 | G18: NWC | J18: ='Historical FS'!K70-'Historical FS'!K59+'Historical FS'!K56 -> -12150.26
G19: EBITDA | J19: ='Historical FS'!K25 -> 9611.42 | L19: For Reference
L20: IRR | O20: =O117 -> 0.33276501
B21: Fees & Expenses | E21: 50
G22: Operating Assumptions
B23: Exit | G23: Revenue Growth | J23: 0.07
B24: EBITDA Multiple | E24: =E15 -> 10 | G24: YOY margin Expansion | J24: 0.01
G25: Tax Rate | J25: 0.25
B27: Sources & Uses
B29: Sources | J29: Uses
E30: Amount | F30: xEBITDA | G30: %Capital | M30: Amount | N30: xEBITDA | O30: %Capital
B31: Bank Debt | E31: =F31*$E$14 -> 38445.68 | F31: =N14 -> 4 | G31: =E31/$E$37 -> 0.39979202 | J31: Debt Retirement | M31: =E17 -> 30000 | N31: =M31/$J$19 -> 3.121287 | O31: =M31/$M$37 -> 0.31196641
B32: Senior Notes | E32: =F32*$E$14 -> 19222.84 | F32: =N15 -> 2 | G32: =E32/$E$37 -> 0.19989601 | J32: Equity Payment | M32: =E18 -> 66114.2 | N32: =M32/$J$19 -> 6.878713 | O32: =M32/$M$37 -> 0.68751365
B33: Total Debt | E33: =E31+E32 -> 57668.52 | F33: =E33/E14 -> 6 | G33: =E33/$E$37 -> 0.59968803
J34: Fees and Expenses | M34: =E21 -> 50 | N34: =M34/$J$19 -> 0.0052021449 | O34: =M34/$M$37 -> 0.00051994401
B35: Sponsor Equity | E35: =E37-E33 -> 38495.68 | F35: =E35/J19 -> 4.0052021 | G35: =E35/$E$37 -> 0.40031197
B37: Total Sources | E37: =M37 -> 96164.2 | F37: =E37/J19 -> 10.005202 | G37: =E37/$E$37 -> 1 | J37: Total Uses | M37: =M31+M32+M34 -> 96164.2 | N37: =N31+N32+N34 -> 10.005202 | O37: =M37/$M$37 -> 1
B39: Financials | M39: Forcasted Years
B42: Operating Model | J42: Year 2025 | K42: Year 2026 | L42: Year 2027 | M42: Year 2028 | N42: Year 2029 | O42: Year 2030
B43: Revenue | J43: =J15 -> 50994.55 | K43: =J43*(1+K44) -> 54564.169 | L43: =K43*(1+L44) -> 58383.66 | M43: =L43*(1+M44) -> 62470.517 | N43: =M43*(1+N44) -> 66843.453 | O43: =N43*(1+O44) -> 71522.494
B44: % Growth | J44: - | K44: =$J$23 -> 0.07 | L44: =$J$23 -> 0.07 | M44: =$J$23 -> 0.07 | N44: =$J$23 -> 0.07 | O44: =$J$23 -> 0.07
B46: EBITDA | J46: =J19 -> 9611.42 | K46: =K47*K43 -> 10829.861 | L46: =L47*L43 -> 12171.788 | M46: =M47*M43 -> 13648.518 | N46: =N47*N43 -> 15272.349 | O46: =O47*O43 -> 17056.638
B47: % Sales | J47: =J46/J43 -> 0.18847936 | K47: =J47+$J$24 -> 0.19847936 | L47: =K47+$J$24 -> 0.20847936 | M47: =L47+$J$24 -> 0.21847936 | N47: =M47+$J$24 -> 0.22847936 | O47: =N47+$J$24 -> 0.23847936
B49: EBIT | J49: =J46-J64 -> 9197.19 | K49: =K46-K64 -> 10386.635 | L49: =L46-L64 -> 11697.536 | M49: =M46-M64 -> 13141.069 | N49: =N46-N64 -> 14729.378 | O49: =O46-O64 -> 16475.659
B50: %Sales | J50: =J49/J43 -> 0.18035633 | K50: =K49/K43 -> 0.19035633 | L50: =L49/L43 -> 0.20035633 | M50: =M49/M43 -> 0.21035633 | N50: =N49/N43 -> 0.22035633 | O50: =O49/O43 -> 0.23035633
B52: Interest | J52: - | K52: =K101 -> 4613.4816 | L52: =L101 -> 4219.9542 | M52: =M101 -> 3740.3661 | N52: =N101 -> 3164.2208 | O52: =O101 -> 2479.957
B54: EBT | J54: - | K54: =K49-K52 -> 5773.1534 | L54: =L49-L52 -> 7477.5818 | M54: =M49-M52 -> 9400.7026 | N54: =N49-N52 -> 11565.157 | O54: =O49-O52 -> 13995.702
B55: % sales | J55: - | K55: =K54/K43 -> 0.10580484 | L55: =L54/L43 -> 0.12807662 | M55: =M54/M43 -> 0.15048223 | N55: =N54/N43 -> 0.17301855 | O55: =O54/O43 -> 0.19568253
B57: Taxes | J57: - | K57: =K54*K58 -> 1443.2883 | L57: =L54*L58 -> 1869.3954 | M57: =M54*M58 -> 2350.1757 | N57: =N54*N58 -> 2891.2893 | O57: =O54*O58 -> 3498.9256
B58: % Tax Rate | J58: - | K58: =$J$25 -> 0.25 | L58: =$J$25 -> 0.25 | M58: =$J$25 -> 0.25 | N58: =$J$25 -> 0.25 | O58: =$J$25 -> 0.25
B60: Net Income | J60: - | K60: =K54-K57 -> 4329.865 | L60: =L54-L57 -> 5608.1863 | M60: =M54-M57 -> 7050.527 | N60: =N54-N57 -> 8673.868 | O60: =O54-O57 -> 10496.777
B61: % Sales | J61: - | K61: =K60/K43 -> 0.079353634 | L61: =L60/L43 -> 0.096057464 | M61: =M60/M43 -> 0.11286167 | N61: =N60/N43 -> 0.12976391 | O61: =O60/O43 -> 0.1467619
B63: Cash Row Items | J63: =J42 -> Year 2025 | K63: =K42 -> Year 2026 | L63: =L42 -> Year 2027 | M63: =M42 -> Year 2028 | N63: =N42 -> Year 2029 | O63: =O42 -> Year 2030
B64: D&A | J64: =J16 -> 414.23 | K64: =K65*K43 -> 443.2261 | L64: =L65*L43 -> 474.25193 | M64: =M65*M43 -> 507.44956 | N64: =N65*N43 -> 542.97103 | O64: =O65*O43 -> 580.979
B65: % sales | J65: =J64/J43 -> 0.0081230249 | K65: 0.0081230249 | L65: 0.0081230249 | M65: 0.0081230249 | N65: 0.0081230249 | O65: 0.0081230249
B67: Net Working Capital | J67: =J18 -> -12150.26 | K67: =K68*K43 -> -13000.778 | L67: =L68*L43 -> -13910.833 | M67: =M68*M43 -> -14884.591 | N67: =N68*N43 -> -15926.512 | O67: =O68*O43 -> -17041.368
B68: % Sales | J68: =J67/J43 -> -0.23826585 | K68: -0.23826585 | L68: -0.23826585 | M68: -0.23826585 | N68: -0.23826585 | O68: -0.23826585
B69: Change in working Capital | J69: - | K69: =K67-J67 -> -850.5182 | L69: =L67-K67 -> -910.05447 | M69: =M67-L67 -> -973.75829 | N69: =N67-M67 -> -1041.9214 | O69: =O67-N67 -> -1114.8559
B71: CapEx | J71: =J17 -> -874 | K71: =K72*K43 -> -935.18 | L71: =L72*L43 -> -1000.6426 | M71: =M72*M43 -> -1070.6876 | N71: =N72*N43 -> -1145.6357 | O71: =O72*O43 -> -1225.8302
B72: % of Sales | J72: =J71/J43 -> -0.017139086 | K72: -0.017139086 | L72: -0.017139086 | M72: -0.017139086 | N72: -0.017139086 | O72: -0.017139086
B74: Levered Cash Flow | J74: =J63 -> Year 2025 | K74: =K63 -> Year 2026 | L74: =L63 -> Year 2027 | M74: =M63 -> Year 2028 | N74: =N63 -> Year 2029 | O74: =O63 -> Year 2030
B75: Net Income | J75: - | K75: =K60 -> 4329.865 | L75: =L60 -> 5608.1863 | M75: =M60 -> 7050.527 | N75: =N60 -> 8673.868 | O75: =O60 -> 10496.777
B76: D&A | J76: - | K76: =K64 -> 443.2261 | L76: =L64 -> 474.25193 | M76: =M64 -> 507.44956 | N76: =N64 -> 542.97103 | O76: =O64 -> 580.979
B77: CapEx | J77: - | K77: =K71 -> -935.18 | L77: =L71 -> -1000.6426 | M77: =M71 -> -1070.6876 | N77: =N71 -> -1145.6357 | O77: =O71 -> -1225.8302
B78: Change in NWC | J78: - | K78: =K69 -> -850.5182 | L78: =L69 -> -910.05447 | M78: =M69 -> -973.75829 | N78: =N69 -> -1041.9214 | O78: =O69 -> -1114.8559
B79: Levered Cash Flow | J79: - | K79: =K75+K76-K77-K78 -> 6558.7893 | L79: =L75+L76-L77-L78 -> 7993.1353 | M79: =M75+M76-M77-M78 -> 9602.4224 | N79: =N75+N76-N77-N78 -> 11404.396 | O79: =O75+O76-O77-O78 -> 13418.442
B81: Debt Schedule
J83: =J74 -> Year 2025 | K83: =K74 -> Year 2026 | L83: =L74 -> Year 2027 | M83: =M74 -> Year 2028 | N83: =N74 -> Year 2029 | O83: =O74 -> Year 2030
B85: Bank Debt
B86: Beginning Bal. | J86: - | K86: =J90 -> 38445.68 | L86: =K90 -> 31886.891 | M86: =L90 -> 23893.755 | N86: =M90 -> 14291.333 | O86: =N90 -> 2886.9369
B87: Interest | J87: - | K87: =K86*$O$14 -> 2306.7408 | L87: =L86*$O$14 -> 1913.2134 | M87: =M86*$O$14 -> 1433.6253 | N87: =N86*$O$14 -> 857.47998 | O87: =O86*$O$14 -> 173.21621
B88: Paydown | J88: - | K88: =MIN(K79,K86) -> 6558.7893 | L88: =MIN(L79,L86) -> 7993.1353 | M88: =MIN(M79,M86) -> 9602.4224 | N88: =MIN(N79,N86) -> 11404.396 | O88: =MIN(O79,O86) -> 2886.9369
B90: Ending Bal. | J90: =E31 -> 38445.68 | K90: =K86-K88 -> 31886.891 | L90: =L86-L88 -> 23893.755 | M90: =M86-M88 -> 14291.333 | N90: =N86-N88 -> 2886.9369 | O90: =O86-O88 -> 0
B92: Sr. Notes
B93: Beginning Bal. | J93: - | K93: =J97 -> 19222.84 | L93: =K97 -> 19222.84 | M93: =L97 -> 19222.84 | N93: =M97 -> 19222.84 | O93: =N97 -> 19222.84
B94: Interest | J94: - | K94: =K93*$O$15 -> 2306.7408 | L94: =L93*$O$15 -> 2306.7408 | M94: =M93*$O$15 -> 2306.7408 | N94: =N93*$O$15 -> 2306.7408 | O94: =O93*$O$15 -> 2306.7408
B95: Paydown | J95: - | K95: =MIN(K79,K79-K88) -> 0 | L95: =MIN(L79,L79-L88) -> 0 | M95: =MIN(M79,M79-M88) -> 0 | N95: =MIN(N79,N79-N88) -> 0 | O95: =MIN(O79,O79-O88) -> 10531.505
B97: Ending Bal. | J97: =E32 -> 19222.84 | K97: =K93-K95 -> 19222.84 | L97: =L93-L95 -> 19222.84 | M97: =M93-M95 -> 19222.84 | N97: =N93-N95 -> 19222.84 | O97: =O93-O95 -> 8691.3349
B99: Total Debt
B100: Beginning Bal. | J100: - | K100: =K86+K93 -> 57668.52 | L100: =L86+L93 -> 51109.731 | M100: =M86+M93 -> 43116.595 | N100: =N86+N93 -> 33514.173 | O100: =O86+O93 -> 22109.777
B101: Interest | J101: - | K101: =K94+K87 -> 4613.4816 | L101: =L94+L87 -> 4219.9542 | M101: =M94+M87 -> 3740.3661 | N101: =N94+N87 -> 3164.2208 | O101: =O94+O87 -> 2479.957
B102: Paydown | J102: - | K102: =K94+K88 -> 8865.5301 | L102: =L94+L88 -> 10299.876 | M102: =M94+M88 -> 11909.163 | N102: =N94+N88 -> 13711.137 | O102: =O94+O88 -> 5193.6777
B104: Ending Bal. | J104: =J90+J97 -> 57668.52 | K104: =K90+K97 -> 51109.731 | L104: =L90+L97 -> 43116.595 | M104: =M90+M97 -> 33514.173 | N104: =N90+N97 -> 22109.777 | O104: =O90+O97 -> 8691.3349
B106: IRR
B108: EBITDA at Exit | O108: =O46 -> 17056.638
B109: Exit Multiple | O109: =E24 -> 10
B110: Enterprise Value | O110: =O108*O109 -> 170566.38
B111: Net Debt | O111: =O104 -> 8691.3349
B112: Sponsor Equity value | O112: =O110-O111 -> 161875.05
B114: Sponsor Equity at Entry | O114: =E35 -> 38495.68
B116: MOIC | O116: =O112/O114 -> 4.2050186
B117: IRR | O117: =O116^(1/5)-1 -> 0.33276501

Sheet M&A
G8: Accretion / Dilution Model
B10: Assumptions
B12: Acquirer | I12: Target
B13: Share Price | G13: 16300 | I13: Share Price | N13: 9110
B14: Diluted Shares Outstanding | G14: 314 | I14: % Offer Premium | N14: 0.25
B15: 2026E EPS | G15: 443 | I15: Offer Price | N15: =N13*(1+N14) -> 11387.5
B16: Share issued | G16: =N18/G13*G22 -> 64.906654 | I16: Dilluted Shares Outstanding | N16: 279
B18: For Ref. only | I18: Purchase price | N18: =N15*N16 -> 3177112.5
B19: Accretive / Dilutive | G19: =N64 -> 0.48669604 | I19: 2026 EPS | N19: ='Historical FS'!K45 -> 211.5819
B21: Consideration | I21: Financials
B22: % Stock | G22: 0.333 | I22: Tax Rate | N22: 0.25
B23: % Debt | G23: 0.333 | I23: Synergies | N23: 7500
B24: % Cash | G24: =1-SUM(G22:G23) -> 0.334 | I24: Interest on Cash | N24: 0.015
B26: Debt | I26: Assest Write Up
B27: Term | G27: 5 Years | I27: Book value of Target assests | N27: 1224
B28: Intrest Rate | G28: 0.07 | I28: Fair market value of target Assets | N28: =N13 -> 9110
B29: Annual Financing fee Amortization | G29: =M39/5 -> 20000 | I29: Assest Write Up | N29: =N28-N27 -> 7886
I30: Useful Life | N30: 15 Years
I31: Incremental D&A Expense | N31: =N29/15 -> 525.73333
B34: Sources and Uses
B36: Sources | I36: Uses
F37: Amount | G37: Capital % | M37: =F37 -> Amount | N37: =G37 -> Capital %
B38: Acqirer Stock issued | F38: =G16*G13 -> 1057978.5 | G38: =F38/$F$41 -> 0.31798698 | I38: Purchase price | M38: =N18 -> 3177112.5 | N38: =M38/$M$41 -> 0.95491586
B39: Net Debt | F39: =G23*N18 -> 1057978.5 | G39: =F39/$F$41 -> 0.31798698 | I39: Financing Fees | M39: 100000 | N39: =M39/$M$41 -> 0.030056092
B40: Cash (Purchase price + fees) | F40: =F41-(F38+F39) -> 1211155.6 | G40: =F40/$F$41 -> 0.36402604 | I40: Transaction fees | M40: 50000 | N40: =M40/$M$41 -> 0.015028046
B41: Total | F41: =M41 -> 3327112.5 | G41: =F41/$F$41 -> 1 | I41: Total | M41: =M38+M39+M40 -> 3327112.5 | N41: =M41/$M$41 -> 1
B43: Pro Forma Income Statement | L43: Acquirer | M43: Target | N43: Pro Forma
B45: Accretion / Dilution Analysis
B46: Standalone net Income | L46: =G15*G14 -> 139102 | M46: =N16*N19 -> 59031.349 | N46: =L46+M46 -> 198133.35
B47: Pre-Tax Income | L47: =L46/(1-N22) -> 185469.33 | M47: =M46/(1-N22) -> 78708.466 | N47: =L47+M47 -> 264177.8
B49: Pro Forma Pre Tax Income - Unadjusted
B50: Less: Interest Expense from Net Debt | N50: =F39*G28 -> 74058.492
B51: Less: Forgone Interest on cash | N51: =F40*N24 -> 18167.334
B52: Less: Incremental D&A expense | N52: =N31 -> 525.73333
B53: Less: Deal Fees | N53: =M40 -> 50000
B54: Less: Financing Fees Amortization | N54: =G29 -> 20000
B55: Plus: Synergies | N55: =N23 -> 7500
B56: Pro Forma Pre Tax Income - Adjusted | N56: =(N47+N55)-SUM(N50:N54) -> 108926.24
B58: Pro Forma Net Income | N58: =N56*(1-N22) -> 81694.68
B59: Pro Forma Shares | N59: =G14+G16 -> 378.90665
B61: Pro Forma EPS | N61: =N58/N59 -> 215.60635
B62: Acquirer Standalone EPS | N62: =G15 -> 443
B63: Accretion / Dilution per Share | N63: =N61-N62 -> -227.39365
B64: Accretion / Dilution % | N64: =N61/N62 -> 0.48669604
B66: Return on Equity(ROE) | C66: Return on Equity(ROE) | D66: Return on Equity(ROE) | E66: Return on Equity(ROE) | F66: Return on Equity(ROE) | G66: Return on Equity(ROE) | H66: Return on Equity(ROE) | I66: Return on Equity(ROE) | J66: Return on Equity(ROE) | K66: Return on Equity(ROE) | L66: Return on Equity(ROE) | M66: Return on Equity(ROE) | N66: Return on Equity(ROE)
